Workbook

Sheet SUMMARY
B1: In-House Wood Control
B3: Conclusion
B4: ="1. Wood received: "&TEXT(F17,"0.00")&" m³, Rp "&TEXT(F18,"#,##0")&"." -> 1. Wood received: 227.34 m³, Rp 1,512,843,233.
B5: ="2. Wood inventory: Rp "&TEXT(F42,"#,##0")&", consisting of board stock and WIP in-house. Shipped to Plant 1: Rp "&TEXT(F45,"#,##0")&"." -> 2. Wood inventory: Rp 279,614,925, consisting of board stock and WIP in-house. Shipped to Plant 1: Rp 1,233,228,308.
B6: ="3. Wood used per chair: "&TEXT(F35,"0.0000")&" m³ against a benchmark of "&TEXT(F36,"0.0000")&" m³. Wood cost per chair: Rp "&TEXT(F37,"#,##0")&"." -> 3. Wood used per chair: 0.0493 m³ against a benchmark of 0.0500 m³. Wood cost per chair: Rp 328,510.
B7: =_xlfn.LET(_xlpm.t,SUMIFS(OUT!$F$14:$F$5084,OUT!$L$14:$L$5084,"Adjustment"),_xlpm.p,SUMIFS(OUT!$O$14:$O$5084,OUT!$L$14:$L$5084,"Adjustment",OUT!$B$14:$B$5084,"<"&'OUT Since Sep'!$B$1)+SUMIFS(OUT!$F$14:$F$5084,OUT!$P$14:$P$5084,"Explained",OUT!$N$14:$N$5084,"",OUT!$B$14:$B$5084,"<"&'OUT Since Sep'!$B$1),"4. Stock adjustment without a usage record: "&TEXT(_xlpm.t,"0.00")&" m³ ("&TEXT(_xlpm.t/F26,"0%")&" of wood used). Before Sep (Edy era, missed records): "&TEXT(_xlpm.p,"0.00")&" m³. Since Sep: "&TEXT(_xlpm.t-_xlpm.p,"0.00")&" m³. "&IF(F35<=F36,"Wood used per chair is within benchmark, so the adjustment is accepted, but its use in production or as scrap cannot be verified.","Wood used per chair is above benchmark, and the use of the adjustment in production or as scrap cannot be verified.")) -> 4. Stock adjustment without a usage record: 28.81 m³ (14% of wood used). Before Sep (Edy era, missed records): 28.61 m³. Since Sep: 0.20 m³. Wood used per chair is within benchmark, so the adjustment is accepted, but its use in production or as scrap cannot be verified.
B8: ="5. Without a BoM per product, overuse on individual products or MOs cannot be identified, even when the overall average is within benchmark." -> 5. Without a BoM per product, overuse on individual products or MOs cannot be identified, even when the overall average is within benchmark.
B9: ="6. Required: a complete record of every wood issue, and a BoM per product." -> 6. Required: a complete record of every wood issue, and a BoM per product.
B11: Input | G11: Basis
B12: Wood benchmark per chair (m³) | C12: 0.05 | G12: Assumption
B13: Seater-only counted as (chair) | C13: 0.1 | G13: Assumption
B15: Description | C15: Teak | D15: Sungkai | E15: Pine | F15: Total | G15: Basis | J15: Zero check
B16: 1. Wood received
B17: Volume (m³) | C17: =SUMIFS(IN!$G$2:$G$5001,IN!$D$2:$D$5001,"Teak",IN!$J$2:$J$5001,"Received") -> 148.16234 | D17: =SUMIFS(IN!$G$2:$G$5001,IN!$D$2:$D$5001,"Sungkai",IN!$J$2:$J$5001,"Received") -> 78.193031 | E17: =SUMIFS(IN!$G$2:$G$5001,IN!$D$2:$D$5001,"Pine",IN!$J$2:$J$5001,"Received") -> 0.9839 | F17: =SUM(C17:E17) -> 227.33927 | G17: Data | J17: =ROUND(F17-SUMIFS(IN!$G$2:$G$5001,IN!$J$2:$J$5001,"Received"),6) -> 0
B18: Value (Rp) | C18: =SUMIFS(IN!$H$2:$H$5001,IN!$D$2:$D$5001,"Teak",IN!$J$2:$J$5001,"Received") -> 1.1146335e+09 | D18: =SUMIFS(IN!$H$2:$H$5001,IN!$D$2:$D$5001,"Sungkai",IN!$J$2:$J$5001,"Received") -> 3.9515967e+08 | E18: =SUMIFS(IN!$H$2:$H$5001,IN!$D$2:$D$5001,"Pine",IN!$J$2:$J$5001,"Received") -> 3050090 | F18: =SUM(C18:E18) -> 1.5128432e+09 | G18: Data | J18: =ROUND(F18-SUMIFS(IN!$H$2:$H$5001,IN!$J$2:$J$5001,"Received"),0) -> 0
B19: Average price per m³ (Rp) | C19: =IF(C17=0,0,C18/C17) -> 7523055.5 | D19: =IF(D17=0,0,D18/D17) -> 5053643.1 | E19: =IF(E17=0,0,E18/E17) -> 3100000 | F19: =IF(F17=0,0,F18/F17) -> 6654561.9 | G19: Calculated
B21: 2. Board stock (book)
B22: Volume (m³) | C22: =SUMIFS(STOK!$M$5:$M$5002,STOK!$A$5:$A$5002,"Teak") -> 16.12396 | D22: =SUMIFS(STOK!$M$5:$M$5002,STOK!$A$5:$A$5002,"Sungkai") -> 9.930121 | E22: =SUMIFS(STOK!$M$5:$M$5002,STOK!$A$5:$A$5002,"Pine") -> 0.12218 | F22: =SUM(C22:E22) -> 26.176261 | G22: Calculated | J22: =ROUND(F22-STOK!$M$32,6) -> 0
B23: Value (Rp) | C23: =C22*C19 -> 1.2130145e+08 | D23: =D22*D19 -> 50183287 | E23: =E22*E19 -> 378758 | F23: =SUM(C23:E23) -> 1.7186349e+08 | G23: Calculated | J23: =ROUND(F23-SUMPRODUCT(C22:E22,C19:E19),0) -> 0
B25: 3. Wood used
B26: Volume (m³) | C26: =C17-C22 -> 132.03838 | D26: =D17-D22 -> 68.26291 | E26: =E17-E22 -> 0.86172 | F26: =SUM(C26:E26) -> 201.16301 | G26: Calculated | J26: =ROUND(F26-SUM(OUT!$F$14:$F$5084),6) -> 0
B27: Value (Rp) | C27: =C18-C23 -> 9.9333203e+08 | D27: =D18-D23 -> 3.4497638e+08 | E27: =E18-E23 -> 2671332 | F27: =SUM(C27:E27) -> 1.3409797e+09 | G27: Calculated | J27: =ROUND(F27-(F18-F23),0) -> 0
B29: 4. Chairs
B30: Chairs cut | C30: =SUMIFS(REALDATA!$O$2:$O$1048576,REALDATA!$K$2:$K$1048576,"Teak") -> 3106 | D30: =SUMIFS(REALDATA!$O$2:$O$1048576,REALDATA!$K$2:$K$1048576,"Sungkai") -> 961 | E30: =SUMIFS(REALDATA!$O$2:$O$1048576,REALDATA!$K$2:$K$1048576,"Pinus") -> 15 | F30: =SUM(C30:E30) -> 4082 | G30: Calculated | J30: =ROUND(F30-SUM(REALDATA!$O$2:$O$1048576),6) -> 0
B31: Shipped to Plant 1 | C31: =SUMIFS(REALDATA!$V$2:$V$1048576,REALDATA!$K$2:$K$1048576,"Teak") -> 2811 | D31: =SUMIFS(REALDATA!$V$2:$V$1048576,REALDATA!$K$2:$K$1048576,"Sungkai") -> 943 | E31: =SUMIFS(REALDATA!$V$2:$V$1048576,REALDATA!$K$2:$K$1048576,"Pinus") -> 0 | F31: =SUM(C31:E31) -> 3754 | G31: Calculated | J31: =ROUND(F31-SUM(REALDATA!$V$2:$V$1048576),6) -> 0
B32: WIP in-house | C32: =C30-C31 -> 295 | D32: =D30-D31 -> 18 | E32: =E30-E31 -> 15 | F32: =SUM(C32:E32) -> 328 | G32: Calculated | J32: =ROUND(F32-(F30-F31),6) -> 0
B34: 5. Per chair
B35: Wood used per chair (m³) | F35: =IF(F30=0,0,F26/F30) -> 0.049280501 | G35: Calculated
B36: Benchmark per chair (m³) | F36: =$C$12 -> 0.05 | G36: Assumption
B37: Wood cost per chair (Rp) | F37: =IF(F30=0,0,F27/F30) -> 328510.47 | G37: Calculated
B39: 6. Wood inventory (Rp)
B40: Board stock | F40: =F23 -> 1.7186349e+08 | G40: Calculated
B41: WIP in-house | F41: =F32*F37 -> 1.0775143e+08 | G41: Calculated
B42: Total wood inventory | F42: =F40+F41 -> 2.7961493e+08 | G42: Calculated | J42: =ROUND(F42-(F40+F41),0) -> 0
B44: 7. Shipped to Plant 1 (Rp)
B45: Shipped to Plant 1 | F45: =F27-F41 -> 1.2332283e+09 | G45: Calculated | J45: =ROUND(F45+F42-F18,0) -> 0
B47: 8. Wood stock as of 24 Oct (m³)
B48: Thickness (cm) | C48: Teak | D48: Sungkai | E48: Pine | F48: Total
B49: 2 | C49: =SUMIFS(STOK!$M$5:$M$29,STOK!$A$5:$A$29,C$48,STOK!$B$5:$B$29,$B49) -> 0.00736 | D49: =SUMIFS(STOK!$M$5:$M$29,STOK!$A$5:$A$29,D$48,STOK!$B$5:$B$29,$B49) -> 0 | E49: =SUMIFS(STOK!$M$5:$M$29,STOK!$A$5:$A$29,E$48,STOK!$B$5:$B$29,$B49) -> 0 | F49: =SUM(C49:E49) -> 0.00736
B50: 2.5 | C50: =SUMIFS(STOK!$M$5:$M$29,STOK!$A$5:$A$29,C$48,STOK!$B$5:$B$29,$B50) -> 0 | D50: =SUMIFS(STOK!$M$5:$M$29,STOK!$A$5:$A$29,D$48,STOK!$B$5:$B$29,$B50) -> 0.078225 | E50: =SUMIFS(STOK!$M$5:$M$29,STOK!$A$5:$A$29,E$48,STOK!$B$5:$B$29,$B50) -> 0.034505 | F50: =SUM(C50:E50) -> 0.11273
B51: 3 | C51: =SUMIFS(STOK!$M$5:$M$29,STOK!$A$5:$A$29,C$48,STOK!$B$5:$B$29,$B51) -> -0.009 | D51: =SUMIFS(STOK!$M$5:$M$29,STOK!$A$5:$A$29,D$48,STOK!$B$5:$B$29,$B51) -> 1.387281 | E51: =SUMIFS(STOK!$M$5:$M$29,STOK!$A$5:$A$29,E$48,STOK!$B$5:$B$29,$B51) -> 0 | F51: =SUM(C51:E51) -> 1.378281
B52: 3.5 | C52: =SUMIFS(STOK!$M$5:$M$29,STOK!$A$5:$A$29,C$48,STOK!$B$5:$B$29,$B52) -> 2.25351 | D52: =SUMIFS(STOK!$M$5:$M$29,STOK!$A$5:$A$29,D$48,STOK!$B$5:$B$29,$B52) -> 2.609775 | E52: =SUMIFS(STOK!$M$5:$M$29,STOK!$A$5:$A$29,E$48,STOK!$B$5:$B$29,$B52) -> 0.087675 | F52: =SUM(C52:E52) -> 4.95096
B53: 4 | C53: =SUMIFS(STOK!$M$5:$M$29,STOK!$A$5:$A$29,C$48,STOK!$B$5:$B$29,$B53) -> 0.0144 | D53: =SUMIFS(STOK!$M$5:$M$29,STOK!$A$5:$A$29,D$48,STOK!$B$5:$B$29,$B53) -> 0.08876 | E53: =SUMIFS(STOK!$M$5:$M$29,STOK!$A$5:$A$29,E$48,STOK!$B$5:$B$29,$B53) -> 0 | F53: =SUM(C53:E53) -> 0.10316
B54: 4.5 | C54: =SUMIFS(STOK!$M$5:$M$29,STOK!$A$5:$A$29,C$48,STOK!$B$5:$B$29,$B54) -> 0.73584 | D54: =SUMIFS(STOK!$M$5:$M$29,STOK!$A$5:$A$29,D$48,STOK!$B$5:$B$29,$B54) -> 0.00567 | E54: =SUMIFS(STOK!$M$5:$M$29,STOK!$A$5:$A$29,E$48,STOK!$B$5:$B$29,$B54) -> 0 | F54: =SUM(C54:E54) -> 0.74151
B55: 5 | C55: =SUMIFS(STOK!$M$5:$M$29,STOK!$A$5:$A$29,C$48,STOK!$B$5:$B$29,$B55) -> 0 | D55: =SUMIFS(STOK!$M$5:$M$29,STOK!$A$5:$A$29,D$48,STOK!$B$5:$B$29,$B55) -> 0.074655 | E55: =SUMIFS(STOK!$M$5:$M$29,STOK!$A$5:$A$29,E$48,STOK!$B$5:$B$29,$B55) -> 0 | F55: =SUM(C55:E55) -> 0.074655
B56: 5.5 | C56: =SUMIFS(STOK!$M$5:$M$29,STOK!$A$5:$A$29,C$48,STOK!$B$5:$B$29,$B56) -> 0 | D56: =SUMIFS(STOK!$M$5:$M$29,STOK!$A$5:$A$29,D$48,STOK!$B$5:$B$29,$B56) -> 0.10505 | E56: =SUMIFS(STOK!$M$5:$M$29,STOK!$A$5:$A$29,E$48,STOK!$B$5:$B$29,$B56) -> 0 | F56: =SUM(C56:E56) -> 0.10505
B57: 6 | C57: =SUMIFS(STOK!$M$5:$M$29,STOK!$A$5:$A$29,C$48,STOK!$B$5:$B$29,$B57) -> 4.53924 | D57: =SUMIFS(STOK!$M$5:$M$29,STOK!$A$5:$A$29,D$48,STOK!$B$5:$B$29,$B57) -> 0 | E57: =SUMIFS(STOK!$M$5:$M$29,STOK!$A$5:$A$29,E$48,STOK!$B$5:$B$29,$B57) -> 0 | F57: =SUM(C57:E57) -> 4.53924
B58: 7 | C58: =SUMIFS(STOK!$M$5:$M$29,STOK!$A$5:$A$29,C$48,STOK!$B$5:$B$29,$B58) -> 6.21733 | D58: =SUMIFS(STOK!$M$5:$M$29,STOK!$A$5:$A$29,D$48,STOK!$B$5:$B$29,$B58) -> 0 | E58: =SUMIFS(STOK!$M$5:$M$29,STOK!$A$5:$A$29,E$48,STOK!$B$5:$B$29,$B58) -> 0 | F58: =SUM(C58:E58) -> 6.21733
B59: 7.5 | C59: =SUMIFS(STOK!$M$5:$M$29,STOK!$A$5:$A$29,C$48,STOK!$B$5:$B$29,$B59) -> 0 | D59: =SUMIFS(STOK!$M$5:$M$29,STOK!$A$5:$A$29,D$48,STOK!$B$5:$B$29,$B59) -> 2.037825 | E59: =SUMIFS(STOK!$M$5:$M$29,STOK!$A$5:$A$29,E$48,STOK!$B$5:$B$29,$B59) -> 0 | F59: =SUM(C59:E59) -> 2.037825
B60: 8 | C60: =SUMIFS(STOK!$M$5:$M$29,STOK!$A$5:$A$29,C$48,STOK!$B$5:$B$29,$B60) -> 2.36528 | D60: =SUMIFS(STOK!$M$5:$M$29,STOK!$A$5:$A$29,D$48,STOK!$B$5:$B$29,$B60) -> 3.54288 | E60: =SUMIFS(STOK!$M$5:$M$29,STOK!$A$5:$A$29,E$48,STOK!$B$5:$B$29,$B60) -> 0 | F60: =SUM(C60:E60) -> 5.90816
B61: Total | C61: =SUM(C49:C60) -> 16.12396 | D61: =SUM(D49:D60) -> 9.930121 | E61: =SUM(E49:E60) -> 0.12218 | F61: =SUM(F49:F60) -> 26.176261 | J61: =ROUND(F61-STOK!M32,6) -> 0

Sheet STOK
A1: Board Stock by Thickness
A2: ="As of "&TEXT(MAX(OUT!$B$14:$B$5084),"dd-mmm-yyyy") -> As of 24-Oct-2026
A3: Wood Type | B3: Thickness (cm) | C3: Mov. From | D3: Opening Count 14-Oct-2026 | F3: In | H3: Out | J3: Adj | L3: Book Balance | N3: Notes | O3: Latest Count Date | P3: Latest Count | R3: Variance (Book − Count)
D4: pcs | E4: m³ | F4: pcs | G4: m³ | H4: pcs | I4: m³ | J4: pcs | K4: m³ | L4: pcs | M4: m³ | P4: pcs | Q4: m³ | R4: pcs | S4: m³
A5: Teak | B5: 2 | C5: 46310 | D5: =SUMIFS('OPNAME LOG'!$D$2:$D$1000,'OPNAME LOG'!$A$2:$A$1000,DATE(2026,10,14),'OPNAME LOG'!$B$2:$B$1000,IF($A5="Teak","Jati",IF($A5="Pine","Pinus",$A5)),'OPNAME LOG'!$C$2:$C$1000,$B5)+SUMIFS('OPNAME LOG'!$D$2:$D$1000,'OPNAME LOG'!$A$2:$A$1000,DATE(2026,10,14),'OPNAME LOG'!$B$2:$B$1000,IF($A5="Teak","Jati",IF($A5="Pine","Pinus",$A5)),'OPNAME LOG'!$C$2:$C$1000,$B5&" (Grade A)") -> 6 | E5: =SUMIFS('OPNAME LOG'!$E$2:$E$1000,'OPNAME LOG'!$A$2:$A$1000,DATE(2026,10,14),'OPNAME LOG'!$B$2:$B$1000,IF($A5="Teak","Jati",IF($A5="Pine","Pinus",$A5)),'OPNAME LOG'!$C$2:$C$1000,$B5)+SUMIFS('OPNAME LOG'!$E$2:$E$1000,'OPNAME LOG'!$A$2:$A$1000,DATE(2026,10,14),'OPNAME LOG'!$B$2:$B$1000,IF($A5="Teak","Jati",IF($A5="Pine","Pinus",$A5)),'OPNAME LOG'!$C$2:$C$1000,$B5&" (Grade A)") -> 0.02136 | F5: =SUMIFS(INCOMING!$E$2:$E$5000,INCOMING!$C$2:$C$5000,$A5,INCOMING!$D$2:$D$5000,$B5,INCOMING!$B$2:$B$5000,">="&$C5) -> 0 | G5: =SUMIFS(INCOMING!$F$2:$F$5000,INCOMING!$C$2:$C$5000,$A5,INCOMING!$D$2:$D$5000,$B5,INCOMING!$B$2:$B$5000,">="&$C5) -> 0 | H5: =SUMIFS(OUT!$E$14:$E$5084,OUT!$C$14:$C$5084,$A5,OUT!$D$14:$D$5084,$B5,OUT!$B$14:$B$5084,">="&$C5,OUT!$L$14:$L$5084,"<>Adjustment") -> 2 | I5: =SUMIFS(OUT!$F$14:$F$5084,OUT!$C$14:$C$5084,$A5,OUT!$D$14:$D$5084,$B5,OUT!$B$14:$B$5084,">="&$C5,OUT!$L$14:$L$5084,"<>Adjustment") -> 0.014 | J5: =SUMIFS(OUT!$E$14:$E$5084,OUT!$C$14:$C$5084,$A5,OUT!$D$14:$D$5084,$B5,OUT!$B$14:$B$5084,">="&$C5,OUT!$L$14:$L$5084,"Adjustment") -> 0 | K5: =SUMIFS(OUT!$F$14:$F$5084,OUT!$C$14:$C$5084,$A5,OUT!$D$14:$D$5084,$B5,OUT!$B$14:$B$5084,">="&$C5,OUT!$L$14:$L$5084,"Adjustment") -> 0 | L5: =D5+F5-H5-J5 -> 4 | M5: =E5+G5-I5-K5 -> 0.00736 | O5: =_xlfn.MAXIFS('OPNAME LOG'!$A$2:$A$1000,'OPNAME LOG'!$B$2:$B$1000,IF($A5="Teak","Jati",IF($A5="Pine","Pinus",$A5)),'OPNAME LOG'!$C$2:$C$1000,$B5) -> 46319 | P5: =SUMIFS('OPNAME LOG'!$D$2:$D$1000,'OPNAME LOG'!$A$2:$A$1000,$O5,'OPNAME LOG'!$B$2:$B$1000,IF($A5="Teak","Jati",IF($A5="Pine","Pinus",$A5)),'OPNAME LOG'!$C$2:$C$1000,$B5)+SUMIFS('OPNAME LOG'!$D$2:$D$1000,'OPNAME LOG'!$A$2:$A$1000,$O5,'OPNAME LOG'!$B$2:$B$1000,IF($A5="Teak","Jati",IF($A5="Pine","Pinus",$A5)),'OPNAME LOG'!$C$2:$C$1000,$B5&" (Grade A)") -> 3.9808 | Q5: =SUMIFS('OPNAME LOG'!$E$2:$E$1000,'OPNAME LOG'!$A$2:$A$1000,$O5,'OPNAME LOG'!$B$2:$B$1000,IF($A5="Teak","Jati",IF($A5="Pine","Pinus",$A5)),'OPNAME LOG'!$C$2:$C$1000,$B5)+SUMIFS('OPNAME LOG'!$E$2:$E$1000,'OPNAME LOG'!$A$2:$A$1000,$O5,'OPNAME LOG'!$B$2:$B$1000,IF($A5="Teak","Jati",IF($A5="Pine","Pinus",$A5)),'OPNAME LOG'!$C$2:$C$1000,$B5&" (Grade A)") -> 0.00736 | R5: =ROUND(L5-P5,6) -> 0.0192 | S5: =ROUND(M5-Q5,6) -> 0
A6: Teak | B6: 3 | C6: 46310 | D6: =SUMIFS('OPNAME LOG'!$D$2:$D$1000,'OPNAME LOG'!$A$2:$A$1000,DATE(2026,10,14),'OPNAME LOG'!$B$2:$B$1000,IF($A6="Teak","Jati",IF($A6="Pine","Pinus",$A6)),'OPNAME LOG'!$C$2:$C$1000,$B6)+SUMIFS('OPNAME LOG'!$D$2:$D$1000,'OPNAME LOG'!$A$2:$A$1000,DATE(2026,10,14),'OPNAME LOG'!$B$2:$B$1000,IF($A6="Teak","Jati",IF($A6="Pine","Pinus",$A6)),'OPNAME LOG'!$C$2:$C$1000,$B6&" (Grade A)") -> 1 | E6: =SUMIFS('OPNAME LOG'!$E$2:$E$1000,'OPNAME LOG'!$A$2:$A$1000,DATE(2026,10,14),'OPNAME LOG'!$B$2:$B$1000,IF($A6="Teak","Jati",IF($A6="Pine","Pinus",$A6)),'OPNAME LOG'!$C$2:$C$1000,$B6)+SUMIFS('OPNAME LOG'!$E$2:$E$1000,'OPNAME LOG'!$A$2:$A$1000,DATE(2026,10,14),'OPNAME LOG'!$B$2:$B$1000,IF($A6="Teak","Jati",IF($A6="Pine","Pinus",$A6)),'OPNAME LOG'!$C$2:$C$1000,$B6&" (Grade A)") -> 0.0102 | F6: =SUMIFS(INCOMING!$E$2:$E$5000,INCOMING!$C$2:$C$5000,$A6,INCOMING!$D$2:$D$5000,$B6,INCOMING!$B$2:$B$5000,">="&$C6) -> 0 | G6: =SUMIFS(INCOMING!$F$2:$F$5000,INCOMING!$C$2:$C$5000,$A6,INCOMING!$D$2:$D$5000,$B6,INCOMING!$B$2:$B$5000,">="&$C6) -> 0 | H6: =SUMIFS(OUT!$E$14:$E$5084,OUT!$C$14:$C$5084,$A6,OUT!$D$14:$D$5084,$B6,OUT!$B$14:$B$5084,">="&$C6,OUT!$L$14:$L$5084,"<>Adjustment") -> 2 | I6: =SUMIFS(OUT!$F$14:$F$5084,OUT!$C$14:$C$5084,$A6,OUT!$D$14:$D$5084,$B6,OUT!$B$14:$B$5084,">="&$C6,OUT!$L$14:$L$5084,"<>Adjustment") -> 0.0192 | J6: =SUMIFS(OUT!$E$14:$E$5084,OUT!$C$14:$C$5084,$A6,OUT!$D$14:$D$5084,$B6,OUT!$B$14:$B$5084,">="&$C6,OUT!$L$14:$L$5084,"Adjustment") -> 0 | K6: =SUMIFS(OUT!$F$14:$F$5084,OUT!$C$14:$C$5084,$A6,OUT!$D$14:$D$5084,$B6,OUT!$B$14:$B$5084,">="&$C6,OUT!$L$14:$L$5084,"Adjustment") -> 0 | L6: =D6+F6-H6-J6 -> -1 | M6: =E6+G6-I6-K6 -> -0.009 | O6: =_xlfn.MAXIFS('OPNAME LOG'!$A$2:$A$1000,'OPNAME LOG'!$B$2:$B$1000,IF($A6="Teak","Jati",IF($A6="Pine","Pinus",$A6)),'OPNAME LOG'!$C$2:$C$1000,$B6) -> 46319 | P6: =SUMIFS('OPNAME LOG'!$D$2:$D$1000,'OPNAME LOG'!$A$2:$A$1000,$O6,'OPNAME LOG'!$B$2:$B$1000,IF($A6="Teak","Jati",IF($A6="Pine","Pinus",$A6)),'OPNAME LOG'!$C$2:$C$1000,$B6)+SUMIFS('OPNAME LOG'!$D$2:$D$1000,'OPNAME LOG'!$A$2:$A$1000,$O6,'OPNAME LOG'!$B$2:$B$1000,IF($A6="Teak","Jati",IF($A6="Pine","Pinus",$A6)),'OPNAME LOG'!$C$2:$C$1000,$B6&" (Grade A)") -> 1 | Q6: =SUMIFS('OPNAME LOG'!$E$2:$E$1000,'OPNAME LOG'!$A$2:$A$1000,$O6,'OPNAME LOG'!$B$2:$B$1000,IF($A6="Teak","Jati",IF($A6="Pine","Pinus",$A6)),'OPNAME LOG'!$C$2:$C$1000,$B6)+SUMIFS('OPNAME LOG'!$E$2:$E$1000,'OPNAME LOG'!$A$2:$A$1000,$O6,'OPNAME LOG'!$B$2:$B$1000,IF($A6="Teak","Jati",IF($A6="Pine","Pinus",$A6)),'OPNAME LOG'!$C$2:$C$1000,$B6&" (Grade A)") -> 0.0102 | R6: =ROUND(L6-P6,6) -> -2 | S6: =ROUND(M6-Q6,6) -> -0.0192
A7: Teak | B7: 3.5 | C7: 46310 | D7: =SUMIFS('OPNAME LOG'!$D$2:$D$1000,'OPNAME LOG'!$A$2:$A$1000,DATE(2026,10,14),'OPNAME LOG'!$B$2:$B$1000,IF($A7="Teak","Jati",IF($A7="Pine","Pinus",$A7)),'OPNAME LOG'!$C$2:$C$1000,$B7)+SUMIFS('OPNAME LOG'!$D$2:$D$1000,'OPNAME LOG'!$A$2:$A$1000,DATE(2026,10,14),'OPNAME LOG'!$B$2:$B$1000,IF($A7="Teak","Jati",IF($A7="Pine","Pinus",$A7)),'OPNAME LOG'!$C$2:$C$1000,$B7&" (Grade A)") -> 99 | E7: =SUMIFS('OPNAME LOG'!$E$2:$E$1000,'OPNAME LOG'!$A$2:$A$1000,DATE(2026,10,14),'OPNAME LOG'!$B$2:$B$1000,IF($A7="Teak","Jati",IF($A7="Pine","Pinus",$A7)),'OPNAME LOG'!$C$2:$C$1000,$B7)+SUMIFS('OPNAME LOG'!$E$2:$E$1000,'OPNAME LOG'!$A$2:$A$1000,DATE(2026,10,14),'OPNAME LOG'!$B$2:$B$1000,IF($A7="Teak","Jati",IF($A7="Pine","Pinus",$A7)),'OPNAME LOG'!$C$2:$C$1000,$B7&" (Grade A)") -> 1.039465 | F7: =SUMIFS(INCOMING!$E$2:$E$5000,INCOMING!$C$2:$C$5000,$A7,INCOMING!$D$2:$D$5000,$B7,INCOMING!$B$2:$B$5000,">="&$C7) -> 316 | G7: =SUMIFS(INCOMING!$F$2:$F$5000,INCOMING!$C$2:$C$5000,$A7,INCOMING!$D$2:$D$5000,$B7,INCOMING!$B$2:$B$5000,">="&$C7) -> 2.95407 | H7: =SUMIFS(OUT!$E$14:$E$5084,OUT!$C$14:$C$5084,$A7,OUT!$D$14:$D$5084,$B7,OUT!$B$14:$B$5084,">="&$C7,OUT!$L$14:$L$5084,"<>Adjustment") -> 173 | I7: =SUMIFS(OUT!$F$14:$F$5084,OUT!$C$14:$C$5084,$A7,OUT!$D$14:$D$5084,$B7,OUT!$B$14:$B$5084,">="&$C7,OUT!$L$14:$L$5084,"<>Adjustment") -> 1.740025 | J7: =SUMIFS(OUT!$E$14:$E$5084,OUT!$C$14:$C$5084,$A7,OUT!$D$14:$D$5084,$B7,OUT!$B$14:$B$5084,">="&$C7,OUT!$L$14:$L$5084,"Adjustment") -> 0 | K7: =SUMIFS(OUT!$F$14:$F$5084,OUT!$C$14:$C$5084,$A7,OUT!$D$14:$D$5084,$B7,OUT!$B$14:$B$5084,">="&$C7,OUT!$L$14:$L$5084,"Adjustment") -> 0 | L7: =D7+F7-H7-J7 -> 242 | M7: =E7+G7-I7-K7 -> 2.25351 | O7: =_xlfn.MAXIFS('OPNAME LOG'!$A$2:$A$1000,'OPNAME LOG'!$B$2:$B$1000,IF($A7="Teak","Jati",IF($A7="Pine","Pinus",$A7)),'OPNAME LOG'!$C$2:$C$1000,$B7) -> 46319 | P7: =SUMIFS('OPNAME LOG'!$D$2:$D$1000,'OPNAME LOG'!$A$2:$A$1000,$O7,'OPNAME LOG'!$B$2:$B$1000,IF($A7="Teak","Jati",IF($A7="Pine","Pinus",$A7)),'OPNAME LOG'!$C$2:$C$1000,$B7)+SUMIFS('OPNAME LOG'!$D$2:$D$1000,'OPNAME LOG'!$A$2:$A$1000,$O7,'OPNAME LOG'!$B$2:$B$1000,IF($A7="Teak","Jati",IF($A7="Pine","Pinus",$A7)),'OPNAME LOG'!$C$2:$C$1000,$B7&" (Grade A)") -> 242 | Q7: =SUMIFS('OPNAME LOG'!$E$2:$E$1000,'OPNAME LOG'!$A$2:$A$1000,$O7,'OPNAME LOG'!$B$2:$B$1000,IF($A7="Teak","Jati",IF($A7="Pine","Pinus",$A7)),'OPNAME LOG'!$C$2:$C$1000,$B7)+SUMIFS('OPNAME LOG'!$E$2:$E$1000,'OPNAME LOG'!$A$2:$A$1000,$O7,'OPNAME LOG'!$B$2:$B$1000,IF($A7="Teak","Jati",IF($A7="Pine","Pinus",$A7)),'OPNAME LOG'!$C$2:$C$1000,$B7&" (Grade A)") -> 2.13171 | R7: =ROUND(L7-P7,6) -> 0 | S7: =ROUND(M7-Q7,6) -> 0.1218
A8: Teak | B8: 4 | C8: 46310 | D8: =SUMIFS('OPNAME LOG'!$D$2:$D$1000,'OPNAME LOG'!$A$2:$A$1000,DATE(2026,10,14),'OPNAME LOG'!$B$2:$B$1000,IF($A8="Teak","Jati",IF($A8="Pine","Pinus",$A8)),'OPNAME LOG'!$C$2:$C$1000,$B8)+SUMIFS('OPNAME LOG'!$D$2:$D$1000,'OPNAME LOG'!$A$2:$A$1000,DATE(2026,10,14),'OPNAME LOG'!$B$2:$B$1000,IF($A8="Teak","Jati",IF($A8="Pine","Pinus",$A8)),'OPNAME LOG'!$C$2:$C$1000,$B8&" (Grade A)") -> 1 | E8: =SUMIFS('OPNAME LOG'!$E$2:$E$1000,'OPNAME LOG'!$A$2:$A$1000,DATE(2026,10,14),'OPNAME LOG'!$B$2:$B$1000,IF($A8="Teak","Jati",IF($A8="Pine","Pinus",$A8)),'OPNAME LOG'!$C$2:$C$1000,$B8)+SUMIFS('OPNAME LOG'!$E$2:$E$1000,'OPNAME LOG'!$A$2:$A$1000,DATE(2026,10,14),'OPNAME LOG'!$B$2:$B$1000,IF($A8="Teak","Jati",IF($A8="Pine","Pinus",$A8)),'OPNAME LOG'!$C$2:$C$1000,$B8&" (Grade A)") -> 0.0144 | F8: =SUMIFS(INCOMING!$E$2:$E$5000,INCOMING!$C$2:$C$5000,$A8,INCOMING!$D$2:$D$5000,$B8,INCOMING!$B$2:$B$5000,">="&$C8) -> 0 | G8: =SUMIFS(INCOMING!$F$2:$F$5000,INCOMING!$C$2:$C$5000,$A8,INCOMING!$D$2:$D$5000,$B8,INCOMING!$B$2:$B$5000,">="&$C8) -> 0 | H8: =SUMIFS(OUT!$E$14:$E$5084,OUT!$C$14:$C$5084,$A8,OUT!$D$14:$D$5084,$B8,OUT!$B$14:$B$5084,">="&$C8,OUT!$L$14:$L$5084,"<>Adjustment") -> 0 | I8: =SUMIFS(OUT!$F$14:$F$5084,OUT!$C$14:$C$5084,$A8,OUT!$D$14:$D$5084,$B8,OUT!$B$14:$B$5084,">="&$C8,OUT!$L$14:$L$5084,"<>Adjustment") -> 0 | J8: =SUMIFS(OUT!$E$14:$E$5084,OUT!$C$14:$C$5084,$A8,OUT!$D$14:$D$5084,$B8,OUT!$B$14:$B$5084,">="&$C8,OUT!$L$14:$L$5084,"Adjustment") -> 0 | K8: =SUMIFS(OUT!$F$14:$F$5084,OUT!$C$14:$C$5084,$A8,OUT!$D$14:$D$5084,$B8,OUT!$B$14:$B$5084,">="&$C8,OUT!$L$14:$L$5084,"Adjustment") -> 0 | L8: =D8+F8-H8-J8 -> 1 | M8: =E8+G8-I8-K8 -> 0.0144 | O8: =_xlfn.MAXIFS('OPNAME LOG'!$A$2:$A$1000,'OPNAME LOG'!$B$2:$B$1000,IF($A8="Teak","Jati",IF($A8="Pine","Pinus",$A8)),'OPNAME LOG'!$C$2:$C$1000,$B8) -> 46319 | P8: =SUMIFS('OPNAME LOG'!$D$2:$D$1000,'OPNAME LOG'!$A$2:$A$1000,$O8,'OPNAME LOG'!$B$2:$B$1000,IF($A8="Teak","Jati",IF($A8="Pine","Pinus",$A8)),'OPNAME LOG'!$C$2:$C$1000,$B8)+SUMIFS('OPNAME LOG'!$D$2:$D$1000,'OPNAME LOG'!$A$2:$A$1000,$O8,'OPNAME LOG'!$B$2:$B$1000,IF($A8="Teak","Jati",IF($A8="Pine","Pinus",$A8)),'OPNAME LOG'!$C$2:$C$1000,$B8&" (Grade A)") -> 1 | Q8: =SUMIFS('OPNAME LOG'!$E$2:$E$1000,'OPNAME LOG'!$A$2:$A$1000,$O8,'OPNAME LOG'!$B$2:$B$1000,IF($A8="Teak","Jati",IF($A8="Pine","Pinus",$A8)),'OPNAME LOG'!$C$2:$C$1000,$B8)+SUMIFS('OPNAME LOG'!$E$2:$E$1000,'OPNAME LOG'!$A$2:$A$1000,$O8,'OPNAME LOG'!$B$2:$B$1000,IF($A8="Teak","Jati",IF($A8="Pine","Pinus",$A8)),'OPNAME LOG'!$C$2:$C$1000,$B8&" (Grade A)") -> 0.0144 | R8: =ROUND(L8-P8,6) -> 0 | S8: =ROUND(M8-Q8,6) -> 0
A9: Teak | B9: 4.5 | C9: 46310 | D9: =SUMIFS('OPNAME LOG'!$D$2:$D$1000,'OPNAME LOG'!$A$2:$A$1000,DATE(2026,10,14),'OPNAME LOG'!$B$2:$B$1000,IF($A9="Teak","Jati",IF($A9="Pine","Pinus",$A9)),'OPNAME LOG'!$C$2:$C$1000,$B9)+SUMIFS('OPNAME LOG'!$D$2:$D$1000,'OPNAME LOG'!$A$2:$A$1000,DATE(2026,10,14),'OPNAME LOG'!$B$2:$B$1000,IF($A9="Teak","Jati",IF($A9="Pine","Pinus",$A9)),'OPNAME LOG'!$C$2:$C$1000,$B9&" (Grade A)") -> 167 | E9: =SUMIFS('OPNAME LOG'!$E$2:$E$1000,'OPNAME LOG'!$A$2:$A$1000,DATE(2026,10,14),'OPNAME LOG'!$B$2:$B$1000,IF($A9="Teak","Jati",IF($A9="Pine","Pinus",$A9)),'OPNAME LOG'!$C$2:$C$1000,$B9)+SUMIFS('OPNAME LOG'!$E$2:$E$1000,'OPNAME LOG'!$A$2:$A$1000,DATE(2026,10,14),'OPNAME LOG'!$B$2:$B$1000,IF($A9="Teak","Jati",IF($A9="Pine","Pinus",$A9)),'OPNAME LOG'!$C$2:$C$1000,$B9&" (Grade A)") -> 2.80422 | F9: =SUMIFS(INCOMING!$E$2:$E$5000,INCOMING!$C$2:$C$5000,$A9,INCOMING!$D$2:$D$5000,$B9,INCOMING!$B$2:$B$5000,">="&$C9) -> 123 | G9: =SUMIFS(INCOMING!$F$2:$F$5000,INCOMING!$C$2:$C$5000,$A9,INCOMING!$D$2:$D$5000,$B9,INCOMING!$B$2:$B$5000,">="&$C9) -> 1.997415 | H9: =SUMIFS(OUT!$E$14:$E$5084,OUT!$C$14:$C$5084,$A9,OUT!$D$14:$D$5084,$B9,OUT!$B$14:$B$5084,">="&$C9,OUT!$L$14:$L$5084,"<>Adjustment") -> 245 | I9: =SUMIFS(OUT!$F$14:$F$5084,OUT!$C$14:$C$5084,$A9,OUT!$D$14:$D$5084,$B9,OUT!$B$14:$B$5084,">="&$C9,OUT!$L$14:$L$5084,"<>Adjustment") -> 4.065795 | J9: =SUMIFS(OUT!$E$14:$E$5084,OUT!$C$14:$C$5084,$A9,OUT!$D$14:$D$5084,$B9,OUT!$B$14:$B$5084,">="&$C9,OUT!$L$14:$L$5084,"Adjustment") -> 0 | K9: =SUMIFS(OUT!$F$14:$F$5084,OUT!$C$14:$C$5084,$A9,OUT!$D$14:$D$5084,$B9,OUT!$B$14:$B$5084,">="&$C9,OUT!$L$14:$L$5084,"Adjustment") -> 0 | L9: =D9+F9-H9-J9 -> 45 | M9: =E9+G9-I9-K9 -> 0.73584 | O9: =_xlfn.MAXIFS('OPNAME LOG'!$A$2:$A$1000,'OPNAME LOG'!$B$2:$B$1000,IF($A9="Teak","Jati",IF($A9="Pine","Pinus",$A9)),'OPNAME LOG'!$C$2:$C$1000,$B9) -> 46319 | P9: =SUMIFS('OPNAME LOG'!$D$2:$D$1000,'OPNAME LOG'!$A$2:$A$1000,$O9,'OPNAME LOG'!$B$2:$B$1000,IF($A9="Teak","Jati",IF($A9="Pine","Pinus",$A9)),'OPNAME LOG'!$C$2:$C$1000,$B9)+SUMIFS('OPNAME LOG'!$D$2:$D$1000,'OPNAME LOG'!$A$2:$A$1000,$O9,'OPNAME LOG'!$B$2:$B$1000,IF($A9="Teak","Jati",IF($A9="Pine","Pinus",$A9)),'OPNAME LOG'!$C$2:$C$1000,$B9&" (Grade A)") -> 57 | Q9: =SUMIFS('OPNAME LOG'!$E$2:$E$1000,'OPNAME LOG'!$A$2:$A$1000,$O9,'OPNAME LOG'!$B$2:$B$1000,IF($A9="Teak","Jati",IF($A9="Pine","Pinus",$A9)),'OPNAME LOG'!$C$2:$C$1000,$B9)+SUMIFS('OPNAME LOG'!$E$2:$E$1000,'OPNAME LOG'!$A$2:$A$1000,$O9,'OPNAME LOG'!$B$2:$B$1000,IF($A9="Teak","Jati",IF($A9="Pine","Pinus",$A9)),'OPNAME LOG'!$C$2:$C$1000,$B9&" (Grade A)") -> 0.846945 | R9: =ROUND(L9-P9,6) -> -12 | S9: =ROUND(M9-Q9,6) -> -0.111105
A10: Teak | B10: 5 | C10: 46310 | D10: =SUMIFS('OPNAME LOG'!$D$2:$D$1000,'OPNAME LOG'!$A$2:$A$1000,DATE(2026,10,14),'OPNAME LOG'!$B$2:$B$1000,IF($A10="Teak","Jati",IF($A10="Pine","Pinus",$A10)),'OPNAME LOG'!$C$2:$C$1000,$B10)+SUMIFS('OPNAME LOG'!$D$2:$D$1000,'OPNAME LOG'!$A$2:$A$1000,DATE(2026,10,14),'OPNAME LOG'!$B$2:$B$1000,IF($A10="Teak","Jati",IF($A10="Pine","Pinus",$A10)),'OPNAME LOG'!$C$2:$C$1000,$B10&" (Grade A)") -> 1 | E10: =SUMIFS('OPNAME LOG'!$E$2:$E$1000,'OPNAME LOG'!$A$2:$A$1000,DATE(2026,10,14),'OPNAME LOG'!$B$2:$B$1000,IF($A10="Teak","Jati",IF($A10="Pine","Pinus",$A10)),'OPNAME LOG'!$C$2:$C$1000,$B10)+SUMIFS('OPNAME LOG'!$E$2:$E$1000,'OPNAME LOG'!$A$2:$A$1000,DATE(2026,10,14),'OPNAME LOG'!$B$2:$B$1000,IF($A10="Teak","Jati",IF($A10="Pine","Pinus",$A10)),'OPNAME LOG'!$C$2:$C$1000,$B10&" (Grade A)") -> 0 | F10: =SUMIFS(INCOMING!$E$2:$E$5000,INCOMING!$C$2:$C$5000,$A10,INCOMING!$D$2:$D$5000,$B10,INCOMING!$B$2:$B$5000,">="&$C10) -> 0 | G10: =SUMIFS(INCOMING!$F$2:$F$5000,INCOMING!$C$2:$C$5000,$A10,INCOMING!$D$2:$D$5000,$B10,INCOMING!$B$2:$B$5000,">="&$C10) -> 0 | H10: =SUMIFS(OUT!$E$14:$E$5084,OUT!$C$14:$C$5084,$A10,OUT!$D$14:$D$5084,$B10,OUT!$B$14:$B$5084,">="&$C10,OUT!$L$14:$L$5084,"<>Adjustment") -> 0 | I10: =SUMIFS(OUT!$F$14:$F$5084,OUT!$C$14:$C$5084,$A10,OUT!$D$14:$D$5084,$B10,OUT!$B$14:$B$5084,">="&$C10,OUT!$L$14:$L$5084,"<>Adjustment") -> 0 | J10: =SUMIFS(OUT!$E$14:$E$5084,OUT!$C$14:$C$5084,$A10,OUT!$D$14:$D$5084,$B10,OUT!$B$14:$B$5084,">="&$C10,OUT!$L$14:$L$5084,"Adjustment") -> 0 | K10: =SUMIFS(OUT!$F$14:$F$5084,OUT!$C$14:$C$5084,$A10,OUT!$D$14:$D$5084,$B10,OUT!$B$14:$B$5084,">="&$C10,OUT!$L$14:$L$5084,"Adjustment") -> 0 | L10: =D10+F10-H10-J10 -> 1 | M10: =E10+G10-I10-K10 -> 0 | N10: Out 0.371 m³ exceeds count 0.351 m³. 1 pcs not yet measured. | O10: =_xlfn.MAXIFS('OPNAME LOG'!$A$2:$A$1000,'OPNAME LOG'!$B$2:$B$1000,IF($A10="Teak","Jati",IF($A10="Pine","Pinus",$A10)),'OPNAME LOG'!$C$2:$C$1000,$B10) -> 46319 | P10: =SUMIFS('OPNAME LOG'!$D$2:$D$1000,'OPNAME LOG'!$A$2:$A$1000,$O10,'OPNAME LOG'!$B$2:$B$1000,IF($A10="Teak","Jati",IF($A10="Pine","Pinus",$A10)),'OPNAME LOG'!$C$2:$C$1000,$B10)+SUMIFS('OPNAME LOG'!$D$2:$D$1000,'OPNAME LOG'!$A$2:$A$1000,$O10,'OPNAME LOG'!$B$2:$B$1000,IF($A10="Teak","Jati",IF($A10="Pine","Pinus",$A10)),'OPNAME LOG'!$C$2:$C$1000,$B10&" (Grade A)") -> 0 | Q10: =SUMIFS('OPNAME LOG'!$E$2:$E$1000,'OPNAME LOG'!$A$2:$A$1000,$O10,'OPNAME LOG'!$B$2:$B$1000,IF($A10="Teak","Jati",IF($A10="Pine","Pinus",$A10)),'OPNAME LOG'!$C$2:$C$1000,$B10)+SUMIFS('OPNAME LOG'!$E$2:$E$1000,'OPNAME LOG'!$A$2:$A$1000,$O10,'OPNAME LOG'!$B$2:$B$1000,IF($A10="Teak","Jati",IF($A10="Pine","Pinus",$A10)),'OPNAME LOG'!$C$2:$C$1000,$B10&" (Grade A)") -> 0 | R10: =ROUND(L10-P10,6) -> 1 | S10: =ROUND(M10-Q10,6) -> 0
A11: Teak | B11: 5.5 | C11: 46310 | D11: =SUMIFS('OPNAME LOG'!$D$2:$D$1000,'OPNAME LOG'!$A$2:$A$1000,DATE(2026,10,14),'OPNAME LOG'!$B$2:$B$1000,IF($A11="Teak","Jati",IF($A11="Pine","Pinus",$A11)),'OPNAME LOG'!$C$2:$C$1000,$B11)+SUMIFS('OPNAME LOG'!$D$2:$D$1000,'OPNAME LOG'!$A$2:$A$1000,DATE(2026,10,14),'OPNAME LOG'!$B$2:$B$1000,IF($A11="Teak","Jati",IF($A11="Pine","Pinus",$A11)),'OPNAME LOG'!$C$2:$C$1000,$B11&" (Grade A)") -> 0 | E11: =SUMIFS('OPNAME LOG'!$E$2:$E$1000,'OPNAME LOG'!$A$2:$A$1000,DATE(2026,10,14),'OPNAME LOG'!$B$2:$B$1000,IF($A11="Teak","Jati",IF($A11="Pine","Pinus",$A11)),'OPNAME LOG'!$C$2:$C$1000,$B11)+SUMIFS('OPNAME LOG'!$E$2:$E$1000,'OPNAME LOG'!$A$2:$A$1000,DATE(2026,10,14),'OPNAME LOG'!$B$2:$B$1000,IF($A11="Teak","Jati",IF($A11="Pine","Pinus",$A11)),'OPNAME LOG'!$C$2:$C$1000,$B11&" (Grade A)") -> 0 | F11: =SUMIFS(INCOMING!$E$2:$E$5000,INCOMING!$C$2:$C$5000,$A11,INCOMING!$D$2:$D$5000,$B11,INCOMING!$B$2:$B$5000,">="&$C11) -> 0 | G11: =SUMIFS(INCOMING!$F$2:$F$5000,INCOMING!$C$2:$C$5000,$A11,INCOMING!$D$2:$D$5000,$B11,INCOMING!$B$2:$B$5000,">="&$C11) -> 0 | H11: =SUMIFS(OUT!$E$14:$E$5084,OUT!$C$14:$C$5084,$A11,OUT!$D$14:$D$5084,$B11,OUT!$B$14:$B$5084,">="&$C11,OUT!$L$14:$L$5084,"<>Adjustment") -> 0 | I11: =SUMIFS(OUT!$F$14:$F$5084,OUT!$C$14:$C$5084,$A11,OUT!$D$14:$D$5084,$B11,OUT!$B$14:$B$5084,">="&$C11,OUT!$L$14:$L$5084,"<>Adjustment") -> 0 | J11: =SUMIFS(OUT!$E$14:$E$5084,OUT!$C$14:$C$5084,$A11,OUT!$D$14:$D$5084,$B11,OUT!$B$14:$B$5084,">="&$C11,OUT!$L$14:$L$5084,"Adjustment") -> 0 | K11: =SUMIFS(OUT!$F$14:$F$5084,OUT!$C$14:$C$5084,$A11,OUT!$D$14:$D$5084,$B11,OUT!$B$14:$B$5084,">="&$C11,OUT!$L$14:$L$5084,"Adjustment") -> 0 | L11: =D11+F11-H11-J11 -> 0 | M11: =E11+G11-I11-K11 -> 0 | O11: =_xlfn.MAXIFS('OPNAME LOG'!$A$2:$A$1000,'OPNAME LOG'!$B$2:$B$1000,IF($A11="Teak","Jati",IF($A11="Pine","Pinus",$A11)),'OPNAME LOG'!$C$2:$C$1000,$B11) -> 46319 | P11: =SUMIFS('OPNAME LOG'!$D$2:$D$1000,'OPNAME LOG'!$A$2:$A$1000,$O11,'OPNAME LOG'!$B$2:$B$1000,IF($A11="Teak","Jati",IF($A11="Pine","Pinus",$A11)),'OPNAME LOG'!$C$2:$C$1000,$B11)+SUMIFS('OPNAME LOG'!$D$2:$D$1000,'OPNAME LOG'!$A$2:$A$1000,$O11,'OPNAME LOG'!$B$2:$B$1000,IF($A11="Teak","Jati",IF($A11="Pine","Pinus",$A11)),'OPNAME LOG'!$C$2:$C$1000,$B11&" (Grade A)") -> 0 | Q11: =SUMIFS('OPNAME LOG'!$E$2:$E$1000,'OPNAME LOG'!$A$2:$A$1000,$O11,'OPNAME LOG'!$B$2:$B$1000,IF($A11="Teak","Jati",IF($A11="Pine","Pinus",$A11)),'OPNAME LOG'!$C$2:$C$1000,$B11)+SUMIFS('OPNAME LOG'!$E$2:$E$1000,'OPNAME LOG'!$A$2:$A$1000,$O11,'OPNAME LOG'!$B$2:$B$1000,IF($A11="Teak","Jati",IF($A11="Pine","Pinus",$A11)),'OPNAME LOG'!$C$2:$C$1000,$B11&" (Grade A)") -> 0 | R11: =ROUND(L11-P11,6) -> 0 | S11: =ROUND(M11-Q11,6) -> 0
A12: Teak | B12: 6 | C12: 46310 | D12: =SUMIFS('OPNAME LOG'!$D$2:$D$1000,'OPNAME LOG'!$A$2:$A$1000,DATE(2026,10,14),'OPNAME LOG'!$B$2:$B$1000,IF($A12="Teak","Jati",IF($A12="Pine","Pinus",$A12)),'OPNAME LOG'!$C$2:$C$1000,$B12)+SUMIFS('OPNAME LOG'!$D$2:$D$1000,'OPNAME LOG'!$A$2:$A$1000,DATE(2026,10,14),'OPNAME LOG'!$B$2:$B$1000,IF($A12="Teak","Jati",IF($A12="Pine","Pinus",$A12)),'OPNAME LOG'!$C$2:$C$1000,$B12&" (Grade A)") -> 240.9808 | E12: =SUMIFS('OPNAME LOG'!$E$2:$E$1000,'OPNAME LOG'!$A$2:$A$1000,DATE(2026,10,14),'OPNAME LOG'!$B$2:$B$1000,IF($A12="Teak","Jati",IF($A12="Pine","Pinus",$A12)),'OPNAME LOG'!$C$2:$C$1000,$B12)+SUMIFS('OPNAME LOG'!$E$2:$E$1000,'OPNAME LOG'!$A$2:$A$1000,DATE(2026,10,14),'OPNAME LOG'!$B$2:$B$1000,IF($A12="Teak","Jati",IF($A12="Pine","Pinus",$A12)),'OPNAME LOG'!$C$2:$C$1000,$B12&" (Grade A)") -> 5.36976 | F12: =SUMIFS(INCOMING!$E$2:$E$5000,INCOMING!$C$2:$C$5000,$A12,INCOMING!$D$2:$D$5000,$B12,INCOMING!$B$2:$B$5000,">="&$C12) -> 0 | G12: =SUMIFS(INCOMING!$F$2:$F$5000,INCOMING!$C$2:$C$5000,$A12,INCOMING!$D$2:$D$5000,$B12,INCOMING!$B$2:$B$5000,">="&$C12) -> 0 | H12: =SUMIFS(OUT!$E$14:$E$5084,OUT!$C$14:$C$5084,$A12,OUT!$D$14:$D$5084,$B12,OUT!$B$14:$B$5084,">="&$C12,OUT!$L$14:$L$5084,"<>Adjustment") -> 33 | I12: =SUMIFS(OUT!$F$14:$F$5084,OUT!$C$14:$C$5084,$A12,OUT!$D$14:$D$5084,$B12,OUT!$B$14:$B$5084,">="&$C12,OUT!$L$14:$L$5084,"<>Adjustment") -> 0.83052 | J12: =SUMIFS(OUT!$E$14:$E$5084,OUT!$C$14:$C$5084,$A12,OUT!$D$14:$D$5084,$B12,OUT!$B$14:$B$5084,">="&$C12,OUT!$L$14:$L$5084,"Adjustment") -> 0 | K12: =SUMIFS(OUT!$F$14:$F$5084,OUT!$C$14:$C$5084,$A12,OUT!$D$14:$D$5084,$B12,OUT!$B$14:$B$5084,">="&$C12,OUT!$L$14:$L$5084,"Adjustment") -> 0 | L12: =D12+F12-H12-J12 -> 207.9808 | M12: =E12+G12-I12-K12 -> 4.53924 | O12: =_xlfn.MAXIFS('OPNAME LOG'!$A$2:$A$1000,'OPNAME LOG'!$B$2:$B$1000,IF($A12="Teak","Jati",IF($A12="Pine","Pinus",$A12)),'OPNAME LOG'!$C$2:$C$1000,$B12) -> 46319 | P12: =SUMIFS('OPNAME LOG'!$D$2:$D$1000,'OPNAME LOG'!$A$2:$A$1000,$O12,'OPNAME LOG'!$B$2:$B$1000,IF($A12="Teak","Jati",IF($A12="Pine","Pinus",$A12)),'OPNAME LOG'!$C$2:$C$1000,$B12)+SUMIFS('OPNAME LOG'!$D$2:$D$1000,'OPNAME LOG'!$A$2:$A$1000,$O12,'OPNAME LOG'!$B$2:$B$1000,IF($A12="Teak","Jati",IF($A12="Pine","Pinus",$A12)),'OPNAME LOG'!$C$2:$C$1000,$B12&" (Grade A)") -> 222.74343 | Q12: =SUMIFS('OPNAME LOG'!$E$2:$E$1000,'OPNAME LOG'!$A$2:$A$1000,$O12,'OPNAME LOG'!$B$2:$B$1000,IF($A12="Teak","Jati",IF($A12="Pine","Pinus",$A12)),'OPNAME LOG'!$C$2:$C$1000,$B12)+SUMIFS('OPNAME LOG'!$E$2:$E$1000,'OPNAME LOG'!$A$2:$A$1000,$O12,'OPNAME LOG'!$B$2:$B$1000,IF($A12="Teak","Jati",IF($A12="Pine","Pinus",$A12)),'OPNAME LOG'!$C$2:$C$1000,$B12&" (Grade A)") -> 5.03256 | R12: =ROUND(L12-P12,6) -> -14.762625 | S12: =ROUND(M12-Q12,6) -> -0.49332
A13: Teak | B13: 7 | C13: 46310 | D13: =SUMIFS('OPNAME LOG'!$D$2:$D$1000,'OPNAME LOG'!$A$2:$A$1000,DATE(2026,10,14),'OPNAME LOG'!$B$2:$B$1000,IF($A13="Teak","Jati",IF($A13="Pine","Pinus",$A13)),'OPNAME LOG'!$C$2:$C$1000,$B13)+SUMIFS('OPNAME LOG'!$D$2:$D$1000,'OPNAME LOG'!$A$2:$A$1000,DATE(2026,10,14),'OPNAME LOG'!$B$2:$B$1000,IF($A13="Teak","Jati",IF($A13="Pine","Pinus",$A13)),'OPNAME LOG'!$C$2:$C$1000,$B13&" (Grade A)") -> 263 | E13: =SUMIFS('OPNAME LOG'!$E$2:$E$1000,'OPNAME LOG'!$A$2:$A$1000,DATE(2026,10,14),'OPNAME LOG'!$B$2:$B$1000,IF($A13="Teak","Jati",IF($A13="Pine","Pinus",$A13)),'OPNAME LOG'!$C$2:$C$1000,$B13)+SUMIFS('OPNAME LOG'!$E$2:$E$1000,'OPNAME LOG'!$A$2:$A$1000,DATE(2026,10,14),'OPNAME LOG'!$B$2:$B$1000,IF($A13="Teak","Jati",IF($A13="Pine","Pinus",$A13)),'OPNAME LOG'!$C$2:$C$1000,$B13&" (Grade A)") -> 7.51863 | F13: =SUMIFS(INCOMING!$E$2:$E$5000,INCOMING!$C$2:$C$5000,$A13,INCOMING!$D$2:$D$5000,$B13,INCOMING!$B$2:$B$5000,">="&$C13) -> 0 | G13: =SUMIFS(INCOMING!$F$2:$F$5000,INCOMING!$C$2:$C$5000,$A13,INCOMING!$D$2:$D$5000,$B13,INCOMING!$B$2:$B$5000,">="&$C13) -> 0 | H13: =SUMIFS(OUT!$E$14:$E$5084,OUT!$C$14:$C$5084,$A13,OUT!$D$14:$D$5084,$B13,OUT!$B$14:$B$5084,">="&$C13,OUT!$L$14:$L$5084,"<>Adjustment") -> 42 | I13: =SUMIFS(OUT!$F$14:$F$5084,OUT!$C$14:$C$5084,$A13,OUT!$D$14:$D$5084,$B13,OUT!$B$14:$B$5084,">="&$C13,OUT!$L$14:$L$5084,"<>Adjustment") -> 1.3013 | J13: =SUMIFS(OUT!$E$14:$E$5084,OUT!$C$14:$C$5084,$A13,OUT!$D$14:$D$5084,$B13,OUT!$B$14:$B$5084,">="&$C13,OUT!$L$14:$L$5084,"Adjustment") -> 0 | K13: =SUMIFS(OUT!$F$14:$F$5084,OUT!$C$14:$C$5084,$A13,OUT!$D$14:$D$5084,$B13,OUT!$B$14:$B$5084,">="&$C13,OUT!$L$14:$L$5084,"Adjustment") -> 0 | L13: =D13+F13-H13-J13 -> 221 | M13: =E13+G13-I13-K13 -> 6.21733 | O13: =_xlfn.MAXIFS('OPNAME LOG'!$A$2:$A$1000,'OPNAME LOG'!$B$2:$B$1000,IF($A13="Teak","Jati",IF($A13="Pine","Pinus",$A13)),'OPNAME LOG'!$C$2:$C$1000,$B13) -> 46319 | P13: =SUMIFS('OPNAME LOG'!$D$2:$D$1000,'OPNAME LOG'!$A$2:$A$1000,$O13,'OPNAME LOG'!$B$2:$B$1000,IF($A13="Teak","Jati",IF($A13="Pine","Pinus",$A13)),'OPNAME LOG'!$C$2:$C$1000,$B13)+SUMIFS('OPNAME LOG'!$D$2:$D$1000,'OPNAME LOG'!$A$2:$A$1000,$O13,'OPNAME LOG'!$B$2:$B$1000,IF($A13="Teak","Jati",IF($A13="Pine","Pinus",$A13)),'OPNAME LOG'!$C$2:$C$1000,$B13&" (Grade A)") -> 41 | Q13: =SUMIFS('OPNAME LOG'!$E$2:$E$1000,'OPNAME LOG'!$A$2:$A$1000,$O13,'OPNAME LOG'!$B$2:$B$1000,IF($A13="Teak","Jati",IF($A13="Pine","Pinus",$A13)),'OPNAME LOG'!$C$2:$C$1000,$B13)+SUMIFS('OPNAME LOG'!$E$2:$E$1000,'OPNAME LOG'!$A$2:$A$1000,$O13,'OPNAME LOG'!$B$2:$B$1000,IF($A13="Teak","Jati",IF($A13="Pine","Pinus",$A13)),'OPNAME LOG'!$C$2:$C$1000,$B13&" (Grade A)") -> 6.982416 | R13: =ROUND(L13-P13,6) -> 180 | S13: =ROUND(M13-Q13,6) -> -0.765086
A14: Teak | B14: 8 | C14: 46310 | D14: =SUMIFS('OPNAME LOG'!$D$2:$D$1000,'OPNAME LOG'!$A$2:$A$1000,DATE(2026,10,14),'OPNAME LOG'!$B$2:$B$1000,IF($A14="Teak","Jati",IF($A14="Pine","Pinus",$A14)),'OPNAME LOG'!$C$2:$C$1000,$B14)+SUMIFS('OPNAME LOG'!$D$2:$D$1000,'OPNAME LOG'!$A$2:$A$1000,DATE(2026,10,14),'OPNAME LOG'!$B$2:$B$1000,IF($A14="Teak","Jati",IF($A14="Pine","Pinus",$A14)),'OPNAME LOG'!$C$2:$C$1000,$B14&" (Grade A)") -> 75 | E14: =SUMIFS('OPNAME LOG'!$E$2:$E$1000,'OPNAME LOG'!$A$2:$A$1000,DATE(2026,10,14),'OPNAME LOG'!$B$2:$B$1000,IF($A14="Teak","Jati",IF($A14="Pine","Pinus",$A14)),'OPNAME LOG'!$C$2:$C$1000,$B14)+SUMIFS('OPNAME LOG'!$E$2:$E$1000,'OPNAME LOG'!$A$2:$A$1000,DATE(2026,10,14),'OPNAME LOG'!$B$2:$B$1000,IF($A14="Teak","Jati",IF($A14="Pine","Pinus",$A14)),'OPNAME LOG'!$C$2:$C$1000,$B14&" (Grade A)") -> 2.36528 | F14: =SUMIFS(INCOMING!$E$2:$E$5000,INCOMING!$C$2:$C$5000,$A14,INCOMING!$D$2:$D$5000,$B14,INCOMING!$B$2:$B$5000,">="&$C14) -> 0 | G14: =SUMIFS(INCOMING!$F$2:$F$5000,INCOMING!$C$2:$C$5000,$A14,INCOMING!$D$2:$D$5000,$B14,INCOMING!$B$2:$B$5000,">="&$C14) -> 0 | H14: =SUMIFS(OUT!$E$14:$E$5084,OUT!$C$14:$C$5084,$A14,OUT!$D$14:$D$5084,$B14,OUT!$B$14:$B$5084,">="&$C14,OUT!$L$14:$L$5084,"<>Adjustment") -> 0 | I14: =SUMIFS(OUT!$F$14:$F$5084,OUT!$C$14:$C$5084,$A14,OUT!$D$14:$D$5084,$B14,OUT!$B$14:$B$5084,">="&$C14,OUT!$L$14:$L$5084,"<>Adjustment") -> 0 | J14: =SUMIFS(OUT!$E$14:$E$5084,OUT!$C$14:$C$5084,$A14,OUT!$D$14:$D$5084,$B14,OUT!$B$14:$B$5084,">="&$C14,OUT!$L$14:$L$5084,"Adjustment") -> 0 | K14: =SUMIFS(OUT!$F$14:$F$5084,OUT!$C$14:$C$5084,$A14,OUT!$D$14:$D$5084,$B14,OUT!$B$14:$B$5084,">="&$C14,OUT!$L$14:$L$5084,"Adjustment") -> 0 | L14: =D14+F14-H14-J14 -> 75 | M14: =E14+G14-I14-K14 -> 2.36528 | O14: =_xlfn.MAXIFS('OPNAME LOG'!$A$2:$A$1000,'OPNAME LOG'!$B$2:$B$1000,IF($A14="Teak","Jati",IF($A14="Pine","Pinus",$A14)),'OPNAME LOG'!$C$2:$C$1000,$B14) -> 46319 | P14: =SUMIFS('OPNAME LOG'!$D$2:$D$1000,'OPNAME LOG'!$A$2:$A$1000,$O14,'OPNAME LOG'!$B$2:$B$1000,IF($A14="Teak","Jati",IF($A14="Pine","Pinus",$A14)),'OPNAME LOG'!$C$2:$C$1000,$B14)+SUMIFS('OPNAME LOG'!$D$2:$D$1000,'OPNAME LOG'!$A$2:$A$1000,$O14,'OPNAME LOG'!$B$2:$B$1000,IF($A14="Teak","Jati",IF($A14="Pine","Pinus",$A14)),'OPNAME LOG'!$C$2:$C$1000,$B14&" (Grade A)") -> 74 | Q14: =SUMIFS('OPNAME LOG'!$E$2:$E$1000,'OPNAME LOG'!$A$2:$A$1000,$O14,'OPNAME LOG'!$B$2:$B$1000,IF($A14="Teak","Jati",IF($A14="Pine","Pinus",$A14)),'OPNAME LOG'!$C$2:$C$1000,$B14)+SUMIFS('OPNAME LOG'!$E$2:$E$1000,'OPNAME LOG'!$A$2:$A$1000,$O14,'OPNAME LOG'!$B$2:$B$1000,IF($A14="Teak","Jati",IF($A14="Pine","Pinus",$A14)),'OPNAME LOG'!$C$2:$C$1000,$B14&" (Grade A)") -> 2.30008 | R14: =ROUND(L14-P14,6) -> 1 | S14: =ROUND(M14-Q14,6) -> 0.0652
A15: Total Teak | D15: =SUM(D5:D14) -> 853.9808 | E15: =SUM(E5:E14) -> 19.143315 | F15: =SUM(F5:F14) -> 439 | G15: =SUM(G5:G14) -> 4.951485 | H15: =SUM(H5:H14) -> 497 | I15: =SUM(I5:I14) -> 7.97084 | J15: =SUM(J5:J14) -> 0 | K15: =SUM(K5:K14) -> 0 | ... M15: =SUM(M5:M14) -> 16.12396 | P15: =SUM(P5:P14) -> 642.72422 | Q15: =SUM(Q5:Q14) -> 17.325671 | R15: =SUM(R5:R14) -> 153.25657 | S15: =SUM(S5:S14) -> -1.201711
A17: Sungkai | B17: 2.5 | C17: 46310 | D17: =SUMIFS('OPNAME LOG'!$D$2:$D$1000,'OPNAME LOG'!$A$2:$A$1000,DATE(2026,10,14),'OPNAME LOG'!$B$2:$B$1000,IF($A17="Teak","Jati",IF($A17="Pine","Pinus",$A17)),'OPNAME LOG'!$C$2:$C$1000,$B17)+SUMIFS('OPNAME LOG'!$D$2:$D$1000,'OPNAME LOG'!$A$2:$A$1000,DATE(2026,10,14),'OPNAME LOG'!$B$2:$B$1000,IF($A17="Teak","Jati",IF($A17="Pine","Pinus",$A17)),'OPNAME LOG'!$C$2:$C$1000,$B17&" (Grade A)") -> 18 | E17: =SUMIFS('OPNAME LOG'!$E$2:$E$1000,'OPNAME LOG'!$A$2:$A$1000,DATE(2026,10,14),'OPNAME LOG'!$B$2:$B$1000,IF($A17="Teak","Jati",IF($A17="Pine","Pinus",$A17)),'OPNAME LOG'!$C$2:$C$1000,$B17)+SUMIFS('OPNAME LOG'!$E$2:$E$1000,'OPNAME LOG'!$A$2:$A$1000,DATE(2026,10,14),'OPNAME LOG'!$B$2:$B$1000,IF($A17="Teak","Jati",IF($A17="Pine","Pinus",$A17)),'OPNAME LOG'!$C$2:$C$1000,$B17&" (Grade A)") -> 0.078225 | F17: =SUMIFS(INCOMING!$E$2:$E$5000,INCOMING!$C$2:$C$5000,$A17,INCOMING!$D$2:$D$5000,$B17,INCOMING!$B$2:$B$5000,">="&$C17) -> 0 | G17: =SUMIFS(INCOMING!$F$2:$F$5000,INCOMING!$C$2:$C$5000,$A17,INCOMING!$D$2:$D$5000,$B17,INCOMING!$B$2:$B$5000,">="&$C17) -> 0 | H17: =SUMIFS(OUT!$E$14:$E$5084,OUT!$C$14:$C$5084,$A17,OUT!$D$14:$D$5084,$B17,OUT!$B$14:$B$5084,">="&$C17,OUT!$L$14:$L$5084,"<>Adjustment") -> 0 | I17: =SUMIFS(OUT!$F$14:$F$5084,OUT!$C$14:$C$5084,$A17,OUT!$D$14:$D$5084,$B17,OUT!$B$14:$B$5084,">="&$C17,OUT!$L$14:$L$5084,"<>Adjustment") -> 0 | J17: =SUMIFS(OUT!$E$14:$E$5084,OUT!$C$14:$C$5084,$A17,OUT!$D$14:$D$5084,$B17,OUT!$B$14:$B$5084,">="&$C17,OUT!$L$14:$L$5084,"Adjustment") -> 0 | K17: =SUMIFS(OUT!$F$14:$F$5084,OUT!$C$14:$C$5084,$A17,OUT!$D$14:$D$5084,$B17,OUT!$B$14:$B$5084,">="&$C17,OUT!$L$14:$L$5084,"Adjustment") -> 0 | L17: =D17+F17-H17-J17 -> 18 | M17: =E17+G17-I17-K17 -> 0.078225 | O17: =_xlfn.MAXIFS('OPNAME LOG'!$A$2:$A$1000,'OPNAME LOG'!$B$2:$B$1000,IF($A17="Teak","Jati",IF($A17="Pine","Pinus",$A17)),'OPNAME LOG'!$C$2:$C$1000,$B17) -> 46319 | P17: =SUMIFS('OPNAME LOG'!$D$2:$D$1000,'OPNAME LOG'!$A$2:$A$1000,$O17,'OPNAME LOG'!$B$2:$B$1000,IF($A17="Teak","Jati",IF($A17="Pine","Pinus",$A17)),'OPNAME LOG'!$C$2:$C$1000,$B17)+SUMIFS('OPNAME LOG'!$D$2:$D$1000,'OPNAME LOG'!$A$2:$A$1000,$O17,'OPNAME LOG'!$B$2:$B$1000,IF($A17="Teak","Jati",IF($A17="Pine","Pinus",$A17)),'OPNAME LOG'!$C$2:$C$1000,$B17&" (Grade A)") -> 18 | Q17: =SUMIFS('OPNAME LOG'!$E$2:$E$1000,'OPNAME LOG'!$A$2:$A$1000,$O17,'OPNAME LOG'!$B$2:$B$1000,IF($A17="Teak","Jati",IF($A17="Pine","Pinus",$A17)),'OPNAME LOG'!$C$2:$C$1000,$B17)+SUMIFS('OPNAME LOG'!$E$2:$E$1000,'OPNAME LOG'!$A$2:$A$1000,$O17,'OPNAME LOG'!$B$2:$B$1000,IF($A17="Teak","Jati",IF($A17="Pine","Pinus",$A17)),'OPNAME LOG'!$C$2:$C$1000,$B17&" (Grade A)") -> 0.078225 | R17: =ROUND(L17-P17,6) -> 0 | S17: =ROUND(M17-Q17,6) -> 0
A18: Sungkai | B18: 3 | C18: 46310 | D18: =SUMIFS('OPNAME LOG'!$D$2:$D$1000,'OPNAME LOG'!$A$2:$A$1000,DATE(2026,10,14),'OPNAME LOG'!$B$2:$B$1000,IF($A18="Teak","Jati",IF($A18="Pine","Pinus",$A18)),'OPNAME LOG'!$C$2:$C$1000,$B18)+SUMIFS('OPNAME LOG'!$D$2:$D$1000,'OPNAME LOG'!$A$2:$A$1000,DATE(2026,10,14),'OPNAME LOG'!$B$2:$B$1000,IF($A18="Teak","Jati",IF($A18="Pine","Pinus",$A18)),'OPNAME LOG'!$C$2:$C$1000,$B18&" (Grade A)") -> 300 | E18: =SUMIFS('OPNAME LOG'!$E$2:$E$1000,'OPNAME LOG'!$A$2:$A$1000,DATE(2026,10,14),'OPNAME LOG'!$B$2:$B$1000,IF($A18="Teak","Jati",IF($A18="Pine","Pinus",$A18)),'OPNAME LOG'!$C$2:$C$1000,$B18)+SUMIFS('OPNAME LOG'!$E$2:$E$1000,'OPNAME LOG'!$A$2:$A$1000,DATE(2026,10,14),'OPNAME LOG'!$B$2:$B$1000,IF($A18="Teak","Jati",IF($A18="Pine","Pinus",$A18)),'OPNAME LOG'!$C$2:$C$1000,$B18&" (Grade A)") -> 1.694871 | F18: =SUMIFS(INCOMING!$E$2:$E$5000,INCOMING!$C$2:$C$5000,$A18,INCOMING!$D$2:$D$5000,$B18,INCOMING!$B$2:$B$5000,">="&$C18) -> 0 | G18: =SUMIFS(INCOMING!$F$2:$F$5000,INCOMING!$C$2:$C$5000,$A18,INCOMING!$D$2:$D$5000,$B18,INCOMING!$B$2:$B$5000,">="&$C18) -> 0 | H18: =SUMIFS(OUT!$E$14:$E$5084,OUT!$C$14:$C$5084,$A18,OUT!$D$14:$D$5084,$B18,OUT!$B$14:$B$5084,">="&$C18,OUT!$L$14:$L$5084,"<>Adjustment") -> 45 | I18: =SUMIFS(OUT!$F$14:$F$5084,OUT!$C$14:$C$5084,$A18,OUT!$D$14:$D$5084,$B18,OUT!$B$14:$B$5084,">="&$C18,OUT!$L$14:$L$5084,"<>Adjustment") -> 0.30759 | J18: =SUMIFS(OUT!$E$14:$E$5084,OUT!$C$14:$C$5084,$A18,OUT!$D$14:$D$5084,$B18,OUT!$B$14:$B$5084,">="&$C18,OUT!$L$14:$L$5084,"Adjustment") -> 0 | K18: =SUMIFS(OUT!$F$14:$F$5084,OUT!$C$14:$C$5084,$A18,OUT!$D$14:$D$5084,$B18,OUT!$B$14:$B$5084,">="&$C18,OUT!$L$14:$L$5084,"Adjustment") -> 0 | L18: =D18+F18-H18-J18 -> 255 | M18: =E18+G18-I18-K18 -> 1.387281 | O18: =_xlfn.MAXIFS('OPNAME LOG'!$A$2:$A$1000,'OPNAME LOG'!$B$2:$B$1000,IF($A18="Teak","Jati",IF($A18="Pine","Pinus",$A18)),'OPNAME LOG'!$C$2:$C$1000,$B18) -> 46319 | P18: =SUMIFS('OPNAME LOG'!$D$2:$D$1000,'OPNAME LOG'!$A$2:$A$1000,$O18,'OPNAME LOG'!$B$2:$B$1000,IF($A18="Teak","Jati",IF($A18="Pine","Pinus",$A18)),'OPNAME LOG'!$C$2:$C$1000,$B18)+SUMIFS('OPNAME LOG'!$D$2:$D$1000,'OPNAME LOG'!$A$2:$A$1000,$O18,'OPNAME LOG'!$B$2:$B$1000,IF($A18="Teak","Jati",IF($A18="Pine","Pinus",$A18)),'OPNAME LOG'!$C$2:$C$1000,$B18&" (Grade A)") -> 254.88354 | Q18: =SUMIFS('OPNAME LOG'!$E$2:$E$1000,'OPNAME LOG'!$A$2:$A$1000,$O18,'OPNAME LOG'!$B$2:$B$1000,IF($A18="Teak","Jati",IF($A18="Pine","Pinus",$A18)),'OPNAME LOG'!$C$2:$C$1000,$B18)+SUMIFS('OPNAME LOG'!$E$2:$E$1000,'OPNAME LOG'!$A$2:$A$1000,$O18,'OPNAME LOG'!$B$2:$B$1000,IF($A18="Teak","Jati",IF($A18="Pine","Pinus",$A18)),'OPNAME LOG'!$C$2:$C$1000,$B18&" (Grade A)") -> 1.387281 | R18: =ROUND(L18-P18,6) -> 0.11646 | S18: =ROUND(M18-Q18,6) -> 0
A19: Sungkai | B19: 3.5 | C19: 46310 | D19: =SUMIFS('OPNAME LOG'!$D$2:$D$1000,'OPNAME LOG'!$A$2:$A$1000,DATE(2026,10,14),'OPNAME LOG'!$B$2:$B$1000,IF($A19="Teak","Jati",IF($A19="Pine","Pinus",$A19)),'OPNAME LOG'!$C$2:$C$1000,$B19)+SUMIFS('OPNAME LOG'!$D$2:$D$1000,'OPNAME LOG'!$A$2:$A$1000,DATE(2026,10,14),'OPNAME LOG'!$B$2:$B$1000,IF($A19="Teak","Jati",IF($A19="Pine","Pinus",$A19)),'OPNAME LOG'!$C$2:$C$1000,$B19&" (Grade A)") -> 338 | E19: =SUMIFS('OPNAME LOG'!$E$2:$E$1000,'OPNAME LOG'!$A$2:$A$1000,DATE(2026,10,14),'OPNAME LOG'!$B$2:$B$1000,IF($A19="Teak","Jati",IF($A19="Pine","Pinus",$A19)),'OPNAME LOG'!$C$2:$C$1000,$B19)+SUMIFS('OPNAME LOG'!$E$2:$E$1000,'OPNAME LOG'!$A$2:$A$1000,DATE(2026,10,14),'OPNAME LOG'!$B$2:$B$1000,IF($A19="Teak","Jati",IF($A19="Pine","Pinus",$A19)),'OPNAME LOG'!$C$2:$C$1000,$B19&" (Grade A)") -> 2.763775 | F19: =SUMIFS(INCOMING!$E$2:$E$5000,INCOMING!$C$2:$C$5000,$A19,INCOMING!$D$2:$D$5000,$B19,INCOMING!$B$2:$B$5000,">="&$C19) -> 0 | G19: =SUMIFS(INCOMING!$F$2:$F$5000,INCOMING!$C$2:$C$5000,$A19,INCOMING!$D$2:$D$5000,$B19,INCOMING!$B$2:$B$5000,">="&$C19) -> 0 | H19: =SUMIFS(OUT!$E$14:$E$5084,OUT!$C$14:$C$5084,$A19,OUT!$D$14:$D$5084,$B19,OUT!$B$14:$B$5084,">="&$C19,OUT!$L$14:$L$5084,"<>Adjustment") -> 18 | I19: =SUMIFS(OUT!$F$14:$F$5084,OUT!$C$14:$C$5084,$A19,OUT!$D$14:$D$5084,$B19,OUT!$B$14:$B$5084,">="&$C19,OUT!$L$14:$L$5084,"<>Adjustment") -> 0.154 | J19: =SUMIFS(OUT!$E$14:$E$5084,OUT!$C$14:$C$5084,$A19,OUT!$D$14:$D$5084,$B19,OUT!$B$14:$B$5084,">="&$C19,OUT!$L$14:$L$5084,"Adjustment") -> 0 | K19: =SUMIFS(OUT!$F$14:$F$5084,OUT!$C$14:$C$5084,$A19,OUT!$D$14:$D$5084,$B19,OUT!$B$14:$B$5084,">="&$C19,OUT!$L$14:$L$5084,"Adjustment") -> 0 | L19: =D19+F19-H19-J19 -> 320 | M19: =E19+G19-I19-K19 -> 2.609775 | O19: =_xlfn.MAXIFS('OPNAME LOG'!$A$2:$A$1000,'OPNAME LOG'!$B$2:$B$1000,IF($A19="Teak","Jati",IF($A19="Pine","Pinus",$A19)),'OPNAME LOG'!$C$2:$C$1000,$B19) -> 46319 | P19: =SUMIFS('OPNAME LOG'!$D$2:$D$1000,'OPNAME LOG'!$A$2:$A$1000,$O19,'OPNAME LOG'!$B$2:$B$1000,IF($A19="Teak","Jati",IF($A19="Pine","Pinus",$A19)),'OPNAME LOG'!$C$2:$C$1000,$B19)+SUMIFS('OPNAME LOG'!$D$2:$D$1000,'OPNAME LOG'!$A$2:$A$1000,$O19,'OPNAME LOG'!$B$2:$B$1000,IF($A19="Teak","Jati",IF($A19="Pine","Pinus",$A19)),'OPNAME LOG'!$C$2:$C$1000,$B19&" (Grade A)") -> 319.84394 | Q19: =SUMIFS('OPNAME LOG'!$E$2:$E$1000,'OPNAME LOG'!$A$2:$A$1000,$O19,'OPNAME LOG'!$B$2:$B$1000,IF($A19="Teak","Jati",IF($A19="Pine","Pinus",$A19)),'OPNAME LOG'!$C$2:$C$1000,$B19)+SUMIFS('OPNAME LOG'!$E$2:$E$1000,'OPNAME LOG'!$A$2:$A$1000,$O19,'OPNAME LOG'!$B$2:$B$1000,IF($A19="Teak","Jati",IF($A19="Pine","Pinus",$A19)),'OPNAME LOG'!$C$2:$C$1000,$B19&" (Grade A)") -> 2.609775 | R19: =ROUND(L19-P19,6) -> 0.15606 | S19: =ROUND(M19-Q19,6) -> 0
A20: Sungkai | B20: 4 | C20: 46310 | D20: =SUMIFS('OPNAME LOG'!$D$2:$D$1000,'OPNAME LOG'!$A$2:$A$1000,DATE(2026,10,14),'OPNAME LOG'!$B$2:$B$1000,IF($A20="Teak","Jati",IF($A20="Pine","Pinus",$A20)),'OPNAME LOG'!$C$2:$C$1000,$B20)+SUMIFS('OPNAME LOG'!$D$2:$D$1000,'OPNAME LOG'!$A$2:$A$1000,DATE(2026,10,14),'OPNAME LOG'!$B$2:$B$1000,IF($A20="Teak","Jati",IF($A20="Pine","Pinus",$A20)),'OPNAME LOG'!$C$2:$C$1000,$B20&" (Grade A)") -> 7 | E20: =SUMIFS('OPNAME LOG'!$E$2:$E$1000,'OPNAME LOG'!$A$2:$A$1000,DATE(2026,10,14),'OPNAME LOG'!$B$2:$B$1000,IF($A20="Teak","Jati",IF($A20="Pine","Pinus",$A20)),'OPNAME LOG'!$C$2:$C$1000,$B20)+SUMIFS('OPNAME LOG'!$E$2:$E$1000,'OPNAME LOG'!$A$2:$A$1000,DATE(2026,10,14),'OPNAME LOG'!$B$2:$B$1000,IF($A20="Teak","Jati",IF($A20="Pine","Pinus",$A20)),'OPNAME LOG'!$C$2:$C$1000,$B20&" (Grade A)") -> 0.13044 | F20: =SUMIFS(INCOMING!$E$2:$E$5000,INCOMING!$C$2:$C$5000,$A20,INCOMING!$D$2:$D$5000,$B20,INCOMING!$B$2:$B$5000,">="&$C20) -> 0 | G20: =SUMIFS(INCOMING!$F$2:$F$5000,INCOMING!$C$2:$C$5000,$A20,INCOMING!$D$2:$D$5000,$B20,INCOMING!$B$2:$B$5000,">="&$C20) -> 0 | H20: =SUMIFS(OUT!$E$14:$E$5084,OUT!$C$14:$C$5084,$A20,OUT!$D$14:$D$5084,$B20,OUT!$B$14:$B$5084,">="&$C20,OUT!$L$14:$L$5084,"<>Adjustment") -> 4 | I20: =SUMIFS(OUT!$F$14:$F$5084,OUT!$C$14:$C$5084,$A20,OUT!$D$14:$D$5084,$B20,OUT!$B$14:$B$5084,">="&$C20,OUT!$L$14:$L$5084,"<>Adjustment") -> 0.04168 | J20: =SUMIFS(OUT!$E$14:$E$5084,OUT!$C$14:$C$5084,$A20,OUT!$D$14:$D$5084,$B20,OUT!$B$14:$B$5084,">="&$C20,OUT!$L$14:$L$5084,"Adjustment") -> 0 | K20: =SUMIFS(OUT!$F$14:$F$5084,OUT!$C$14:$C$5084,$A20,OUT!$D$14:$D$5084,$B20,OUT!$B$14:$B$5084,">="&$C20,OUT!$L$14:$L$5084,"Adjustment") -> 0 | L20: =D20+F20-H20-J20 -> 3 | M20: =E20+G20-I20-K20 -> 0.08876 | O20: =_xlfn.MAXIFS('OPNAME LOG'!$A$2:$A$1000,'OPNAME LOG'!$B$2:$B$1000,IF($A20="Teak","Jati",IF($A20="Pine","Pinus",$A20)),'OPNAME LOG'!$C$2:$C$1000,$B20) -> 46319 | P20: =SUMIFS('OPNAME LOG'!$D$2:$D$1000,'OPNAME LOG'!$A$2:$A$1000,$O20,'OPNAME LOG'!$B$2:$B$1000,IF($A20="Teak","Jati",IF($A20="Pine","Pinus",$A20)),'OPNAME LOG'!$C$2:$C$1000,$B20)+SUMIFS('OPNAME LOG'!$D$2:$D$1000,'OPNAME LOG'!$A$2:$A$1000,$O20,'OPNAME LOG'!$B$2:$B$1000,IF($A20="Teak","Jati",IF($A20="Pine","Pinus",$A20)),'OPNAME LOG'!$C$2:$C$1000,$B20&" (Grade A)") -> 3 | Q20: =SUMIFS('OPNAME LOG'!$E$2:$E$1000,'OPNAME LOG'!$A$2:$A$1000,$O20,'OPNAME LOG'!$B$2:$B$1000,IF($A20="Teak","Jati",IF($A20="Pine","Pinus",$A20)),'OPNAME LOG'!$C$2:$C$1000,$B20)+SUMIFS('OPNAME LOG'!$E$2:$E$1000,'OPNAME LOG'!$A$2:$A$1000,$O20,'OPNAME LOG'!$B$2:$B$1000,IF($A20="Teak","Jati",IF($A20="Pine","Pinus",$A20)),'OPNAME LOG'!$C$2:$C$1000,$B20&" (Grade A)") -> 0.08876 | R20: =ROUND(L20-P20,6) -> 0 | S20: =ROUND(M20-Q20,6) -> 0
A21: Sungkai | B21: 4.5 | C21: 46310 | D21: =SUMIFS('OPNAME LOG'!$D$2:$D$1000,'OPNAME LOG'!$A$2:$A$1000,DATE(2026,10,14),'OPNAME LOG'!$B$2:$B$1000,IF($A21="Teak","Jati",IF($A21="Pine","Pinus",$A21)),'OPNAME LOG'!$C$2:$C$1000,$B21)+SUMIFS('OPNAME LOG'!$D$2:$D$1000,'OPNAME LOG'!$A$2:$A$1000,DATE(2026,10,14),'OPNAME LOG'!$B$2:$B$1000,IF($A21="Teak","Jati",IF($A21="Pine","Pinus",$A21)),'OPNAME LOG'!$C$2:$C$1000,$B21&" (Grade A)") -> 39 | E21: =SUMIFS('OPNAME LOG'!$E$2:$E$1000,'OPNAME LOG'!$A$2:$A$1000,DATE(2026,10,14),'OPNAME LOG'!$B$2:$B$1000,IF($A21="Teak","Jati",IF($A21="Pine","Pinus",$A21)),'OPNAME LOG'!$C$2:$C$1000,$B21)+SUMIFS('OPNAME LOG'!$E$2:$E$1000,'OPNAME LOG'!$A$2:$A$1000,DATE(2026,10,14),'OPNAME LOG'!$B$2:$B$1000,IF($A21="Teak","Jati",IF($A21="Pine","Pinus",$A21)),'OPNAME LOG'!$C$2:$C$1000,$B21&" (Grade A)") -> 0.394245 | F21: =SUMIFS(INCOMING!$E$2:$E$5000,INCOMING!$C$2:$C$5000,$A21,INCOMING!$D$2:$D$5000,$B21,INCOMING!$B$2:$B$5000,">="&$C21) -> 0 | G21: =SUMIFS(INCOMING!$F$2:$F$5000,INCOMING!$C$2:$C$5000,$A21,INCOMING!$D$2:$D$5000,$B21,INCOMING!$B$2:$B$5000,">="&$C21) -> 0 | H21: =SUMIFS(OUT!$E$14:$E$5084,OUT!$C$14:$C$5084,$A21,OUT!$D$14:$D$5084,$B21,OUT!$B$14:$B$5084,">="&$C21,OUT!$L$14:$L$5084,"<>Adjustment") -> 39 | I21: =SUMIFS(OUT!$F$14:$F$5084,OUT!$C$14:$C$5084,$A21,OUT!$D$14:$D$5084,$B21,OUT!$B$14:$B$5084,">="&$C21,OUT!$L$14:$L$5084,"<>Adjustment") -> 0.388575 | J21: =SUMIFS(OUT!$E$14:$E$5084,OUT!$C$14:$C$5084,$A21,OUT!$D$14:$D$5084,$B21,OUT!$B$14:$B$5084,">="&$C21,OUT!$L$14:$L$5084,"Adjustment") -> 0 | K21: =SUMIFS(OUT!$F$14:$F$5084,OUT!$C$14:$C$5084,$A21,OUT!$D$14:$D$5084,$B21,OUT!$B$14:$B$5084,">="&$C21,OUT!$L$14:$L$5084,"Adjustment") -> 0 | L21: =D21+F21-H21-J21 -> 0 | M21: =E21+G21-I21-K21 -> 0.00567 | O21: =_xlfn.MAXIFS('OPNAME LOG'!$A$2:$A$1000,'OPNAME LOG'!$B$2:$B$1000,IF($A21="Teak","Jati",IF($A21="Pine","Pinus",$A21)),'OPNAME LOG'!$C$2:$C$1000,$B21) -> 46319 | P21: =SUMIFS('OPNAME LOG'!$D$2:$D$1000,'OPNAME LOG'!$A$2:$A$1000,$O21,'OPNAME LOG'!$B$2:$B$1000,IF($A21="Teak","Jati",IF($A21="Pine","Pinus",$A21)),'OPNAME LOG'!$C$2:$C$1000,$B21)+SUMIFS('OPNAME LOG'!$D$2:$D$1000,'OPNAME LOG'!$A$2:$A$1000,$O21,'OPNAME LOG'!$B$2:$B$1000,IF($A21="Teak","Jati",IF($A21="Pine","Pinus",$A21)),'OPNAME LOG'!$C$2:$C$1000,$B21&" (Grade A)") -> 0 | Q21: =SUMIFS('OPNAME LOG'!$E$2:$E$1000,'OPNAME LOG'!$A$2:$A$1000,$O21,'OPNAME LOG'!$B$2:$B$1000,IF($A21="Teak","Jati",IF($A21="Pine","Pinus",$A21)),'OPNAME LOG'!$C$2:$C$1000,$B21)+SUMIFS('OPNAME LOG'!$E$2:$E$1000,'OPNAME LOG'!$A$2:$A$1000,$O21,'OPNAME LOG'!$B$2:$B$1000,IF($A21="Teak","Jati",IF($A21="Pine","Pinus",$A21)),'OPNAME LOG'!$C$2:$C$1000,$B21&" (Grade A)") -> 0.00567 | R21: =ROUND(L21-P21,6) -> 0 | S21: =ROUND(M21-Q21,6) -> 0
A22: Sungkai | B22: 5 | C22: 46310 | D22: =SUMIFS('OPNAME LOG'!$D$2:$D$1000,'OPNAME LOG'!$A$2:$A$1000,DATE(2026,10,14),'OPNAME LOG'!$B$2:$B$1000,IF($A22="Teak","Jati",IF($A22="Pine","Pinus",$A22)),'OPNAME LOG'!$C$2:$C$1000,$B22)+SUMIFS('OPNAME LOG'!$D$2:$D$1000,'OPNAME LOG'!$A$2:$A$1000,DATE(2026,10,14),'OPNAME LOG'!$B$2:$B$1000,IF($A22="Teak","Jati",IF($A22="Pine","Pinus",$A22)),'OPNAME LOG'!$C$2:$C$1000,$B22&" (Grade A)") -> 43 | E22: =SUMIFS('OPNAME LOG'!$E$2:$E$1000,'OPNAME LOG'!$A$2:$A$1000,DATE(2026,10,14),'OPNAME LOG'!$B$2:$B$1000,IF($A22="Teak","Jati",IF($A22="Pine","Pinus",$A22)),'OPNAME LOG'!$C$2:$C$1000,$B22)+SUMIFS('OPNAME LOG'!$E$2:$E$1000,'OPNAME LOG'!$A$2:$A$1000,DATE(2026,10,14),'OPNAME LOG'!$B$2:$B$1000,IF($A22="Teak","Jati",IF($A22="Pine","Pinus",$A22)),'OPNAME LOG'!$C$2:$C$1000,$B22&" (Grade A)") -> 0.4283 | F22: =SUMIFS(INCOMING!$E$2:$E$5000,INCOMING!$C$2:$C$5000,$A22,INCOMING!$D$2:$D$5000,$B22,INCOMING!$B$2:$B$5000,">="&$C22) -> 0 | G22: =SUMIFS(INCOMING!$F$2:$F$5000,INCOMING!$C$2:$C$5000,$A22,INCOMING!$D$2:$D$5000,$B22,INCOMING!$B$2:$B$5000,">="&$C22) -> 0 | H22: =SUMIFS(OUT!$E$14:$E$5084,OUT!$C$14:$C$5084,$A22,OUT!$D$14:$D$5084,$B22,OUT!$B$14:$B$5084,">="&$C22,OUT!$L$14:$L$5084,"<>Adjustment") -> 36 | I22: =SUMIFS(OUT!$F$14:$F$5084,OUT!$C$14:$C$5084,$A22,OUT!$D$14:$D$5084,$B22,OUT!$B$14:$B$5084,">="&$C22,OUT!$L$14:$L$5084,"<>Adjustment") -> 0.353645 | J22: =SUMIFS(OUT!$E$14:$E$5084,OUT!$C$14:$C$5084,$A22,OUT!$D$14:$D$5084,$B22,OUT!$B$14:$B$5084,">="&$C22,OUT!$L$14:$L$5084,"Adjustment") -> 0 | K22: =SUMIFS(OUT!$F$14:$F$5084,OUT!$C$14:$C$5084,$A22,OUT!$D$14:$D$5084,$B22,OUT!$B$14:$B$5084,">="&$C22,OUT!$L$14:$L$5084,"Adjustment") -> 0 | L22: =D22+F22-H22-J22 -> 7 | M22: =E22+G22-I22-K22 -> 0.074655 | O22: =_xlfn.MAXIFS('OPNAME LOG'!$A$2:$A$1000,'OPNAME LOG'!$B$2:$B$1000,IF($A22="Teak","Jati",IF($A22="Pine","Pinus",$A22)),'OPNAME LOG'!$C$2:$C$1000,$B22) -> 46319 | P22: =SUMIFS('OPNAME LOG'!$D$2:$D$1000,'OPNAME LOG'!$A$2:$A$1000,$O22,'OPNAME LOG'!$B$2:$B$1000,IF($A22="Teak","Jati",IF($A22="Pine","Pinus",$A22)),'OPNAME LOG'!$C$2:$C$1000,$B22)+SUMIFS('OPNAME LOG'!$D$2:$D$1000,'OPNAME LOG'!$A$2:$A$1000,$O22,'OPNAME LOG'!$B$2:$B$1000,IF($A22="Teak","Jati",IF($A22="Pine","Pinus",$A22)),'OPNAME LOG'!$C$2:$C$1000,$B22&" (Grade A)") -> 7 | Q22: =SUMIFS('OPNAME LOG'!$E$2:$E$1000,'OPNAME LOG'!$A$2:$A$1000,$O22,'OPNAME LOG'!$B$2:$B$1000,IF($A22="Teak","Jati",IF($A22="Pine","Pinus",$A22)),'OPNAME LOG'!$C$2:$C$1000,$B22)+SUMIFS('OPNAME LOG'!$E$2:$E$1000,'OPNAME LOG'!$A$2:$A$1000,$O22,'OPNAME LOG'!$B$2:$B$1000,IF($A22="Teak","Jati",IF($A22="Pine","Pinus",$A22)),'OPNAME LOG'!$C$2:$C$1000,$B22&" (Grade A)") -> 0.074655 | R22: =ROUND(L22-P22,6) -> 0 | S22: =ROUND(M22-Q22,6) -> 0
A23: Sungkai | B23: 5.5 | C23: 46310 | D23: =SUMIFS('OPNAME LOG'!$D$2:$D$1000,'OPNAME LOG'!$A$2:$A$1000,DATE(2026,10,14),'OPNAME LOG'!$B$2:$B$1000,IF($A23="Teak","Jati",IF($A23="Pine","Pinus",$A23)),'OPNAME LOG'!$C$2:$C$1000,$B23)+SUMIFS('OPNAME LOG'!$D$2:$D$1000,'OPNAME LOG'!$A$2:$A$1000,DATE(2026,10,14),'OPNAME LOG'!$B$2:$B$1000,IF($A23="Teak","Jati",IF($A23="Pine","Pinus",$A23)),'OPNAME LOG'!$C$2:$C$1000,$B23&" (Grade A)") -> 34 | E23: =SUMIFS('OPNAME LOG'!$E$2:$E$1000,'OPNAME LOG'!$A$2:$A$1000,DATE(2026,10,14),'OPNAME LOG'!$B$2:$B$1000,IF($A23="Teak","Jati",IF($A23="Pine","Pinus",$A23)),'OPNAME LOG'!$C$2:$C$1000,$B23)+SUMIFS('OPNAME LOG'!$E$2:$E$1000,'OPNAME LOG'!$A$2:$A$1000,DATE(2026,10,14),'OPNAME LOG'!$B$2:$B$1000,IF($A23="Teak","Jati",IF($A23="Pine","Pinus",$A23)),'OPNAME LOG'!$C$2:$C$1000,$B23&" (Grade A)") -> 0.400015 | F23: =SUMIFS(INCOMING!$E$2:$E$5000,INCOMING!$C$2:$C$5000,$A23,INCOMING!$D$2:$D$5000,$B23,INCOMING!$B$2:$B$5000,">="&$C23) -> 0 | G23: =SUMIFS(INCOMING!$F$2:$F$5000,INCOMING!$C$2:$C$5000,$A23,INCOMING!$D$2:$D$5000,$B23,INCOMING!$B$2:$B$5000,">="&$C23) -> 0 | H23: =SUMIFS(OUT!$E$14:$E$5084,OUT!$C$14:$C$5084,$A23,OUT!$D$14:$D$5084,$B23,OUT!$B$14:$B$5084,">="&$C23,OUT!$L$14:$L$5084,"<>Adjustment") -> 24 | I23: =SUMIFS(OUT!$F$14:$F$5084,OUT!$C$14:$C$5084,$A23,OUT!$D$14:$D$5084,$B23,OUT!$B$14:$B$5084,">="&$C23,OUT!$L$14:$L$5084,"<>Adjustment") -> 0.294965 | J23: =SUMIFS(OUT!$E$14:$E$5084,OUT!$C$14:$C$5084,$A23,OUT!$D$14:$D$5084,$B23,OUT!$B$14:$B$5084,">="&$C23,OUT!$L$14:$L$5084,"Adjustment") -> 0 | K23: =SUMIFS(OUT!$F$14:$F$5084,OUT!$C$14:$C$5084,$A23,OUT!$D$14:$D$5084,$B23,OUT!$B$14:$B$5084,">="&$C23,OUT!$L$14:$L$5084,"Adjustment") -> 0 | L23: =D23+F23-H23-J23 -> 10 | M23: =E23+G23-I23-K23 -> 0.10505 | O23: =_xlfn.MAXIFS('OPNAME LOG'!$A$2:$A$1000,'OPNAME LOG'!$B$2:$B$1000,IF($A23="Teak","Jati",IF($A23="Pine","Pinus",$A23)),'OPNAME LOG'!$C$2:$C$1000,$B23) -> 46319 | P23: =SUMIFS('OPNAME LOG'!$D$2:$D$1000,'OPNAME LOG'!$A$2:$A$1000,$O23,'OPNAME LOG'!$B$2:$B$1000,IF($A23="Teak","Jati",IF($A23="Pine","Pinus",$A23)),'OPNAME LOG'!$C$2:$C$1000,$B23)+SUMIFS('OPNAME LOG'!$D$2:$D$1000,'OPNAME LOG'!$A$2:$A$1000,$O23,'OPNAME LOG'!$B$2:$B$1000,IF($A23="Teak","Jati",IF($A23="Pine","Pinus",$A23)),'OPNAME LOG'!$C$2:$C$1000,$B23&" (Grade A)") -> 10 | Q23: =SUMIFS('OPNAME LOG'!$E$2:$E$1000,'OPNAME LOG'!$A$2:$A$1000,$O23,'OPNAME LOG'!$B$2:$B$1000,IF($A23="Teak","Jati",IF($A23="Pine","Pinus",$A23)),'OPNAME LOG'!$C$2:$C$1000,$B23)+SUMIFS('OPNAME LOG'!$E$2:$E$1000,'OPNAME LOG'!$A$2:$A$1000,$O23,'OPNAME LOG'!$B$2:$B$1000,IF($A23="Teak","Jati",IF($A23="Pine","Pinus",$A23)),'OPNAME LOG'!$C$2:$C$1000,$B23&" (Grade A)") -> 0.10505 | R23: =ROUND(L23-P23,6) -> 0 | S23: =ROUND(M23-Q23,6) -> 0
A24: Sungkai | B24: 7.5 | C24: 46310 | D24: =SUMIFS('OPNAME LOG'!$D$2:$D$1000,'OPNAME LOG'!$A$2:$A$1000,DATE(2026,10,14),'OPNAME LOG'!$B$2:$B$1000,IF($A24="Teak","Jati",IF($A24="Pine","Pinus",$A24)),'OPNAME LOG'!$C$2:$C$1000,$B24)+SUMIFS('OPNAME LOG'!$D$2:$D$1000,'OPNAME LOG'!$A$2:$A$1000,DATE(2026,10,14),'OPNAME LOG'!$B$2:$B$1000,IF($A24="Teak","Jati",IF($A24="Pine","Pinus",$A24)),'OPNAME LOG'!$C$2:$C$1000,$B24&" (Grade A)") -> 127 | E24: =SUMIFS('OPNAME LOG'!$E$2:$E$1000,'OPNAME LOG'!$A$2:$A$1000,DATE(2026,10,14),'OPNAME LOG'!$B$2:$B$1000,IF($A24="Teak","Jati",IF($A24="Pine","Pinus",$A24)),'OPNAME LOG'!$C$2:$C$1000,$B24)+SUMIFS('OPNAME LOG'!$E$2:$E$1000,'OPNAME LOG'!$A$2:$A$1000,DATE(2026,10,14),'OPNAME LOG'!$B$2:$B$1000,IF($A24="Teak","Jati",IF($A24="Pine","Pinus",$A24)),'OPNAME LOG'!$C$2:$C$1000,$B24&" (Grade A)") -> 2.71845 | F24: =SUMIFS(INCOMING!$E$2:$E$5000,INCOMING!$C$2:$C$5000,$A24,INCOMING!$D$2:$D$5000,$B24,INCOMING!$B$2:$B$5000,">="&$C24) -> 0 | G24: =SUMIFS(INCOMING!$F$2:$F$5000,INCOMING!$C$2:$C$5000,$A24,INCOMING!$D$2:$D$5000,$B24,INCOMING!$B$2:$B$5000,">="&$C24) -> 0 | H24: =SUMIFS(OUT!$E$14:$E$5084,OUT!$C$14:$C$5084,$A24,OUT!$D$14:$D$5084,$B24,OUT!$B$14:$B$5084,">="&$C24,OUT!$L$14:$L$5084,"<>Adjustment") -> 25 | I24: =SUMIFS(OUT!$F$14:$F$5084,OUT!$C$14:$C$5084,$A24,OUT!$D$14:$D$5084,$B24,OUT!$B$14:$B$5084,">="&$C24,OUT!$L$14:$L$5084,"<>Adjustment") -> 0.680625 | J24: =SUMIFS(OUT!$E$14:$E$5084,OUT!$C$14:$C$5084,$A24,OUT!$D$14:$D$5084,$B24,OUT!$B$14:$B$5084,">="&$C24,OUT!$L$14:$L$5084,"Adjustment") -> 0 | K24: =SUMIFS(OUT!$F$14:$F$5084,OUT!$C$14:$C$5084,$A24,OUT!$D$14:$D$5084,$B24,OUT!$B$14:$B$5084,">="&$C24,OUT!$L$14:$L$5084,"Adjustment") -> 0 | L24: =D24+F24-H24-J24 -> 102 | M24: =E24+G24-I24-K24 -> 2.037825 | O24: =_xlfn.MAXIFS('OPNAME LOG'!$A$2:$A$1000,'OPNAME LOG'!$B$2:$B$1000,IF($A24="Teak","Jati",IF($A24="Pine","Pinus",$A24)),'OPNAME LOG'!$C$2:$C$1000,$B24) -> 46319 | P24: =SUMIFS('OPNAME LOG'!$D$2:$D$1000,'OPNAME LOG'!$A$2:$A$1000,$O24,'OPNAME LOG'!$B$2:$B$1000,IF($A24="Teak","Jati",IF($A24="Pine","Pinus",$A24)),'OPNAME LOG'!$C$2:$C$1000,$B24)+SUMIFS('OPNAME LOG'!$D$2:$D$1000,'OPNAME LOG'!$A$2:$A$1000,$O24,'OPNAME LOG'!$B$2:$B$1000,IF($A24="Teak","Jati",IF($A24="Pine","Pinus",$A24)),'OPNAME LOG'!$C$2:$C$1000,$B24&" (Grade A)") -> 102 | Q24: =SUMIFS('OPNAME LOG'!$E$2:$E$1000,'OPNAME LOG'!$A$2:$A$1000,$O24,'OPNAME LOG'!$B$2:$B$1000,IF($A24="Teak","Jati",IF($A24="Pine","Pinus",$A24)),'OPNAME LOG'!$C$2:$C$1000,$B24)+SUMIFS('OPNAME LOG'!$E$2:$E$1000,'OPNAME LOG'!$A$2:$A$1000,$O24,'OPNAME LOG'!$B$2:$B$1000,IF($A24="Teak","Jati",IF($A24="Pine","Pinus",$A24)),'OPNAME LOG'!$C$2:$C$1000,$B24&" (Grade A)") -> 2.037825 | R24: =ROUND(L24-P24,6) -> 0 | S24: =ROUND(M24-Q24,6) -> 0
A25: Sungkai | B25: 8 | C25: 46310 | D25: =SUMIFS('OPNAME LOG'!$D$2:$D$1000,'OPNAME LOG'!$A$2:$A$1000,DATE(2026,10,14),'OPNAME LOG'!$B$2:$B$1000,IF($A25="Teak","Jati",IF($A25="Pine","Pinus",$A25)),'OPNAME LOG'!$C$2:$C$1000,$B25)+SUMIFS('OPNAME LOG'!$D$2:$D$1000,'OPNAME LOG'!$A$2:$A$1000,DATE(2026,10,14),'OPNAME LOG'!$B$2:$B$1000,IF($A25="Teak","Jati",IF($A25="Pine","Pinus",$A25)),'OPNAME LOG'!$C$2:$C$1000,$B25&" (Grade A)") -> 165 | E25: =SUMIFS('OPNAME LOG'!$E$2:$E$1000,'OPNAME LOG'!$A$2:$A$1000,DATE(2026,10,14),'OPNAME LOG'!$B$2:$B$1000,IF($A25="Teak","Jati",IF($A25="Pine","Pinus",$A25)),'OPNAME LOG'!$C$2:$C$1000,$B25)+SUMIFS('OPNAME LOG'!$E$2:$E$1000,'OPNAME LOG'!$A$2:$A$1000,DATE(2026,10,14),'OPNAME LOG'!$B$2:$B$1000,IF($A25="Teak","Jati",IF($A25="Pine","Pinus",$A25)),'OPNAME LOG'!$C$2:$C$1000,$B25&" (Grade A)") -> 3.76424 | F25: =SUMIFS(INCOMING!$E$2:$E$5000,INCOMING!$C$2:$C$5000,$A25,INCOMING!$D$2:$D$5000,$B25,INCOMING!$B$2:$B$5000,">="&$C25) -> 0 | G25: =SUMIFS(INCOMING!$F$2:$F$5000,INCOMING!$C$2:$C$5000,$A25,INCOMING!$D$2:$D$5000,$B25,INCOMING!$B$2:$B$5000,">="&$C25) -> 0 | H25: =SUMIFS(OUT!$E$14:$E$5084,OUT!$C$14:$C$5084,$A25,OUT!$D$14:$D$5084,$B25,OUT!$B$14:$B$5084,">="&$C25,OUT!$L$14:$L$5084,"<>Adjustment") -> 9 | I25: =SUMIFS(OUT!$F$14:$F$5084,OUT!$C$14:$C$5084,$A25,OUT!$D$14:$D$5084,$B25,OUT!$B$14:$B$5084,">="&$C25,OUT!$L$14:$L$5084,"<>Adjustment") -> 0.22136 | J25: =SUMIFS(OUT!$E$14:$E$5084,OUT!$C$14:$C$5084,$A25,OUT!$D$14:$D$5084,$B25,OUT!$B$14:$B$5084,">="&$C25,OUT!$L$14:$L$5084,"Adjustment") -> 0 | K25: =SUMIFS(OUT!$F$14:$F$5084,OUT!$C$14:$C$5084,$A25,OUT!$D$14:$D$5084,$B25,OUT!$B$14:$B$5084,">="&$C25,OUT!$L$14:$L$5084,"Adjustment") -> 0 | L25: =D25+F25-H25-J25 -> 156 | M25: =E25+G25-I25-K25 -> 3.54288 | O25: =_xlfn.MAXIFS('OPNAME LOG'!$A$2:$A$1000,'OPNAME LOG'!$B$2:$B$1000,IF($A25="Teak","Jati",IF($A25="Pine","Pinus",$A25)),'OPNAME LOG'!$C$2:$C$1000,$B25) -> 46319 | P25: =SUMIFS('OPNAME LOG'!$D$2:$D$1000,'OPNAME LOG'!$A$2:$A$1000,$O25,'OPNAME LOG'!$B$2:$B$1000,IF($A25="Teak","Jati",IF($A25="Pine","Pinus",$A25)),'OPNAME LOG'!$C$2:$C$1000,$B25)+SUMIFS('OPNAME LOG'!$D$2:$D$1000,'OPNAME LOG'!$A$2:$A$1000,$O25,'OPNAME LOG'!$B$2:$B$1000,IF($A25="Teak","Jati",IF($A25="Pine","Pinus",$A25)),'OPNAME LOG'!$C$2:$C$1000,$B25&" (Grade A)") -> 156 | Q25: =SUMIFS('OPNAME LOG'!$E$2:$E$1000,'OPNAME LOG'!$A$2:$A$1000,$O25,'OPNAME LOG'!$B$2:$B$1000,IF($A25="Teak","Jati",IF($A25="Pine","Pinus",$A25)),'OPNAME LOG'!$C$2:$C$1000,$B25)+SUMIFS('OPNAME LOG'!$E$2:$E$1000,'OPNAME LOG'!$A$2:$A$1000,$O25,'OPNAME LOG'!$B$2:$B$1000,IF($A25="Teak","Jati",IF($A25="Pine","Pinus",$A25)),'OPNAME LOG'!$C$2:$C$1000,$B25&" (Grade A)") -> 3.54288 | R25: =ROUND(L25-P25,6) -> 0 | S25: =ROUND(M25-Q25,6) -> 0
A26: Total Sungkai | D26: =SUM(D17:D25) -> 1071 | E26: =SUM(E17:E25) -> 12.372561 | F26: =SUM(F17:F25) -> 0 | G26: =SUM(G17:G25) -> 0 | H26: =SUM(H17:H25) -> 200 | I26: =SUM(I17:I25) -> 2.44244 | J26: =SUM(J17:J25) -> 0 | K26: =SUM(K17:K25) -> 0 | ... M26: =SUM(M17:M25) -> 9.930121 | P26: =SUM(P17:P25) -> 870.72748 | Q26: =SUM(Q17:Q25) -> 9.930121 | R26: =SUM(R17:R25) -> 0.27252 | S26: =SUM(S17:S25) -> 0
A28: Pine | B28: 2.5 | C28: 46309 | D28: =SUMIFS('OPNAME LOG'!$D$2:$D$1000,'OPNAME LOG'!$A$2:$A$1000,DATE(2026,10,14),'OPNAME LOG'!$B$2:$B$1000,IF($A28="Teak","Jati",IF($A28="Pine","Pinus",$A28)),'OPNAME LOG'!$C$2:$C$1000,$B28)+SUMIFS('OPNAME LOG'!$D$2:$D$1000,'OPNAME LOG'!$A$2:$A$1000,DATE(2026,10,14),'OPNAME LOG'!$B$2:$B$1000,IF($A28="Teak","Jati",IF($A28="Pine","Pinus",$A28)),'OPNAME LOG'!$C$2:$C$1000,$B28&" (Grade A)") -> 12 | E28: =SUMIFS('OPNAME LOG'!$E$2:$E$1000,'OPNAME LOG'!$A$2:$A$1000,DATE(2026,10,14),'OPNAME LOG'!$B$2:$B$1000,IF($A28="Teak","Jati",IF($A28="Pine","Pinus",$A28)),'OPNAME LOG'!$C$2:$C$1000,$B28)+SUMIFS('OPNAME LOG'!$E$2:$E$1000,'OPNAME LOG'!$A$2:$A$1000,DATE(2026,10,14),'OPNAME LOG'!$B$2:$B$1000,IF($A28="Teak","Jati",IF($A28="Pine","Pinus",$A28)),'OPNAME LOG'!$C$2:$C$1000,$B28&" (Grade A)") -> 0.04878 | F28: =SUMIFS(INCOMING!$E$2:$E$5000,INCOMING!$C$2:$C$5000,$A28,INCOMING!$D$2:$D$5000,$B28,INCOMING!$B$2:$B$5000,">="&$C28) -> 0 | G28: =SUMIFS(INCOMING!$F$2:$F$5000,INCOMING!$C$2:$C$5000,$A28,INCOMING!$D$2:$D$5000,$B28,INCOMING!$B$2:$B$5000,">="&$C28) -> 0 | H28: =SUMIFS(OUT!$E$14:$E$5084,OUT!$C$14:$C$5084,$A28,OUT!$D$14:$D$5084,$B28,OUT!$B$14:$B$5084,">="&$C28,OUT!$L$14:$L$5084,"<>Adjustment") -> 4 | I28: =SUMIFS(OUT!$F$14:$F$5084,OUT!$C$14:$C$5084,$A28,OUT!$D$14:$D$5084,$B28,OUT!$B$14:$B$5084,">="&$C28,OUT!$L$14:$L$5084,"<>Adjustment") -> 0.014275 | J28: =SUMIFS(OUT!$E$14:$E$5084,OUT!$C$14:$C$5084,$A28,OUT!$D$14:$D$5084,$B28,OUT!$B$14:$B$5084,">="&$C28,OUT!$L$14:$L$5084,"Adjustment") -> 0 | K28: =SUMIFS(OUT!$F$14:$F$5084,OUT!$C$14:$C$5084,$A28,OUT!$D$14:$D$5084,$B28,OUT!$B$14:$B$5084,">="&$C28,OUT!$L$14:$L$5084,"Adjustment") -> 0 | L28: =D28+F28-H28-J28 -> 8 | M28: =E28+G28-I28-K28 -> 0.034505 | O28: =_xlfn.MAXIFS('OPNAME LOG'!$A$2:$A$1000,'OPNAME LOG'!$B$2:$B$1000,IF($A28="Teak","Jati",IF($A28="Pine","Pinus",$A28)),'OPNAME LOG'!$C$2:$C$1000,$B28) -> 46319 | P28: =SUMIFS('OPNAME LOG'!$D$2:$D$1000,'OPNAME LOG'!$A$2:$A$1000,$O28,'OPNAME LOG'!$B$2:$B$1000,IF($A28="Teak","Jati",IF($A28="Pine","Pinus",$A28)),'OPNAME LOG'!$C$2:$C$1000,$B28)+SUMIFS('OPNAME LOG'!$D$2:$D$1000,'OPNAME LOG'!$A$2:$A$1000,$O28,'OPNAME LOG'!$B$2:$B$1000,IF($A28="Teak","Jati",IF($A28="Pine","Pinus",$A28)),'OPNAME LOG'!$C$2:$C$1000,$B28&" (Grade A)") -> 8 | Q28: =SUMIFS('OPNAME LOG'!$E$2:$E$1000,'OPNAME LOG'!$A$2:$A$1000,$O28,'OPNAME LOG'!$B$2:$B$1000,IF($A28="Teak","Jati",IF($A28="Pine","Pinus",$A28)),'OPNAME LOG'!$C$2:$C$1000,$B28)+SUMIFS('OPNAME LOG'!$E$2:$E$1000,'OPNAME LOG'!$A$2:$A$1000,$O28,'OPNAME LOG'!$B$2:$B$1000,IF($A28="Teak","Jati",IF($A28="Pine","Pinus",$A28)),'OPNAME LOG'!$C$2:$C$1000,$B28&" (Grade A)") -> 0.034505 | R28: =ROUND(L28-P28,6) -> 0 | S28: =ROUND(M28-Q28,6) -> 0
A29: Pine | B29: 3.5 | C29: 46309 | D29: =SUMIFS('OPNAME LOG'!$D$2:$D$1000,'OPNAME LOG'!$A$2:$A$1000,DATE(2026,10,14),'OPNAME LOG'!$B$2:$B$1000,IF($A29="Teak","Jati",IF($A29="Pine","Pinus",$A29)),'OPNAME LOG'!$C$2:$C$1000,$B29)+SUMIFS('OPNAME LOG'!$D$2:$D$1000,'OPNAME LOG'!$A$2:$A$1000,DATE(2026,10,14),'OPNAME LOG'!$B$2:$B$1000,IF($A29="Teak","Jati",IF($A29="Pine","Pinus",$A29)),'OPNAME LOG'!$C$2:$C$1000,$B29&" (Grade A)") -> 8 | E29: =SUMIFS('OPNAME LOG'!$E$2:$E$1000,'OPNAME LOG'!$A$2:$A$1000,DATE(2026,10,14),'OPNAME LOG'!$B$2:$B$1000,IF($A29="Teak","Jati",IF($A29="Pine","Pinus",$A29)),'OPNAME LOG'!$C$2:$C$1000,$B29)+SUMIFS('OPNAME LOG'!$E$2:$E$1000,'OPNAME LOG'!$A$2:$A$1000,DATE(2026,10,14),'OPNAME LOG'!$B$2:$B$1000,IF($A29="Teak","Jati",IF($A29="Pine","Pinus",$A29)),'OPNAME LOG'!$C$2:$C$1000,$B29&" (Grade A)") -> 0.087675 | F29: =SUMIFS(INCOMING!$E$2:$E$5000,INCOMING!$C$2:$C$5000,$A29,INCOMING!$D$2:$D$5000,$B29,INCOMING!$B$2:$B$5000,">="&$C29) -> 0 | G29: =SUMIFS(INCOMING!$F$2:$F$5000,INCOMING!$C$2:$C$5000,$A29,INCOMING!$D$2:$D$5000,$B29,INCOMING!$B$2:$B$5000,">="&$C29) -> 0 | H29: =SUMIFS(OUT!$E$14:$E$5084,OUT!$C$14:$C$5084,$A29,OUT!$D$14:$D$5084,$B29,OUT!$B$14:$B$5084,">="&$C29,OUT!$L$14:$L$5084,"<>Adjustment") -> 0 | I29: =SUMIFS(OUT!$F$14:$F$5084,OUT!$C$14:$C$5084,$A29,OUT!$D$14:$D$5084,$B29,OUT!$B$14:$B$5084,">="&$C29,OUT!$L$14:$L$5084,"<>Adjustment") -> 0 | J29: =SUMIFS(OUT!$E$14:$E$5084,OUT!$C$14:$C$5084,$A29,OUT!$D$14:$D$5084,$B29,OUT!$B$14:$B$5084,">="&$C29,OUT!$L$14:$L$5084,"Adjustment") -> 0 | K29: =SUMIFS(OUT!$F$14:$F$5084,OUT!$C$14:$C$5084,$A29,OUT!$D$14:$D$5084,$B29,OUT!$B$14:$B$5084,">="&$C29,OUT!$L$14:$L$5084,"Adjustment") -> 0 | L29: =D29+F29-H29-J29 -> 8 | M29: =E29+G29-I29-K29 -> 0.087675 | O29: =_xlfn.MAXIFS('OPNAME LOG'!$A$2:$A$1000,'OPNAME LOG'!$B$2:$B$1000,IF($A29="Teak","Jati",IF($A29="Pine","Pinus",$A29)),'OPNAME LOG'!$C$2:$C$1000,$B29) -> 46319 | P29: =SUMIFS('OPNAME LOG'!$D$2:$D$1000,'OPNAME LOG'!$A$2:$A$1000,$O29,'OPNAME LOG'!$B$2:$B$1000,IF($A29="Teak","Jati",IF($A29="Pine","Pinus",$A29)),'OPNAME LOG'!$C$2:$C$1000,$B29)+SUMIFS('OPNAME LOG'!$D$2:$D$1000,'OPNAME LOG'!$A$2:$A$1000,$O29,'OPNAME LOG'!$B$2:$B$1000,IF($A29="Teak","Jati",IF($A29="Pine","Pinus",$A29)),'OPNAME LOG'!$C$2:$C$1000,$B29&" (Grade A)") -> 8 | Q29: =SUMIFS('OPNAME LOG'!$E$2:$E$1000,'OPNAME LOG'!$A$2:$A$1000,$O29,'OPNAME LOG'!$B$2:$B$1000,IF($A29="Teak","Jati",IF($A29="Pine","Pinus",$A29)),'OPNAME LOG'!$C$2:$C$1000,$B29)+SUMIFS('OPNAME LOG'!$E$2:$E$1000,'OPNAME LOG'!$A$2:$A$1000,$O29,'OPNAME LOG'!$B$2:$B$1000,IF($A29="Teak","Jati",IF($A29="Pine","Pinus",$A29)),'OPNAME LOG'!$C$2:$C$1000,$B29&" (Grade A)") -> 0.087675 | R29: =ROUND(L29-P29,6) -> 0 | S29: =ROUND(M29-Q29,6) -> 0
A30: Total Pine | D30: =SUM(D28:D29) -> 20 | E30: =SUM(E28:E29) -> 0.136455 | F30: =SUM(F28:F29) -> 0 | G30: =SUM(G28:G29) -> 0 | H30: =SUM(H28:H29) -> 4 | I30: =SUM(I28:I29) -> 0.014275 | J30: =SUM(J28:J29) -> 0 | K30: =SUM(K28:K29) -> 0 | ... M30: =SUM(M28:M29) -> 0.12218 | P30: =SUM(P28:P29) -> 16 | Q30: =SUM(Q28:Q29) -> 0.12218 | R30: =SUM(R28:R29) -> 0 | S30: =SUM(S28:S29) -> 0
A32: Grand Total | L32: =L15+L26+L30 -> 1682.9808 | M32: =M15+M26+M30 -> 26.176261 | P32: =P15+P26+P30 -> 1529.4517 | Q32: =Q15+Q26+Q30 -> 27.377972 | R32: =R15+R26+R30 -> 153.52909 | S32: =S15+S26+S30 -> -1.201711
A33: Check | M33: =ROUND(SUMIFS(IN!$G$2:$G$5001,IN!$J$2:$J$5001,"Received")-SUM(OUT!$F$14:$F$5084)-M32,6) -> 0
A34: Check vs SUMMARY | M34: =ROUND(M32-SUMMARY!F22,6) -> 0
A35: Adjustment without reference | C35: 46305 | M35: =SUMPRODUCT((OUT!$L$14:$L$5084="Adjustment")*(OUT!$B$14:$B$5084>=$C$35)*(((OUT!$N$14:$N$5084<>"")*(COUNTIF(OUT!$A$14:$A$5084,OUT!$N$14:$N$5084)>0)+((COUNTIFS('OPNAME LOG'!$A$2:$A$1000,OUT!$B$14:$B$5084,'OPNAME LOG'!$B$2:$B$1000,"Jati",'OPNAME LOG'!$C$2:$C$1000,OUT!$D$14:$D$5084)*(OUT!$C$14:$C$5084="Teak")+COUNTIFS('OPNAME LOG'!$A$2:$A$1000,OUT!$B$14:$B$5084,'OPNAME LOG'!$B$2:$B$1000,"Sungkai",'OPNAME LOG'!$C$2:$C$1000,OUT!$D$14:$D$5084)*(OUT!$C$14:$C$5084="Sungkai")+COUNTIFS('OPNAME LOG'!$A$2:$A$1000,OUT!$B$14:$B$5084,'OPNAME LOG'!$B$2:$B$1000,"Pinus",'OPNAME LOG'!$C$2:$C$1000,OUT!$D$14:$D$5084)*(OUT!$C$14:$C$5084="Pine"))>0))=0)) -> 0
A36: Adjustment rows | C36: =C35 -> 46305 | M36: =COUNTIFS(OUT!$L$14:$L$5084,"Adjustment",OUT!$B$14:$B$5084,">="&$C$35) -> 0

Sheet REKON
A1: Rekon Stok Kayu In-House, 14 sampai 24 Okt 2026 (m³)
A3: Jenis | B3: Tebal (cm) | C3: Mutasi mulai | D3: Saldo awal 14 Okt | E3: 15 sampai 17 Okt | J3: 18 sampai 21 Okt | O3: 22 sampai 24 Okt
E4: Masuk | F4: Keluar | G4: Catatan | H4: Laporan | I4: Selisih | J4: Masuk | K4: Keluar | L4: Catatan | M4: Laporan | N4: Selisih | O4: Masuk | P4: Keluar | Q4: Catatan | R4: Laporan | S4: Selisih
A5: Teak | B5: 2 | C5: 46310 | D5: =SUMIFS('LAPORAN OPERATION'!$F$2:$F$1000,'LAPORAN OPERATION'!$A$2:$A$1000,DATE(2026,10,14),'LAPORAN OPERATION'!$B$2:$B$1000,"Count",'LAPORAN OPERATION'!$C$2:$C$1000,IF($A5="Pine","Pinus",$A5),'LAPORAN OPERATION'!$D$2:$D$1000,$B5)+SUMIFS('LAPORAN OPERATION'!$F$2:$F$1000,'LAPORAN OPERATION'!$A$2:$A$1000,DATE(2026,10,14),'LAPORAN OPERATION'!$B$2:$B$1000,"Count",'LAPORAN OPERATION'!$C$2:$C$1000,IF($A5="Pine","Pinus",$A5),'LAPORAN OPERATION'!$D$2:$D$1000,$B5&" (Grade A)") -> 0.02136 | E5: =SUMIFS(INCOMING!$F$2:$F$5000,INCOMING!$C$2:$C$5000,$A5,INCOMING!$D$2:$D$5000,$B5,INCOMING!$B$2:$B$5000,">="&$C5,INCOMING!$B$2:$B$5000,"<="&DATE(2026,10,17)) -> 0 | F5: =SUMIFS(OUT!$F$14:$F$5084,OUT!$C$14:$C$5084,$A5,OUT!$D$14:$D$5084,$B5,OUT!$B$14:$B$5084,">="&$C5,OUT!$B$14:$B$5084,"<="&DATE(2026,10,17),OUT!$L$14:$L$5084,"<>Adjustment") -> 0.014 | G5: =D5+E5-F5 -> 0.00736 | H5: =SUMIFS('LAPORAN OPERATION'!$F$2:$F$1000,'LAPORAN OPERATION'!$A$2:$A$1000,DATE(2026,10,17),'LAPORAN OPERATION'!$B$2:$B$1000,"Balance",'LAPORAN OPERATION'!$C$2:$C$1000,IF($A5="Pine","Pinus",$A5),'LAPORAN OPERATION'!$D$2:$D$1000,$B5)+SUMIFS('LAPORAN OPERATION'!$F$2:$F$1000,'LAPORAN OPERATION'!$A$2:$A$1000,DATE(2026,10,17),'LAPORAN OPERATION'!$B$2:$B$1000,"Balance",'LAPORAN OPERATION'!$C$2:$C$1000,IF($A5="Pine","Pinus",$A5),'LAPORAN OPERATION'!$D$2:$D$1000,$B5&" (Grade A)") -> 0.02136 | I5: =ROUND(G5-H5,6) -> -0.014 | J5: =SUMIFS(INCOMING!$F$2:$F$5000,INCOMING!$C$2:$C$5000,$A5,INCOMING!$D$2:$D$5000,$B5,INCOMING!$B$2:$B$5000,">="&DATE(2026,10,18),INCOMING!$B$2:$B$5000,"<="&DATE(2026,10,21)) -> 0 | K5: =SUMIFS(OUT!$F$14:$F$5084,OUT!$C$14:$C$5084,$A5,OUT!$D$14:$D$5084,$B5,OUT!$B$14:$B$5084,">="&DATE(2026,10,18),OUT!$B$14:$B$5084,"<="&DATE(2026,10,21),OUT!$L$14:$L$5084,"<>Adjustment") -> 0 | L5: =G5+J5-K5 -> 0.00736 | M5: =SUMIFS('LAPORAN OPERATION'!$F$2:$F$1000,'LAPORAN OPERATION'!$A$2:$A$1000,DATE(2026,10,21),'LAPORAN OPERATION'!$B$2:$B$1000,"Balance",'LAPORAN OPERATION'!$C$2:$C$1000,IF($A5="Pine","Pinus",$A5),'LAPORAN OPERATION'!$D$2:$D$1000,$B5)+SUMIFS('LAPORAN OPERATION'!$F$2:$F$1000,'LAPORAN OPERATION'!$A$2:$A$1000,DATE(2026,10,21),'LAPORAN OPERATION'!$B$2:$B$1000,"Balance",'LAPORAN OPERATION'!$C$2:$C$1000,IF($A5="Pine","Pinus",$A5),'LAPORAN OPERATION'!$D$2:$D$1000,$B5&" (Grade A)") -> 0.00736 | N5: =ROUND(L5-M5,6) -> 0 | O5: =SUMIFS(INCOMING!$F$2:$F$5000,INCOMING!$C$2:$C$5000,$A5,INCOMING!$D$2:$D$5000,$B5,INCOMING!$B$2:$B$5000,">="&DATE(2026,10,22),INCOMING!$B$2:$B$5000,"<="&DATE(2026,10,24)) -> 0 | P5: =SUMIFS(OUT!$F$14:$F$5084,OUT!$C$14:$C$5084,$A5,OUT!$D$14:$D$5084,$B5,OUT!$B$14:$B$5084,">="&DATE(2026,10,22),OUT!$B$14:$B$5084,"<="&DATE(2026,10,24),OUT!$L$14:$L$5084,"<>Adjustment") -> 0 | Q5: =L5+O5-P5 -> 0.00736 | R5: =SUMIFS('LAPORAN OPERATION'!$F$2:$F$1000,'LAPORAN OPERATION'!$A$2:$A$1000,DATE(2026,10,24),'LAPORAN OPERATION'!$B$2:$B$1000,"Count",'LAPORAN OPERATION'!$C$2:$C$1000,IF($A5="Pine","Pinus",$A5),'LAPORAN OPERATION'!$D$2:$D$1000,$B5)+SUMIFS('LAPORAN OPERATION'!$F$2:$F$1000,'LAPORAN OPERATION'!$A$2:$A$1000,DATE(2026,10,24),'LAPORAN OPERATION'!$B$2:$B$1000,"Count",'LAPORAN OPERATION'!$C$2:$C$1000,IF($A5="Pine","Pinus",$A5),'LAPORAN OPERATION'!$D$2:$D$1000,$B5&" (Grade A)") -> 0.00736 | S5: =ROUND(Q5-R5,6) -> 0
A6: Teak | B6: 3 | C6: 46310 | D6: =SUMIFS('LAPORAN OPERATION'!$F$2:$F$1000,'LAPORAN OPERATION'!$A$2:$A$1000,DATE(2026,10,14),'LAPORAN OPERATION'!$B$2:$B$1000,"Count",'LAPORAN OPERATION'!$C$2:$C$1000,IF($A6="Pine","Pinus",$A6),'LAPORAN OPERATION'!$D$2:$D$1000,$B6)+SUMIFS('LAPORAN OPERATION'!$F$2:$F$1000,'LAPORAN OPERATION'!$A$2:$A$1000,DATE(2026,10,14),'LAPORAN OPERATION'!$B$2:$B$1000,"Count",'LAPORAN OPERATION'!$C$2:$C$1000,IF($A6="Pine","Pinus",$A6),'LAPORAN OPERATION'!$D$2:$D$1000,$B6&" (Grade A)") -> 0.0102 | E6: =SUMIFS(INCOMING!$F$2:$F$5000,INCOMING!$C$2:$C$5000,$A6,INCOMING!$D$2:$D$5000,$B6,INCOMING!$B$2:$B$5000,">="&$C6,INCOMING!$B$2:$B$5000,"<="&DATE(2026,10,17)) -> 0 | F6: =SUMIFS(OUT!$F$14:$F$5084,OUT!$C$14:$C$5084,$A6,OUT!$D$14:$D$5084,$B6,OUT!$B$14:$B$5084,">="&$C6,OUT!$B$14:$B$5084,"<="&DATE(2026,10,17),OUT!$L$14:$L$5084,"<>Adjustment") -> 0.0192 | G6: =D6+E6-F6 -> -0.009 | H6: =SUMIFS('LAPORAN OPERATION'!$F$2:$F$1000,'LAPORAN OPERATION'!$A$2:$A$1000,DATE(2026,10,17),'LAPORAN OPERATION'!$B$2:$B$1000,"Balance",'LAPORAN OPERATION'!$C$2:$C$1000,IF($A6="Pine","Pinus",$A6),'LAPORAN OPERATION'!$D$2:$D$1000,$B6)+SUMIFS('LAPORAN OPERATION'!$F$2:$F$1000,'LAPORAN OPERATION'!$A$2:$A$1000,DATE(2026,10,17),'LAPORAN OPERATION'!$B$2:$B$1000,"Balance",'LAPORAN OPERATION'!$C$2:$C$1000,IF($A6="Pine","Pinus",$A6),'LAPORAN OPERATION'!$D$2:$D$1000,$B6&" (Grade A)") -> 0.0102 | I6: =ROUND(G6-H6,6) -> -0.0192 | J6: =SUMIFS(INCOMING!$F$2:$F$5000,INCOMING!$C$2:$C$5000,$A6,INCOMING!$D$2:$D$5000,$B6,INCOMING!$B$2:$B$5000,">="&DATE(2026,10,18),INCOMING!$B$2:$B$5000,"<="&DATE(2026,10,21)) -> 0 | K6: =SUMIFS(OUT!$F$14:$F$5084,OUT!$C$14:$C$5084,$A6,OUT!$D$14:$D$5084,$B6,OUT!$B$14:$B$5084,">="&DATE(2026,10,18),OUT!$B$14:$B$5084,"<="&DATE(2026,10,21),OUT!$L$14:$L$5084,"<>Adjustment") -> 0 | L6: =G6+J6-K6 -> -0.009 | M6: =SUMIFS('LAPORAN OPERATION'!$F$2:$F$1000,'LAPORAN OPERATION'!$A$2:$A$1000,DATE(2026,10,21),'LAPORAN OPERATION'!$B$2:$B$1000,"Balance",'LAPORAN OPERATION'!$C$2:$C$1000,IF($A6="Pine","Pinus",$A6),'LAPORAN OPERATION'!$D$2:$D$1000,$B6)+SUMIFS('LAPORAN OPERATION'!$F$2:$F$1000,'LAPORAN OPERATION'!$A$2:$A$1000,DATE(2026,10,21),'LAPORAN OPERATION'!$B$2:$B$1000,"Balance",'LAPORAN OPERATION'!$C$2:$C$1000,IF($A6="Pine","Pinus",$A6),'LAPORAN OPERATION'!$D$2:$D$1000,$B6&" (Grade A)") -> 0.0102 | N6: =ROUND(L6-M6,6) -> -0.0192 | O6: =SUMIFS(INCOMING!$F$2:$F$5000,INCOMING!$C$2:$C$5000,$A6,INCOMING!$D$2:$D$5000,$B6,INCOMING!$B$2:$B$5000,">="&DATE(2026,10,22),INCOMING!$B$2:$B$5000,"<="&DATE(2026,10,24)) -> 0 | P6: =SUMIFS(OUT!$F$14:$F$5084,OUT!$C$14:$C$5084,$A6,OUT!$D$14:$D$5084,$B6,OUT!$B$14:$B$5084,">="&DATE(2026,10,22),OUT!$B$14:$B$5084,"<="&DATE(2026,10,24),OUT!$L$14:$L$5084,"<>Adjustment") -> 0 | Q6: =L6+O6-P6 -> -0.009 | R6: =SUMIFS('LAPORAN OPERATION'!$F$2:$F$1000,'LAPORAN OPERATION'!$A$2:$A$1000,DATE(2026,10,24),'LAPORAN OPERATION'!$B$2:$B$1000,"Count",'LAPORAN OPERATION'!$C$2:$C$1000,IF($A6="Pine","Pinus",$A6),'LAPORAN OPERATION'!$D$2:$D$1000,$B6)+SUMIFS('LAPORAN OPERATION'!$F$2:$F$1000,'LAPORAN OPERATION'!$A$2:$A$1000,DATE(2026,10,24),'LAPORAN OPERATION'!$B$2:$B$1000,"Count",'LAPORAN OPERATION'!$C$2:$C$1000,IF($A6="Pine","Pinus",$A6),'LAPORAN OPERATION'!$D$2:$D$1000,$B6&" (Grade A)") -> 0.0102 | S6: =ROUND(Q6-R6,6) -> -0.0192
A7: Teak | B7: 3.5 | C7: 46310 | D7: =SUMIFS('LAPORAN OPERATION'!$F$2:$F$1000,'LAPORAN OPERATION'!$A$2:$A$1000,DATE(2026,10,14),'LAPORAN OPERATION'!$B$2:$B$1000,"Count",'LAPORAN OPERATION'!$C$2:$C$1000,IF($A7="Pine","Pinus",$A7),'LAPORAN OPERATION'!$D$2:$D$1000,$B7)+SUMIFS('LAPORAN OPERATION'!$F$2:$F$1000,'LAPORAN OPERATION'!$A$2:$A$1000,DATE(2026,10,14),'LAPORAN OPERATION'!$B$2:$B$1000,"Count",'LAPORAN OPERATION'!$C$2:$C$1000,IF($A7="Pine","Pinus",$A7),'LAPORAN OPERATION'!$D$2:$D$1000,$B7&" (Grade A)") -> 1.039465 | E7: =SUMIFS(INCOMING!$F$2:$F$5000,INCOMING!$C$2:$C$5000,$A7,INCOMING!$D$2:$D$5000,$B7,INCOMING!$B$2:$B$5000,">="&$C7,INCOMING!$B$2:$B$5000,"<="&DATE(2026,10,17)) -> 0 | F7: =SUMIFS(OUT!$F$14:$F$5084,OUT!$C$14:$C$5084,$A7,OUT!$D$14:$D$5084,$B7,OUT!$B$14:$B$5084,">="&$C7,OUT!$B$14:$B$5084,"<="&DATE(2026,10,17),OUT!$L$14:$L$5084,"<>Adjustment") -> 0.865165 | G7: =D7+E7-F7 -> 0.1743 | H7: =SUMIFS('LAPORAN OPERATION'!$F$2:$F$1000,'LAPORAN OPERATION'!$A$2:$A$1000,DATE(2026,10,17),'LAPORAN OPERATION'!$B$2:$B$1000,"Balance",'LAPORAN OPERATION'!$C$2:$C$1000,IF($A7="Pine","Pinus",$A7),'LAPORAN OPERATION'!$D$2:$D$1000,$B7)+SUMIFS('LAPORAN OPERATION'!$F$2:$F$1000,'LAPORAN OPERATION'!$A$2:$A$1000,DATE(2026,10,17),'LAPORAN OPERATION'!$B$2:$B$1000,"Balance",'LAPORAN OPERATION'!$C$2:$C$1000,IF($A7="Pine","Pinus",$A7),'LAPORAN OPERATION'!$D$2:$D$1000,$B7&" (Grade A)") -> 0.815115 | I7: =ROUND(G7-H7,6) -> -0.640815 | J7: =SUMIFS(INCOMING!$F$2:$F$5000,INCOMING!$C$2:$C$5000,$A7,INCOMING!$D$2:$D$5000,$B7,INCOMING!$B$2:$B$5000,">="&DATE(2026,10,18),INCOMING!$B$2:$B$5000,"<="&DATE(2026,10,21)) -> 1.894305 | K7: =SUMIFS(OUT!$F$14:$F$5084,OUT!$C$14:$C$5084,$A7,OUT!$D$14:$D$5084,$B7,OUT!$B$14:$B$5084,">="&DATE(2026,10,18),OUT!$B$14:$B$5084,"<="&DATE(2026,10,21),OUT!$L$14:$L$5084,"<>Adjustment") -> 0.25914 | L7: =G7+J7-K7 -> 1.809465 | M7: =SUMIFS('LAPORAN OPERATION'!$F$2:$F$1000,'LAPORAN OPERATION'!$A$2:$A$1000,DATE(2026,10,21),'LAPORAN OPERATION'!$B$2:$B$1000,"Balance",'LAPORAN OPERATION'!$C$2:$C$1000,IF($A7="Pine","Pinus",$A7),'LAPORAN OPERATION'!$D$2:$D$1000,$B7)+SUMIFS('LAPORAN OPERATION'!$F$2:$F$1000,'LAPORAN OPERATION'!$A$2:$A$1000,DATE(2026,10,21),'LAPORAN OPERATION'!$B$2:$B$1000,"Balance",'LAPORAN OPERATION'!$C$2:$C$1000,IF($A7="Pine","Pinus",$A7),'LAPORAN OPERATION'!$D$2:$D$1000,$B7&" (Grade A)") -> 1.635165 | N7: =ROUND(L7-M7,6) -> 0.1743 | O7: =SUMIFS(INCOMING!$F$2:$F$5000,INCOMING!$C$2:$C$5000,$A7,INCOMING!$D$2:$D$5000,$B7,INCOMING!$B$2:$B$5000,">="&DATE(2026,10,22),INCOMING!$B$2:$B$5000,"<="&DATE(2026,10,24)) -> 1.059765 | P7: =SUMIFS(OUT!$F$14:$F$5084,OUT!$C$14:$C$5084,$A7,OUT!$D$14:$D$5084,$B7,OUT!$B$14:$B$5084,">="&DATE(2026,10,22),OUT!$B$14:$B$5084,"<="&DATE(2026,10,24),OUT!$L$14:$L$5084,"<>Adjustment") -> 0.61572 | Q7: =L7+O7-P7 -> 2.25351 | R7: =SUMIFS('LAPORAN OPERATION'!$F$2:$F$1000,'LAPORAN OPERATION'!$A$2:$A$1000,DATE(2026,10,24),'LAPORAN OPERATION'!$B$2:$B$1000,"Count",'LAPORAN OPERATION'!$C$2:$C$1000,IF($A7="Pine","Pinus",$A7),'LAPORAN OPERATION'!$D$2:$D$1000,$B7)+SUMIFS('LAPORAN OPERATION'!$F$2:$F$1000,'LAPORAN OPERATION'!$A$2:$A$1000,DATE(2026,10,24),'LAPORAN OPERATION'!$B$2:$B$1000,"Count",'LAPORAN OPERATION'!$C$2:$C$1000,IF($A7="Pine","Pinus",$A7),'LAPORAN OPERATION'!$D$2:$D$1000,$B7&" (Grade A)") -> 2.13171 | S7: =ROUND(Q7-R7,6) -> 0.1218
A8: Teak | B8: 4 | C8: 46310 | D8: =SUMIFS('LAPORAN OPERATION'!$F$2:$F$1000,'LAPORAN OPERATION'!$A$2:$A$1000,DATE(2026,10,14),'LAPORAN OPERATION'!$B$2:$B$1000,"Count",'LAPORAN OPERATION'!$C$2:$C$1000,IF($A8="Pine","Pinus",$A8),'LAPORAN OPERATION'!$D$2:$D$1000,$B8)+SUMIFS('LAPORAN OPERATION'!$F$2:$F$1000,'LAPORAN OPERATION'!$A$2:$A$1000,DATE(2026,10,14),'LAPORAN OPERATION'!$B$2:$B$1000,"Count",'LAPORAN OPERATION'!$C$2:$C$1000,IF($A8="Pine","Pinus",$A8),'LAPORAN OPERATION'!$D$2:$D$1000,$B8&" (Grade A)") -> 0.0144 | E8: =SUMIFS(INCOMING!$F$2:$F$5000,INCOMING!$C$2:$C$5000,$A8,INCOMING!$D$2:$D$5000,$B8,INCOMING!$B$2:$B$5000,">="&$C8,INCOMING!$B$2:$B$5000,"<="&DATE(2026,10,17)) -> 0 | F8: =SUMIFS(OUT!$F$14:$F$5084,OUT!$C$14:$C$5084,$A8,OUT!$D$14:$D$5084,$B8,OUT!$B$14:$B$5084,">="&$C8,OUT!$B$14:$B$5084,"<="&DATE(2026,10,17),OUT!$L$14:$L$5084,"<>Adjustment") -> 0 | G8: =D8+E8-F8 -> 0.0144 | H8: =SUMIFS('LAPORAN OPERATION'!$F$2:$F$1000,'LAPORAN OPERATION'!$A$2:$A$1000,DATE(2026,10,17),'LAPORAN OPERATION'!$B$2:$B$1000,"Balance",'LAPORAN OPERATION'!$C$2:$C$1000,IF($A8="Pine","Pinus",$A8),'LAPORAN OPERATION'!$D$2:$D$1000,$B8)+SUMIFS('LAPORAN OPERATION'!$F$2:$F$1000,'LAPORAN OPERATION'!$A$2:$A$1000,DATE(2026,10,17),'LAPORAN OPERATION'!$B$2:$B$1000,"Balance",'LAPORAN OPERATION'!$C$2:$C$1000,IF($A8="Pine","Pinus",$A8),'LAPORAN OPERATION'!$D$2:$D$1000,$B8&" (Grade A)") -> 0.0144 | I8: =ROUND(G8-H8,6) -> 0 | J8: =SUMIFS(INCOMING!$F$2:$F$5000,INCOMING!$C$2:$C$5000,$A8,INCOMING!$D$2:$D$5000,$B8,INCOMING!$B$2:$B$5000,">="&DATE(2026,10,18),INCOMING!$B$2:$B$5000,"<="&DATE(2026,10,21)) -> 0 | K8: =SUMIFS(OUT!$F$14:$F$5084,OUT!$C$14:$C$5084,$A8,OUT!$D$14:$D$5084,$B8,OUT!$B$14:$B$5084,">="&DATE(2026,10,18),OUT!$B$14:$B$5084,"<="&DATE(2026,10,21),OUT!$L$14:$L$5084,"<>Adjustment") -> 0 | L8: =G8+J8-K8 -> 0.0144 | M8: =SUMIFS('LAPORAN OPERATION'!$F$2:$F$1000,'LAPORAN OPERATION'!$A$2:$A$1000,DATE(2026,10,21),'LAPORAN OPERATION'!$B$2:$B$1000,"Balance",'LAPORAN OPERATION'!$C$2:$C$1000,IF($A8="Pine","Pinus",$A8),'LAPORAN OPERATION'!$D$2:$D$1000,$B8)+SUMIFS('LAPORAN OPERATION'!$F$2:$F$1000,'LAPORAN OPERATION'!$A$2:$A$1000,DATE(2026,10,21),'LAPORAN OPERATION'!$B$2:$B$1000,"Balance",'LAPORAN OPERATION'!$C$2:$C$1000,IF($A8="Pine","Pinus",$A8),'LAPORAN OPERATION'!$D$2:$D$1000,$B8&" (Grade A)") -> 0.0144 | N8: =ROUND(L8-M8,6) -> 0 | O8: =SUMIFS(INCOMING!$F$2:$F$5000,INCOMING!$C$2:$C$5000,$A8,INCOMING!$D$2:$D$5000,$B8,INCOMING!$B$2:$B$5000,">="&DATE(2026,10,22),INCOMING!$B$2:$B$5000,"<="&DATE(2026,10,24)) -> 0 | P8: =SUMIFS(OUT!$F$14:$F$5084,OUT!$C$14:$C$5084,$A8,OUT!$D$14:$D$5084,$B8,OUT!$B$14:$B$5084,">="&DATE(2026,10,22),OUT!$B$14:$B$5084,"<="&DATE(2026,10,24),OUT!$L$14:$L$5084,"<>Adjustment") -> 0 | Q8: =L8+O8-P8 -> 0.0144 | R8: =SUMIFS('LAPORAN OPERATION'!$F$2:$F$1000,'LAPORAN OPERATION'!$A$2:$A$1000,DATE(2026,10,24),'LAPORAN OPERATION'!$B$2:$B$1000,"Count",'LAPORAN OPERATION'!$C$2:$C$1000,IF($A8="Pine","Pinus",$A8),'LAPORAN OPERATION'!$D$2:$D$1000,$B8)+SUMIFS('LAPORAN OPERATION'!$F$2:$F$1000,'LAPORAN OPERATION'!$A$2:$A$1000,DATE(2026,10,24),'LAPORAN OPERATION'!$B$2:$B$1000,"Count",'LAPORAN OPERATION'!$C$2:$C$1000,IF($A8="Pine","Pinus",$A8),'LAPORAN OPERATION'!$D$2:$D$1000,$B8&" (Grade A)") -> 0.0144 | S8: =ROUND(Q8-R8,6) -> 0
A9: Teak | B9: 4.5 | C9: 46310 | D9: =SUMIFS('LAPORAN OPERATION'!$F$2:$F$1000,'LAPORAN OPERATION'!$A$2:$A$1000,DATE(2026,10,14),'LAPORAN OPERATION'!$B$2:$B$1000,"Count",'LAPORAN OPERATION'!$C$2:$C$1000,IF($A9="Pine","Pinus",$A9),'LAPORAN OPERATION'!$D$2:$D$1000,$B9)+SUMIFS('LAPORAN OPERATION'!$F$2:$F$1000,'LAPORAN OPERATION'!$A$2:$A$1000,DATE(2026,10,14),'LAPORAN OPERATION'!$B$2:$B$1000,"Count",'LAPORAN OPERATION'!$C$2:$C$1000,IF($A9="Pine","Pinus",$A9),'LAPORAN OPERATION'!$D$2:$D$1000,$B9&" (Grade A)") -> 2.80422 | E9: =SUMIFS(INCOMING!$F$2:$F$5000,INCOMING!$C$2:$C$5000,$A9,INCOMING!$D$2:$D$5000,$B9,INCOMING!$B$2:$B$5000,">="&$C9,INCOMING!$B$2:$B$5000,"<="&DATE(2026,10,17)) -> 0 | F9: =SUMIFS(OUT!$F$14:$F$5084,OUT!$C$14:$C$5084,$A9,OUT!$D$14:$D$5084,$B9,OUT!$B$14:$B$5084,">="&$C9,OUT!$B$14:$B$5084,"<="&DATE(2026,10,17),OUT!$L$14:$L$5084,"<>Adjustment") -> 0.83448 | G9: =D9+E9-F9 -> 1.96974 | H9: =SUMIFS('LAPORAN OPERATION'!$F$2:$F$1000,'LAPORAN OPERATION'!$A$2:$A$1000,DATE(2026,10,17),'LAPORAN OPERATION'!$B$2:$B$1000,"Balance",'LAPORAN OPERATION'!$C$2:$C$1000,IF($A9="Pine","Pinus",$A9),'LAPORAN OPERATION'!$D$2:$D$1000,$B9)+SUMIFS('LAPORAN OPERATION'!$F$2:$F$1000,'LAPORAN OPERATION'!$A$2:$A$1000,DATE(2026,10,17),'LAPORAN OPERATION'!$B$2:$B$1000,"Balance",'LAPORAN OPERATION'!$C$2:$C$1000,IF($A9="Pine","Pinus",$A9),'LAPORAN OPERATION'!$D$2:$D$1000,$B9&" (Grade A)") -> 2.75202 | I9: =ROUND(G9-H9,6) -> -0.78228 | J9: =SUMIFS(INCOMING!$F$2:$F$5000,INCOMING!$C$2:$C$5000,$A9,INCOMING!$D$2:$D$5000,$B9,INCOMING!$B$2:$B$5000,">="&DATE(2026,10,18),INCOMING!$B$2:$B$5000,"<="&DATE(2026,10,21)) -> 0 | K9: =SUMIFS(OUT!$F$14:$F$5084,OUT!$C$14:$C$5084,$A9,OUT!$D$14:$D$5084,$B9,OUT!$B$14:$B$5084,">="&DATE(2026,10,18),OUT!$B$14:$B$5084,"<="&DATE(2026,10,21),OUT!$L$14:$L$5084,"<>Adjustment") -> 1.984545 | L9: =G9+J9-K9 -> -0.014805 | M9: =SUMIFS('LAPORAN OPERATION'!$F$2:$F$1000,'LAPORAN OPERATION'!$A$2:$A$1000,DATE(2026,10,21),'LAPORAN OPERATION'!$B$2:$B$1000,"Balance",'LAPORAN OPERATION'!$C$2:$C$1000,IF($A9="Pine","Pinus",$A9),'LAPORAN OPERATION'!$D$2:$D$1000,$B9)+SUMIFS('LAPORAN OPERATION'!$F$2:$F$1000,'LAPORAN OPERATION'!$A$2:$A$1000,DATE(2026,10,21),'LAPORAN OPERATION'!$B$2:$B$1000,"Balance",'LAPORAN OPERATION'!$C$2:$C$1000,IF($A9="Pine","Pinus",$A9),'LAPORAN OPERATION'!$D$2:$D$1000,$B9&" (Grade A)") -> 0 | N9: =ROUND(L9-M9,6) -> -0.014805 | O9: =SUMIFS(INCOMING!$F$2:$F$5000,INCOMING!$C$2:$C$5000,$A9,INCOMING!$D$2:$D$5000,$B9,INCOMING!$B$2:$B$5000,">="&DATE(2026,10,22),INCOMING!$B$2:$B$5000,"<="&DATE(2026,10,24)) -> 1.997415 | P9: =SUMIFS(OUT!$F$14:$F$5084,OUT!$C$14:$C$5084,$A9,OUT!$D$14:$D$5084,$B9,OUT!$B$14:$B$5084,">="&DATE(2026,10,22),OUT!$B$14:$B$5084,"<="&DATE(2026,10,24),OUT!$L$14:$L$5084,"<>Adjustment") -> 1.24677 | Q9: =L9+O9-P9 -> 0.73584 | R9: =SUMIFS('LAPORAN OPERATION'!$F$2:$F$1000,'LAPORAN OPERATION'!$A$2:$A$1000,DATE(2026,10,24),'LAPORAN OPERATION'!$B$2:$B$1000,"Count",'LAPORAN OPERATION'!$C$2:$C$1000,IF($A9="Pine","Pinus",$A9),'LAPORAN OPERATION'!$D$2:$D$1000,$B9)+SUMIFS('LAPORAN OPERATION'!$F$2:$F$1000,'LAPORAN OPERATION'!$A$2:$A$1000,DATE(2026,10,24),'LAPORAN OPERATION'!$B$2:$B$1000,"Count",'LAPORAN OPERATION'!$C$2:$C$1000,IF($A9="Pine","Pinus",$A9),'LAPORAN OPERATION'!$D$2:$D$1000,$B9&" (Grade A)") -> 0.846945 | S9: =ROUND(Q9-R9,6) -> -0.111105
A10: Teak | B10: 5 | C10: 46310 | D10: =SUMIFS('LAPORAN OPERATION'!$F$2:$F$1000,'LAPORAN OPERATION'!$A$2:$A$1000,DATE(2026,10,14),'LAPORAN OPERATION'!$B$2:$B$1000,"Count",'LAPORAN OPERATION'!$C$2:$C$1000,IF($A10="Pine","Pinus",$A10),'LAPORAN OPERATION'!$D$2:$D$1000,$B10)+SUMIFS('LAPORAN OPERATION'!$F$2:$F$1000,'LAPORAN OPERATION'!$A$2:$A$1000,DATE(2026,10,14),'LAPORAN OPERATION'!$B$2:$B$1000,"Count",'LAPORAN OPERATION'!$C$2:$C$1000,IF($A10="Pine","Pinus",$A10),'LAPORAN OPERATION'!$D$2:$D$1000,$B10&" (Grade A)") -> 0 | E10: =SUMIFS(INCOMING!$F$2:$F$5000,INCOMING!$C$2:$C$5000,$A10,INCOMING!$D$2:$D$5000,$B10,INCOMING!$B$2:$B$5000,">="&$C10,INCOMING!$B$2:$B$5000,"<="&DATE(2026,10,17)) -> 0 | F10: =SUMIFS(OUT!$F$14:$F$5084,OUT!$C$14:$C$5084,$A10,OUT!$D$14:$D$5084,$B10,OUT!$B$14:$B$5084,">="&$C10,OUT!$B$14:$B$5084,"<="&DATE(2026,10,17),OUT!$L$14:$L$5084,"<>Adjustment") -> 0 | G10: =D10+E10-F10 -> 0 | H10: =SUMIFS('LAPORAN OPERATION'!$F$2:$F$1000,'LAPORAN OPERATION'!$A$2:$A$1000,DATE(2026,10,17),'LAPORAN OPERATION'!$B$2:$B$1000,"Balance",'LAPORAN OPERATION'!$C$2:$C$1000,IF($A10="Pine","Pinus",$A10),'LAPORAN OPERATION'!$D$2:$D$1000,$B10)+SUMIFS('LAPORAN OPERATION'!$F$2:$F$1000,'LAPORAN OPERATION'!$A$2:$A$1000,DATE(2026,10,17),'LAPORAN OPERATION'!$B$2:$B$1000,"Balance",'LAPORAN OPERATION'!$C$2:$C$1000,IF($A10="Pine","Pinus",$A10),'LAPORAN OPERATION'!$D$2:$D$1000,$B10&" (Grade A)") -> 0 | I10: =ROUND(G10-H10,6) -> 0 | J10: =SUMIFS(INCOMING!$F$2:$F$5000,INCOMING!$C$2:$C$5000,$A10,INCOMING!$D$2:$D$5000,$B10,INCOMING!$B$2:$B$5000,">="&DATE(2026,10,18),INCOMING!$B$2:$B$5000,"<="&DATE(2026,10,21)) -> 0 | K10: =SUMIFS(OUT!$F$14:$F$5084,OUT!$C$14:$C$5084,$A10,OUT!$D$14:$D$5084,$B10,OUT!$B$14:$B$5084,">="&DATE(2026,10,18),OUT!$B$14:$B$5084,"<="&DATE(2026,10,21),OUT!$L$14:$L$5084,"<>Adjustment") -> 0 | L10: =G10+J10-K10 -> 0 | M10: =SUMIFS('LAPORAN OPERATION'!$F$2:$F$1000,'LAPORAN OPERATION'!$A$2:$A$1000,DATE(2026,10,21),'LAPORAN OPERATION'!$B$2:$B$1000,"Balance",'LAPORAN OPERATION'!$C$2:$C$1000,IF($A10="Pine","Pinus",$A10),'LAPORAN OPERATION'!$D$2:$D$1000,$B10)+SUMIFS('LAPORAN OPERATION'!$F$2:$F$1000,'LAPORAN OPERATION'!$A$2:$A$1000,DATE(2026,10,21),'LAPORAN OPERATION'!$B$2:$B$1000,"Balance",'LAPORAN OPERATION'!$C$2:$C$1000,IF($A10="Pine","Pinus",$A10),'LAPORAN OPERATION'!$D$2:$D$1000,$B10&" (Grade A)") -> 0 | N10: =ROUND(L10-M10,6) -> 0 | O10: =SUMIFS(INCOMING!$F$2:$F$5000,INCOMING!$C$2:$C$5000,$A10,INCOMING!$D$2:$D$5000,$B10,INCOMING!$B$2:$B$5000,">="&DATE(2026,10,22),INCOMING!$B$2:$B$5000,"<="&DATE(2026,10,24)) -> 0 | P10: =SUMIFS(OUT!$F$14:$F$5084,OUT!$C$14:$C$5084,$A10,OUT!$D$14:$D$5084,$B10,OUT!$B$14:$B$5084,">="&DATE(2026,10,22),OUT!$B$14:$B$5084,"<="&DATE(2026,10,24),OUT!$L$14:$L$5084,"<>Adjustment") -> 0 | Q10: =L10+O10-P10 -> 0 | R10: =SUMIFS('LAPORAN OPERATION'!$F$2:$F$1000,'LAPORAN OPERATION'!$A$2:$A$1000,DATE(2026,10,24),'LAPORAN OPERATION'!$B$2:$B$1000,"Count",'LAPORAN OPERATION'!$C$2:$C$1000,IF($A10="Pine","Pinus",$A10),'LAPORAN OPERATION'!$D$2:$D$1000,$B10)+SUMIFS('LAPORAN OPERATION'!$F$2:$F$1000,'LAPORAN OPERATION'!$A$2:$A$1000,DATE(2026,10,24),'LAPORAN OPERATION'!$B$2:$B$1000,"Count",'LAPORAN OPERATION'!$C$2:$C$1000,IF($A10="Pine","Pinus",$A10),'LAPORAN OPERATION'!$D$2:$D$1000,$B10&" (Grade A)") -> 0 | S10: =ROUND(Q10-R10,6) -> 0
A11: Teak | B11: 5.5 | C11: 46310 | D11: =SUMIFS('LAPORAN OPERATION'!$F$2:$F$1000,'LAPORAN OPERATION'!$A$2:$A$1000,DATE(2026,10,14),'LAPORAN OPERATION'!$B$2:$B$1000,"Count",'LAPORAN OPERATION'!$C$2:$C$1000,IF($A11="Pine","Pinus",$A11),'LAPORAN OPERATION'!$D$2:$D$1000,$B11)+SUMIFS('LAPORAN OPERATION'!$F$2:$F$1000,'LAPORAN OPERATION'!$A$2:$A$1000,DATE(2026,10,14),'LAPORAN OPERATION'!$B$2:$B$1000,"Count",'LAPORAN OPERATION'!$C$2:$C$1000,IF($A11="Pine","Pinus",$A11),'LAPORAN OPERATION'!$D$2:$D$1000,$B11&" (Grade A)") -> 0 | E11: =SUMIFS(INCOMING!$F$2:$F$5000,INCOMING!$C$2:$C$5000,$A11,INCOMING!$D$2:$D$5000,$B11,INCOMING!$B$2:$B$5000,">="&$C11,INCOMING!$B$2:$B$5000,"<="&DATE(2026,10,17)) -> 0 | F11: =SUMIFS(OUT!$F$14:$F$5084,OUT!$C$14:$C$5084,$A11,OUT!$D$14:$D$5084,$B11,OUT!$B$14:$B$5084,">="&$C11,OUT!$B$14:$B$5084,"<="&DATE(2026,10,17),OUT!$L$14:$L$5084,"<>Adjustment") -> 0 | G11: =D11+E11-F11 -> 0 | H11: =SUMIFS('LAPORAN OPERATION'!$F$2:$F$1000,'LAPORAN OPERATION'!$A$2:$A$1000,DATE(2026,10,17),'LAPORAN OPERATION'!$B$2:$B$1000,"Balance",'LAPORAN OPERATION'!$C$2:$C$1000,IF($A11="Pine","Pinus",$A11),'LAPORAN OPERATION'!$D$2:$D$1000,$B11)+SUMIFS('LAPORAN OPERATION'!$F$2:$F$1000,'LAPORAN OPERATION'!$A$2:$A$1000,DATE(2026,10,17),'LAPORAN OPERATION'!$B$2:$B$1000,"Balance",'LAPORAN OPERATION'!$C$2:$C$1000,IF($A11="Pine","Pinus",$A11),'LAPORAN OPERATION'!$D$2:$D$1000,$B11&" (Grade A)") -> 0 | I11: =ROUND(G11-H11,6) -> 0 | J11: =SUMIFS(INCOMING!$F$2:$F$5000,INCOMING!$C$2:$C$5000,$A11,INCOMING!$D$2:$D$5000,$B11,INCOMING!$B$2:$B$5000,">="&DATE(2026,10,18),INCOMING!$B$2:$B$5000,"<="&DATE(2026,10,21)) -> 0 | K11: =SUMIFS(OUT!$F$14:$F$5084,OUT!$C$14:$C$5084,$A11,OUT!$D$14:$D$5084,$B11,OUT!$B$14:$B$5084,">="&DATE(2026,10,18),OUT!$B$14:$B$5084,"<="&DATE(2026,10,21),OUT!$L$14:$L$5084,"<>Adjustment") -> 0 | L11: =G11+J11-K11 -> 0 | M11: =SUMIFS('LAPORAN OPERATION'!$F$2:$F$1000,'LAPORAN OPERATION'!$A$2:$A$1000,DATE(2026,10,21),'LAPORAN OPERATION'!$B$2:$B$1000,"Balance",'LAPORAN OPERATION'!$C$2:$C$1000,IF($A11="Pine","Pinus",$A11),'LAPORAN OPERATION'!$D$2:$D$1000,$B11)+SUMIFS('LAPORAN OPERATION'!$F$2:$F$1000,'LAPORAN OPERATION'!$A$2:$A$1000,DATE(2026,10,21),'LAPORAN OPERATION'!$B$2:$B$1000,"Balance",'LAPORAN OPERATION'!$C$2:$C$1000,IF($A11="Pine","Pinus",$A11),'LAPORAN OPERATION'!$D$2:$D$1000,$B11&" (Grade A)") -> 0 | N11: =ROUND(L11-M11,6) -> 0 | O11: =SUMIFS(INCOMING!$F$2:$F$5000,INCOMING!$C$2:$C$5000,$A11,INCOMING!$D$2:$D$5000,$B11,INCOMING!$B$2:$B$5000,">="&DATE(2026,10,22),INCOMING!$B$2:$B$5000,"<="&DATE(2026,10,24)) -> 0 | P11: =SUMIFS(OUT!$F$14:$F$5084,OUT!$C$14:$C$5084,$A11,OUT!$D$14:$D$5084,$B11,OUT!$B$14:$B$5084,">="&DATE(2026,10,22),OUT!$B$14:$B$5084,"<="&DATE(2026,10,24),OUT!$L$14:$L$5084,"<>Adjustment") -> 0 | Q11: =L11+O11-P11 -> 0 | R11: =SUMIFS('LAPORAN OPERATION'!$F$2:$F$1000,'LAPORAN OPERATION'!$A$2:$A$1000,DATE(2026,10,24),'LAPORAN OPERATION'!$B$2:$B$1000,"Count",'LAPORAN OPERATION'!$C$2:$C$1000,IF($A11="Pine","Pinus",$A11),'LAPORAN OPERATION'!$D$2:$D$1000,$B11)+SUMIFS('LAPORAN OPERATION'!$F$2:$F$1000,'LAPORAN OPERATION'!$A$2:$A$1000,DATE(2026,10,24),'LAPORAN OPERATION'!$B$2:$B$1000,"Count",'LAPORAN OPERATION'!$C$2:$C$1000,IF($A11="Pine","Pinus",$A11),'LAPORAN OPERATION'!$D$2:$D$1000,$B11&" (Grade A)") -> 0 | S11: =ROUND(Q11-R11,6) -> 0
A12: Teak | B12: 6 | C12: 46310 | D12: =SUMIFS('LAPORAN OPERATION'!$F$2:$F$1000,'LAPORAN OPERATION'!$A$2:$A$1000,DATE(2026,10,14),'LAPORAN OPERATION'!$B$2:$B$1000,"Count",'LAPORAN OPERATION'!$C$2:$C$1000,IF($A12="Pine","Pinus",$A12),'LAPORAN OPERATION'!$D$2:$D$1000,$B12)+SUMIFS('LAPORAN OPERATION'!$F$2:$F$1000,'LAPORAN OPERATION'!$A$2:$A$1000,DATE(2026,10,14),'LAPORAN OPERATION'!$B$2:$B$1000,"Count",'LAPORAN OPERATION'!$C$2:$C$1000,IF($A12="Pine","Pinus",$A12),'LAPORAN OPERATION'!$D$2:$D$1000,$B12&" (Grade A)") -> 5.36976 | E12: =SUMIFS(INCOMING!$F$2:$F$5000,INCOMING!$C$2:$C$5000,$A12,INCOMING!$D$2:$D$5000,$B12,INCOMING!$B$2:$B$5000,">="&$C12,INCOMING!$B$2:$B$5000,"<="&DATE(2026,10,17)) -> 0 | F12: =SUMIFS(OUT!$F$14:$F$5084,OUT!$C$14:$C$5084,$A12,OUT!$D$14:$D$5084,$B12,OUT!$B$14:$B$5084,">="&$C12,OUT!$B$14:$B$5084,"<="&DATE(2026,10,17),OUT!$L$14:$L$5084,"<>Adjustment") -> 0 | G12: =D12+E12-F12 -> 5.36976 | H12: =SUMIFS('LAPORAN OPERATION'!$F$2:$F$1000,'LAPORAN OPERATION'!$A$2:$A$1000,DATE(2026,10,17),'LAPORAN OPERATION'!$B$2:$B$1000,"Balance",'LAPORAN OPERATION'!$C$2:$C$1000,IF($A12="Pine","Pinus",$A12),'LAPORAN OPERATION'!$D$2:$D$1000,$B12)+SUMIFS('LAPORAN OPERATION'!$F$2:$F$1000,'LAPORAN OPERATION'!$A$2:$A$1000,DATE(2026,10,17),'LAPORAN OPERATION'!$B$2:$B$1000,"Balance",'LAPORAN OPERATION'!$C$2:$C$1000,IF($A12="Pine","Pinus",$A12),'LAPORAN OPERATION'!$D$2:$D$1000,$B12&" (Grade A)") -> 5.36976 | I12: =ROUND(G12-H12,6) -> 0 | J12: =SUMIFS(INCOMING!$F$2:$F$5000,INCOMING!$C$2:$C$5000,$A12,INCOMING!$D$2:$D$5000,$B12,INCOMING!$B$2:$B$5000,">="&DATE(2026,10,18),INCOMING!$B$2:$B$5000,"<="&DATE(2026,10,21)) -> 0 | K12: =SUMIFS(OUT!$F$14:$F$5084,OUT!$C$14:$C$5084,$A12,OUT!$D$14:$D$5084,$B12,OUT!$B$14:$B$5084,">="&DATE(2026,10,18),OUT!$B$14:$B$5084,"<="&DATE(2026,10,21),OUT!$L$14:$L$5084,"<>Adjustment") -> 0.83052 | L12: =G12+J12-K12 -> 4.53924 | M12: =SUMIFS('LAPORAN OPERATION'!$F$2:$F$1000,'LAPORAN OPERATION'!$A$2:$A$1000,DATE(2026,10,21),'LAPORAN OPERATION'!$B$2:$B$1000,"Balance",'LAPORAN OPERATION'!$C$2:$C$1000,IF($A12="Pine","Pinus",$A12),'LAPORAN OPERATION'!$D$2:$D$1000,$B12)+SUMIFS('LAPORAN OPERATION'!$F$2:$F$1000,'LAPORAN OPERATION'!$A$2:$A$1000,DATE(2026,10,21),'LAPORAN OPERATION'!$B$2:$B$1000,"Balance",'LAPORAN OPERATION'!$C$2:$C$1000,IF($A12="Pine","Pinus",$A12),'LAPORAN OPERATION'!$D$2:$D$1000,$B12&" (Grade A)") -> 4.53924 | N12: =ROUND(L12-M12,6) -> 0 | O12: =SUMIFS(INCOMING!$F$2:$F$5000,INCOMING!$C$2:$C$5000,$A12,INCOMING!$D$2:$D$5000,$B12,INCOMING!$B$2:$B$5000,">="&DATE(2026,10,22),INCOMING!$B$2:$B$5000,"<="&DATE(2026,10,24)) -> 0 | P12: =SUMIFS(OUT!$F$14:$F$5084,OUT!$C$14:$C$5084,$A12,OUT!$D$14:$D$5084,$B12,OUT!$B$14:$B$5084,">="&DATE(2026,10,22),OUT!$B$14:$B$5084,"<="&DATE(2026,10,24),OUT!$L$14:$L$5084,"<>Adjustment") -> 0 | Q12: =L12+O12-P12 -> 4.53924 | R12: =SUMIFS('LAPORAN OPERATION'!$F$2:$F$1000,'LAPORAN OPERATION'!$A$2:$A$1000,DATE(2026,10,24),'LAPORAN OPERATION'!$B$2:$B$1000,"Count",'LAPORAN OPERATION'!$C$2:$C$1000,IF($A12="Pine","Pinus",$A12),'LAPORAN OPERATION'!$D$2:$D$1000,$B12)+SUMIFS('LAPORAN OPERATION'!$F$2:$F$1000,'LAPORAN OPERATION'!$A$2:$A$1000,DATE(2026,10,24),'LAPORAN OPERATION'!$B$2:$B$1000,"Count",'LAPORAN OPERATION'!$C$2:$C$1000,IF($A12="Pine","Pinus",$A12),'LAPORAN OPERATION'!$D$2:$D$1000,$B12&" (Grade A)") -> 5.03256 | S12: =ROUND(Q12-R12,6) -> -0.49332
A13: Teak | B13: 7 | C13: 46310 | D13: =SUMIFS('LAPORAN OPERATION'!$F$2:$F$1000,'LAPORAN OPERATION'!$A$2:$A$1000,DATE(2026,10,14),'LAPORAN OPERATION'!$B$2:$B$1000,"Count",'LAPORAN OPERATION'!$C$2:$C$1000,IF($A13="Pine","Pinus",$A13),'LAPORAN OPERATION'!$D$2:$D$1000,$B13)+SUMIFS('LAPORAN OPERATION'!$F$2:$F$1000,'LAPORAN OPERATION'!$A$2:$A$1000,DATE(2026,10,14),'LAPORAN OPERATION'!$B$2:$B$1000,"Count",'LAPORAN OPERATION'!$C$2:$C$1000,IF($A13="Pine","Pinus",$A13),'LAPORAN OPERATION'!$D$2:$D$1000,$B13&" (Grade A)") -> 7.51863 | E13: =SUMIFS(INCOMING!$F$2:$F$5000,INCOMING!$C$2:$C$5000,$A13,INCOMING!$D$2:$D$5000,$B13,INCOMING!$B$2:$B$5000,">="&$C13,INCOMING!$B$2:$B$5000,"<="&DATE(2026,10,17)) -> 0 | F13: =SUMIFS(OUT!$F$14:$F$5084,OUT!$C$14:$C$5084,$A13,OUT!$D$14:$D$5084,$B13,OUT!$B$14:$B$5084,">="&$C13,OUT!$B$14:$B$5084,"<="&DATE(2026,10,17),OUT!$L$14:$L$5084,"<>Adjustment") -> 0.1442 | G13: =D13+E13-F13 -> 7.37443 | H13: =SUMIFS('LAPORAN OPERATION'!$F$2:$F$1000,'LAPORAN OPERATION'!$A$2:$A$1000,DATE(2026,10,17),'LAPORAN OPERATION'!$B$2:$B$1000,"Balance",'LAPORAN OPERATION'!$C$2:$C$1000,IF($A13="Pine","Pinus",$A13),'LAPORAN OPERATION'!$D$2:$D$1000,$B13)+SUMIFS('LAPORAN OPERATION'!$F$2:$F$1000,'LAPORAN OPERATION'!$A$2:$A$1000,DATE(2026,10,17),'LAPORAN OPERATION'!$B$2:$B$1000,"Balance",'LAPORAN OPERATION'!$C$2:$C$1000,IF($A13="Pine","Pinus",$A13),'LAPORAN OPERATION'!$D$2:$D$1000,$B13&" (Grade A)") -> 7.51863 | I13: =ROUND(G13-H13,6) -> -0.1442 | J13: =SUMIFS(INCOMING!$F$2:$F$5000,INCOMING!$C$2:$C$5000,$A13,INCOMING!$D$2:$D$5000,$B13,INCOMING!$B$2:$B$5000,">="&DATE(2026,10,18),INCOMING!$B$2:$B$5000,"<="&DATE(2026,10,21)) -> 0 | K13: =SUMIFS(OUT!$F$14:$F$5084,OUT!$C$14:$C$5084,$A13,OUT!$D$14:$D$5084,$B13,OUT!$B$14:$B$5084,">="&DATE(2026,10,18),OUT!$B$14:$B$5084,"<="&DATE(2026,10,21),OUT!$L$14:$L$5084,"<>Adjustment") -> 0 | L13: =G13+J13-K13 -> 7.37443 | M13: =SUMIFS('LAPORAN OPERATION'!$F$2:$F$1000,'LAPORAN OPERATION'!$A$2:$A$1000,DATE(2026,10,21),'LAPORAN OPERATION'!$B$2:$B$1000,"Balance",'LAPORAN OPERATION'!$C$2:$C$1000,IF($A13="Pine","Pinus",$A13),'LAPORAN OPERATION'!$D$2:$D$1000,$B13)+SUMIFS('LAPORAN OPERATION'!$F$2:$F$1000,'LAPORAN OPERATION'!$A$2:$A$1000,DATE(2026,10,21),'LAPORAN OPERATION'!$B$2:$B$1000,"Balance",'LAPORAN OPERATION'!$C$2:$C$1000,IF($A13="Pine","Pinus",$A13),'LAPORAN OPERATION'!$D$2:$D$1000,$B13&" (Grade A)") -> 7.831026 | N13: =ROUND(L13-M13,6) -> -0.456596 | O13: =SUMIFS(INCOMING!$F$2:$F$5000,INCOMING!$C$2:$C$5000,$A13,INCOMING!$D$2:$D$5000,$B13,INCOMING!$B$2:$B$5000,">="&DATE(2026,10,22),INCOMING!$B$2:$B$5000,"<="&DATE(2026,10,24)) -> 0 | P13: =SUMIFS(OUT!$F$14:$F$5084,OUT!$C$14:$C$5084,$A13,OUT!$D$14:$D$5084,$B13,OUT!$B$14:$B$5084,">="&DATE(2026,10,22),OUT!$B$14:$B$5084,"<="&DATE(2026,10,24),OUT!$L$14:$L$5084,"<>Adjustment") -> 1.1571 | Q13: =L13+O13-P13 -> 6.21733 | R13: =SUMIFS('LAPORAN OPERATION'!$F$2:$F$1000,'LAPORAN OPERATION'!$A$2:$A$1000,DATE(2026,10,24),'LAPORAN OPERATION'!$B$2:$B$1000,"Count",'LAPORAN OPERATION'!$C$2:$C$1000,IF($A13="Pine","Pinus",$A13),'LAPORAN OPERATION'!$D$2:$D$1000,$B13)+SUMIFS('LAPORAN OPERATION'!$F$2:$F$1000,'LAPORAN OPERATION'!$A$2:$A$1000,DATE(2026,10,24),'LAPORAN OPERATION'!$B$2:$B$1000,"Count",'LAPORAN OPERATION'!$C$2:$C$1000,IF($A13="Pine","Pinus",$A13),'LAPORAN OPERATION'!$D$2:$D$1000,$B13&" (Grade A)") -> 6.982416 | S13: =ROUND(Q13-R13,6) -> -0.765086
A14: Teak | B14: 8 | C14: 46310 | D14: =SUMIFS('LAPORAN OPERATION'!$F$2:$F$1000,'LAPORAN OPERATION'!$A$2:$A$1000,DATE(2026,10,14),'LAPORAN OPERATION'!$B$2:$B$1000,"Count",'LAPORAN OPERATION'!$C$2:$C$1000,IF($A14="Pine","Pinus",$A14),'LAPORAN OPERATION'!$D$2:$D$1000,$B14)+SUMIFS('LAPORAN OPERATION'!$F$2:$F$1000,'LAPORAN OPERATION'!$A$2:$A$1000,DATE(2026,10,14),'LAPORAN OPERATION'!$B$2:$B$1000,"Count",'LAPORAN OPERATION'!$C$2:$C$1000,IF($A14="Pine","Pinus",$A14),'LAPORAN OPERATION'!$D$2:$D$1000,$B14&" (Grade A)") -> 2.36528 | E14: =SUMIFS(INCOMING!$F$2:$F$5000,INCOMING!$C$2:$C$5000,$A14,INCOMING!$D$2:$D$5000,$B14,INCOMING!$B$2:$B$5000,">="&$C14,INCOMING!$B$2:$B$5000,"<="&DATE(2026,10,17)) -> 0 | F14: =SUMIFS(OUT!$F$14:$F$5084,OUT!$C$14:$C$5084,$A14,OUT!$D$14:$D$5084,$B14,OUT!$B$14:$B$5084,">="&$C14,OUT!$B$14:$B$5084,"<="&DATE(2026,10,17),OUT!$L$14:$L$5084,"<>Adjustment") -> 0 | G14: =D14+E14-F14 -> 2.36528 | H14: =SUMIFS('LAPORAN OPERATION'!$F$2:$F$1000,'LAPORAN OPERATION'!$A$2:$A$1000,DATE(2026,10,17),'LAPORAN OPERATION'!$B$2:$B$1000,"Balance",'LAPORAN OPERATION'!$C$2:$C$1000,IF($A14="Pine","Pinus",$A14),'LAPORAN OPERATION'!$D$2:$D$1000,$B14)+SUMIFS('LAPORAN OPERATION'!$F$2:$F$1000,'LAPORAN OPERATION'!$A$2:$A$1000,DATE(2026,10,17),'LAPORAN OPERATION'!$B$2:$B$1000,"Balance",'LAPORAN OPERATION'!$C$2:$C$1000,IF($A14="Pine","Pinus",$A14),'LAPORAN OPERATION'!$D$2:$D$1000,$B14&" (Grade A)") -> 2.36528 | I14: =ROUND(G14-H14,6) -> 0 | J14: =SUMIFS(INCOMING!$F$2:$F$5000,INCOMING!$C$2:$C$5000,$A14,INCOMING!$D$2:$D$5000,$B14,INCOMING!$B$2:$B$5000,">="&DATE(2026,10,18),INCOMING!$B$2:$B$5000,"<="&DATE(2026,10,21)) -> 0 | K14: =SUMIFS(OUT!$F$14:$F$5084,OUT!$C$14:$C$5084,$A14,OUT!$D$14:$D$5084,$B14,OUT!$B$14:$B$5084,">="&DATE(2026,10,18),OUT!$B$14:$B$5084,"<="&DATE(2026,10,21),OUT!$L$14:$L$5084,"<>Adjustment") -> 0 | L14: =G14+J14-K14 -> 2.36528 | M14: =SUMIFS('LAPORAN OPERATION'!$F$2:$F$1000,'LAPORAN OPERATION'!$A$2:$A$1000,DATE(2026,10,21),'LAPORAN OPERATION'!$B$2:$B$1000,"Balance",'LAPORAN OPERATION'!$C$2:$C$1000,IF($A14="Pine","Pinus",$A14),'LAPORAN OPERATION'!$D$2:$D$1000,$B14)+SUMIFS('LAPORAN OPERATION'!$F$2:$F$1000,'LAPORAN OPERATION'!$A$2:$A$1000,DATE(2026,10,21),'LAPORAN OPERATION'!$B$2:$B$1000,"Balance",'LAPORAN OPERATION'!$C$2:$C$1000,IF($A14="Pine","Pinus",$A14),'LAPORAN OPERATION'!$D$2:$D$1000,$B14&" (Grade A)") -> 2.36528 | N14: =ROUND(L14-M14,6) -> 0 | O14: =SUMIFS(INCOMING!$F$2:$F$5000,INCOMING!$C$2:$C$5000,$A14,INCOMING!$D$2:$D$5000,$B14,INCOMING!$B$2:$B$5000,">="&DATE(2026,10,22),INCOMING!$B$2:$B$5000,"<="&DATE(2026,10,24)) -> 0 | P14: =SUMIFS(OUT!$F$14:$F$5084,OUT!$C$14:$C$5084,$A14,OUT!$D$14:$D$5084,$B14,OUT!$B$14:$B$5084,">="&DATE(2026,10,22),OUT!$B$14:$B$5084,"<="&DATE(2026,10,24),OUT!$L$14:$L$5084,"<>Adjustment") -> 0 | Q14: =L14+O14-P14 -> 2.36528 | R14: =SUMIFS('LAPORAN OPERATION'!$F$2:$F$1000,'LAPORAN OPERATION'!$A$2:$A$1000,DATE(2026,10,24),'LAPORAN OPERATION'!$B$2:$B$1000,"Count",'LAPORAN OPERATION'!$C$2:$C$1000,IF($A14="Pine","Pinus",$A14),'LAPORAN OPERATION'!$D$2:$D$1000,$B14)+SUMIFS('LAPORAN OPERATION'!$F$2:$F$1000,'LAPORAN OPERATION'!$A$2:$A$1000,DATE(2026,10,24),'LAPORAN OPERATION'!$B$2:$B$1000,"Count",'LAPORAN OPERATION'!$C$2:$C$1000,IF($A14="Pine","Pinus",$A14),'LAPORAN OPERATION'!$D$2:$D$1000,$B14&" (Grade A)") -> 2.30008 | S14: =ROUND(Q14-R14,6) -> 0.0652
A15: Total Teak | D15: =SUM(D5:D14) -> 19.143315 | E15: =SUM(E5:E14) -> 0 | F15: =SUM(F5:F14) -> 1.877045 | G15: =SUM(G5:G14) -> 17.26627 | H15: =SUM(H5:H14) -> 18.866765 | I15: =SUM(I5:I14) -> -1.600495 | J15: =SUM(J5:J14) -> 1.894305 | K15: =SUM(K5:K14) -> 3.074205 | ... S15: =SUM(S5:S14) -> -1.201711
A17: Sungkai | B17: 2.5 | C17: 46310 | D17: =SUMIFS('LAPORAN OPERATION'!$F$2:$F$1000,'LAPORAN OPERATION'!$A$2:$A$1000,DATE(2026,10,14),'LAPORAN OPERATION'!$B$2:$B$1000,"Count",'LAPORAN OPERATION'!$C$2:$C$1000,IF($A17="Pine","Pinus",$A17),'LAPORAN OPERATION'!$D$2:$D$1000,$B17)+SUMIFS('LAPORAN OPERATION'!$F$2:$F$1000,'LAPORAN OPERATION'!$A$2:$A$1000,DATE(2026,10,14),'LAPORAN OPERATION'!$B$2:$B$1000,"Count",'LAPORAN OPERATION'!$C$2:$C$1000,IF($A17="Pine","Pinus",$A17),'LAPORAN OPERATION'!$D$2:$D$1000,$B17&" (Grade A)") -> 0.078225 | E17: =SUMIFS(INCOMING!$F$2:$F$5000,INCOMING!$C$2:$C$5000,$A17,INCOMING!$D$2:$D$5000,$B17,INCOMING!$B$2:$B$5000,">="&$C17,INCOMING!$B$2:$B$5000,"<="&DATE(2026,10,17)) -> 0 | F17: =SUMIFS(OUT!$F$14:$F$5084,OUT!$C$14:$C$5084,$A17,OUT!$D$14:$D$5084,$B17,OUT!$B$14:$B$5084,">="&$C17,OUT!$B$14:$B$5084,"<="&DATE(2026,10,17),OUT!$L$14:$L$5084,"<>Adjustment") -> 0 | G17: =D17+E17-F17 -> 0.078225 | H17: =SUMIFS('LAPORAN OPERATION'!$F$2:$F$1000,'LAPORAN OPERATION'!$A$2:$A$1000,DATE(2026,10,17),'LAPORAN OPERATION'!$B$2:$B$1000,"Balance",'LAPORAN OPERATION'!$C$2:$C$1000,IF($A17="Pine","Pinus",$A17),'LAPORAN OPERATION'!$D$2:$D$1000,$B17)+SUMIFS('LAPORAN OPERATION'!$F$2:$F$1000,'LAPORAN OPERATION'!$A$2:$A$1000,DATE(2026,10,17),'LAPORAN OPERATION'!$B$2:$B$1000,"Balance",'LAPORAN OPERATION'!$C$2:$C$1000,IF($A17="Pine","Pinus",$A17),'LAPORAN OPERATION'!$D$2:$D$1000,$B17&" (Grade A)") -> 0.078225 | I17: =ROUND(G17-H17,6) -> 0 | J17: =SUMIFS(INCOMING!$F$2:$F$5000,INCOMING!$C$2:$C$5000,$A17,INCOMING!$D$2:$D$5000,$B17,INCOMING!$B$2:$B$5000,">="&DATE(2026,10,18),INCOMING!$B$2:$B$5000,"<="&DATE(2026,10,21)) -> 0 | K17: =SUMIFS(OUT!$F$14:$F$5084,OUT!$C$14:$C$5084,$A17,OUT!$D$14:$D$5084,$B17,OUT!$B$14:$B$5084,">="&DATE(2026,10,18),OUT!$B$14:$B$5084,"<="&DATE(2026,10,21),OUT!$L$14:$L$5084,"<>Adjustment") -> 0 | L17: =G17+J17-K17 -> 0.078225 | M17: =SUMIFS('LAPORAN OPERATION'!$F$2:$F$1000,'LAPORAN OPERATION'!$A$2:$A$1000,DATE(2026,10,21),'LAPORAN OPERATION'!$B$2:$B$1000,"Balance",'LAPORAN OPERATION'!$C$2:$C$1000,IF($A17="Pine","Pinus",$A17),'LAPORAN OPERATION'!$D$2:$D$1000,$B17)+SUMIFS('LAPORAN OPERATION'!$F$2:$F$1000,'LAPORAN OPERATION'!$A$2:$A$1000,DATE(2026,10,21),'LAPORAN OPERATION'!$B$2:$B$1000,"Balance",'LAPORAN OPERATION'!$C$2:$C$1000,IF($A17="Pine","Pinus",$A17),'LAPORAN OPERATION'!$D$2:$D$1000,$B17&" (Grade A)") -> 0.078225 | N17: =ROUND(L17-M17,6) -> 0 | O17: =SUMIFS(INCOMING!$F$2:$F$5000,INCOMING!$C$2:$C$5000,$A17,INCOMING!$D$2:$D$5000,$B17,INCOMING!$B$2:$B$5000,">="&DATE(2026,10,22),INCOMING!$B$2:$B$5000,"<="&DATE(2026,10,24)) -> 0 | P17: =SUMIFS(OUT!$F$14:$F$5084,OUT!$C$14:$C$5084,$A17,OUT!$D$14:$D$5084,$B17,OUT!$B$14:$B$5084,">="&DATE(2026,10,22),OUT!$B$14:$B$5084,"<="&DATE(2026,10,24),OUT!$L$14:$L$5084,"<>Adjustment") -> 0 | Q17: =L17+O17-P17 -> 0.078225 | R17: =SUMIFS('LAPORAN OPERATION'!$F$2:$F$1000,'LAPORAN OPERATION'!$A$2:$A$1000,DATE(2026,10,24),'LAPORAN OPERATION'!$B$2:$B$1000,"Count",'LAPORAN OPERATION'!$C$2:$C$1000,IF($A17="Pine","Pinus",$A17),'LAPORAN OPERATION'!$D$2:$D$1000,$B17)+SUMIFS('LAPORAN OPERATION'!$F$2:$F$1000,'LAPORAN OPERATION'!$A$2:$A$1000,DATE(2026,10,24),'LAPORAN OPERATION'!$B$2:$B$1000,"Count",'LAPORAN OPERATION'!$C$2:$C$1000,IF($A17="Pine","Pinus",$A17),'LAPORAN OPERATION'!$D$2:$D$1000,$B17&" (Grade A)") -> 0.078225 | S17: =ROUND(Q17-R17,6) -> 0
A18: Sungkai | B18: 3 | C18: 46310 | D18: =SUMIFS('LAPORAN OPERATION'!$F$2:$F$1000,'LAPORAN OPERATION'!$A$2:$A$1000,DATE(2026,10,14),'LAPORAN OPERATION'!$B$2:$B$1000,"Count",'LAPORAN OPERATION'!$C$2:$C$1000,IF($A18="Pine","Pinus",$A18),'LAPORAN OPERATION'!$D$2:$D$1000,$B18)+SUMIFS('LAPORAN OPERATION'!$F$2:$F$1000,'LAPORAN OPERATION'!$A$2:$A$1000,DATE(2026,10,14),'LAPORAN OPERATION'!$B$2:$B$1000,"Count",'LAPORAN OPERATION'!$C$2:$C$1000,IF($A18="Pine","Pinus",$A18),'LAPORAN OPERATION'!$D$2:$D$1000,$B18&" (Grade A)") -> 1.694871 | E18: =SUMIFS(INCOMING!$F$2:$F$5000,INCOMING!$C$2:$C$5000,$A18,INCOMING!$D$2:$D$5000,$B18,INCOMING!$B$2:$B$5000,">="&$C18,INCOMING!$B$2:$B$5000,"<="&DATE(2026,10,17)) -> 0 | F18: =SUMIFS(OUT!$F$14:$F$5084,OUT!$C$14:$C$5084,$A18,OUT!$D$14:$D$5084,$B18,OUT!$B$14:$B$5084,">="&$C18,OUT!$B$14:$B$5084,"<="&DATE(2026,10,17),OUT!$L$14:$L$5084,"<>Adjustment") -> 0 | G18: =D18+E18-F18 -> 1.694871 | H18: =SUMIFS('LAPORAN OPERATION'!$F$2:$F$1000,'LAPORAN OPERATION'!$A$2:$A$1000,DATE(2026,10,17),'LAPORAN OPERATION'!$B$2:$B$1000,"Balance",'LAPORAN OPERATION'!$C$2:$C$1000,IF($A18="Pine","Pinus",$A18),'LAPORAN OPERATION'!$D$2:$D$1000,$B18)+SUMIFS('LAPORAN OPERATION'!$F$2:$F$1000,'LAPORAN OPERATION'!$A$2:$A$1000,DATE(2026,10,17),'LAPORAN OPERATION'!$B$2:$B$1000,"Balance",'LAPORAN OPERATION'!$C$2:$C$1000,IF($A18="Pine","Pinus",$A18),'LAPORAN OPERATION'!$D$2:$D$1000,$B18&" (Grade A)") -> 1.694871 | I18: =ROUND(G18-H18,6) -> 0 | J18: =SUMIFS(INCOMING!$F$2:$F$5000,INCOMING!$C$2:$C$5000,$A18,INCOMING!$D$2:$D$5000,$B18,INCOMING!$B$2:$B$5000,">="&DATE(2026,10,18),INCOMING!$B$2:$B$5000,"<="&DATE(2026,10,21)) -> 0 | K18: =SUMIFS(OUT!$F$14:$F$5084,OUT!$C$14:$C$5084,$A18,OUT!$D$14:$D$5084,$B18,OUT!$B$14:$B$5084,">="&DATE(2026,10,18),OUT!$B$14:$B$5084,"<="&DATE(2026,10,21),OUT!$L$14:$L$5084,"<>Adjustment") -> 0.30759 | L18: =G18+J18-K18 -> 1.387281 | M18: =SUMIFS('LAPORAN OPERATION'!$F$2:$F$1000,'LAPORAN OPERATION'!$A$2:$A$1000,DATE(2026,10,21),'LAPORAN OPERATION'!$B$2:$B$1000,"Balance",'LAPORAN OPERATION'!$C$2:$C$1000,IF($A18="Pine","Pinus",$A18),'LAPORAN OPERATION'!$D$2:$D$1000,$B18)+SUMIFS('LAPORAN OPERATION'!$F$2:$F$1000,'LAPORAN OPERATION'!$A$2:$A$1000,DATE(2026,10,21),'LAPORAN OPERATION'!$B$2:$B$1000,"Balance",'LAPORAN OPERATION'!$C$2:$C$1000,IF($A18="Pine","Pinus",$A18),'LAPORAN OPERATION'!$D$2:$D$1000,$B18&" (Grade A)") -> 1.387281 | N18: =ROUND(L18-M18,6) -> 0 | O18: =SUMIFS(INCOMING!$F$2:$F$5000,INCOMING!$C$2:$C$5000,$A18,INCOMING!$D$2:$D$5000,$B18,INCOMING!$B$2:$B$5000,">="&DATE(2026,10,22),INCOMING!$B$2:$B$5000,"<="&DATE(2026,10,24)) -> 0 | P18: =SUMIFS(OUT!$F$14:$F$5084,OUT!$C$14:$C$5084,$A18,OUT!$D$14:$D$5084,$B18,OUT!$B$14:$B$5084,">="&DATE(2026,10,22),OUT!$B$14:$B$5084,"<="&DATE(2026,10,24),OUT!$L$14:$L$5084,"<>Adjustment") -> 0 | Q18: =L18+O18-P18 -> 1.387281 | R18: =SUMIFS('LAPORAN OPERATION'!$F$2:$F$1000,'LAPORAN OPERATION'!$A$2:$A$1000,DATE(2026,10,24),'LAPORAN OPERATION'!$B$2:$B$1000,"Count",'LAPORAN OPERATION'!$C$2:$C$1000,IF($A18="Pine","Pinus",$A18),'LAPORAN OPERATION'!$D$2:$D$1000,$B18)+SUMIFS('LAPORAN OPERATION'!$F$2:$F$1000,'LAPORAN OPERATION'!$A$2:$A$1000,DATE(2026,10,24),'LAPORAN OPERATION'!$B$2:$B$1000,"Count",'LAPORAN OPERATION'!$C$2:$C$1000,IF($A18="Pine","Pinus",$A18),'LAPORAN OPERATION'!$D$2:$D$1000,$B18&" (Grade A)") -> 1.387281 | S18: =ROUND(Q18-R18,6) -> 0
A19: Sungkai | B19: 3.5 | C19: 46310 | D19: =SUMIFS('LAPORAN OPERATION'!$F$2:$F$1000,'LAPORAN OPERATION'!$A$2:$A$1000,DATE(2026,10,14),'LAPORAN OPERATION'!$B$2:$B$1000,"Count",'LAPORAN OPERATION'!$C$2:$C$1000,IF($A19="Pine","Pinus",$A19),'LAPORAN OPERATION'!$D$2:$D$1000,$B19)+SUMIFS('LAPORAN OPERATION'!$F$2:$F$1000,'LAPORAN OPERATION'!$A$2:$A$1000,DATE(2026,10,14),'LAPORAN OPERATION'!$B$2:$B$1000,"Count",'LAPORAN OPERATION'!$C$2:$C$1000,IF($A19="Pine","Pinus",$A19),'LAPORAN OPERATION'!$D$2:$D$1000,$B19&" (Grade A)") -> 2.763775 | E19: =SUMIFS(INCOMING!$F$2:$F$5000,INCOMING!$C$2:$C$5000,$A19,INCOMING!$D$2:$D$5000,$B19,INCOMING!$B$2:$B$5000,">="&$C19,INCOMING!$B$2:$B$5000,"<="&DATE(2026,10,17)) -> 0 | F19: =SUMIFS(OUT!$F$14:$F$5084,OUT!$C$14:$C$5084,$A19,OUT!$D$14:$D$5084,$B19,OUT!$B$14:$B$5084,">="&$C19,OUT!$B$14:$B$5084,"<="&DATE(2026,10,17),OUT!$L$14:$L$5084,"<>Adjustment") -> 0 | G19: =D19+E19-F19 -> 2.763775 | H19: =SUMIFS('LAPORAN OPERATION'!$F$2:$F$1000,'LAPORAN OPERATION'!$A$2:$A$1000,DATE(2026,10,17),'LAPORAN OPERATION'!$B$2:$B$1000,"Balance",'LAPORAN OPERATION'!$C$2:$C$1000,IF($A19="Pine","Pinus",$A19),'LAPORAN OPERATION'!$D$2:$D$1000,$B19)+SUMIFS('LAPORAN OPERATION'!$F$2:$F$1000,'LAPORAN OPERATION'!$A$2:$A$1000,DATE(2026,10,17),'LAPORAN OPERATION'!$B$2:$B$1000,"Balance",'LAPORAN OPERATION'!$C$2:$C$1000,IF($A19="Pine","Pinus",$A19),'LAPORAN OPERATION'!$D$2:$D$1000,$B19&" (Grade A)") -> 2.763775 | I19: =ROUND(G19-H19,6) -> 0 | J19: =SUMIFS(INCOMING!$F$2:$F$5000,INCOMING!$C$2:$C$5000,$A19,INCOMING!$D$2:$D$5000,$B19,INCOMING!$B$2:$B$5000,">="&DATE(2026,10,18),INCOMING!$B$2:$B$5000,"<="&DATE(2026,10,21)) -> 0 | K19: =SUMIFS(OUT!$F$14:$F$5084,OUT!$C$14:$C$5084,$A19,OUT!$D$14:$D$5084,$B19,OUT!$B$14:$B$5084,">="&DATE(2026,10,18),OUT!$B$14:$B$5084,"<="&DATE(2026,10,21),OUT!$L$14:$L$5084,"<>Adjustment") -> 0.154 | L19: =G19+J19-K19 -> 2.609775 | M19: =SUMIFS('LAPORAN OPERATION'!$F$2:$F$1000,'LAPORAN OPERATION'!$A$2:$A$1000,DATE(2026,10,21),'LAPORAN OPERATION'!$B$2:$B$1000,"Balance",'LAPORAN OPERATION'!$C$2:$C$1000,IF($A19="Pine","Pinus",$A19),'LAPORAN OPERATION'!$D$2:$D$1000,$B19)+SUMIFS('LAPORAN OPERATION'!$F$2:$F$1000,'LAPORAN OPERATION'!$A$2:$A$1000,DATE(2026,10,21),'LAPORAN OPERATION'!$B$2:$B$1000,"Balance",'LAPORAN OPERATION'!$C$2:$C$1000,IF($A19="Pine","Pinus",$A19),'LAPORAN OPERATION'!$D$2:$D$1000,$B19&" (Grade A)") -> 2.609775 | N19: =ROUND(L19-M19,6) -> 0 | O19: =SUMIFS(INCOMING!$F$2:$F$5000,INCOMING!$C$2:$C$5000,$A19,INCOMING!$D$2:$D$5000,$B19,INCOMING!$B$2:$B$5000,">="&DATE(2026,10,22),INCOMING!$B$2:$B$5000,"<="&DATE(2026,10,24)) -> 0 | P19: =SUMIFS(OUT!$F$14:$F$5084,OUT!$C$14:$C$5084,$A19,OUT!$D$14:$D$5084,$B19,OUT!$B$14:$B$5084,">="&DATE(2026,10,22),OUT!$B$14:$B$5084,"<="&DATE(2026,10,24),OUT!$L$14:$L$5084,"<>Adjustment") -> 0 | Q19: =L19+O19-P19 -> 2.609775 | R19: =SUMIFS('LAPORAN OPERATION'!$F$2:$F$1000,'LAPORAN OPERATION'!$A$2:$A$1000,DATE(2026,10,24),'LAPORAN OPERATION'!$B$2:$B$1000,"Count",'LAPORAN OPERATION'!$C$2:$C$1000,IF($A19="Pine","Pinus",$A19),'LAPORAN OPERATION'!$D$2:$D$1000,$B19)+SUMIFS('LAPORAN OPERATION'!$F$2:$F$1000,'LAPORAN OPERATION'!$A$2:$A$1000,DATE(2026,10,24),'LAPORAN OPERATION'!$B$2:$B$1000,"Count",'LAPORAN OPERATION'!$C$2:$C$1000,IF($A19="Pine","Pinus",$A19),'LAPORAN OPERATION'!$D$2:$D$1000,$B19&" (Grade A)") -> 2.609775 | S19: =ROUND(Q19-R19,6) -> 0
A20: Sungkai | B20: 4 | C20: 46310 | D20: =SUMIFS('LAPORAN OPERATION'!$F$2:$F$1000,'LAPORAN OPERATION'!$A$2:$A$1000,DATE(2026,10,14),'LAPORAN OPERATION'!$B$2:$B$1000,"Count",'LAPORAN OPERATION'!$C$2:$C$1000,IF($A20="Pine","Pinus",$A20),'LAPORAN OPERATION'!$D$2:$D$1000,$B20)+SUMIFS('LAPORAN OPERATION'!$F$2:$F$1000,'LAPORAN OPERATION'!$A$2:$A$1000,DATE(2026,10,14),'LAPORAN OPERATION'!$B$2:$B$1000,"Count",'LAPORAN OPERATION'!$C$2:$C$1000,IF($A20="Pine","Pinus",$A20),'LAPORAN OPERATION'!$D$2:$D$1000,$B20&" (Grade A)") -> 0.13044 | E20: =SUMIFS(INCOMING!$F$2:$F$5000,INCOMING!$C$2:$C$5000,$A20,INCOMING!$D$2:$D$5000,$B20,INCOMING!$B$2:$B$5000,">="&$C20,INCOMING!$B$2:$B$5000,"<="&DATE(2026,10,17)) -> 0 | F20: =SUMIFS(OUT!$F$14:$F$5084,OUT!$C$14:$C$5084,$A20,OUT!$D$14:$D$5084,$B20,OUT!$B$14:$B$5084,">="&$C20,OUT!$B$14:$B$5084,"<="&DATE(2026,10,17),OUT!$L$14:$L$5084,"<>Adjustment") -> 0 | G20: =D20+E20-F20 -> 0.13044 | H20: =SUMIFS('LAPORAN OPERATION'!$F$2:$F$1000,'LAPORAN OPERATION'!$A$2:$A$1000,DATE(2026,10,17),'LAPORAN OPERATION'!$B$2:$B$1000,"Balance",'LAPORAN OPERATION'!$C$2:$C$1000,IF($A20="Pine","Pinus",$A20),'LAPORAN OPERATION'!$D$2:$D$1000,$B20)+SUMIFS('LAPORAN OPERATION'!$F$2:$F$1000,'LAPORAN OPERATION'!$A$2:$A$1000,DATE(2026,10,17),'LAPORAN OPERATION'!$B$2:$B$1000,"Balance",'LAPORAN OPERATION'!$C$2:$C$1000,IF($A20="Pine","Pinus",$A20),'LAPORAN OPERATION'!$D$2:$D$1000,$B20&" (Grade A)") -> 0.13044 | I20: =ROUND(G20-H20,6) -> 0 | J20: =SUMIFS(INCOMING!$F$2:$F$5000,INCOMING!$C$2:$C$5000,$A20,INCOMING!$D$2:$D$5000,$B20,INCOMING!$B$2:$B$5000,">="&DATE(2026,10,18),INCOMING!$B$2:$B$5000,"<="&DATE(2026,10,21)) -> 0 | K20: =SUMIFS(OUT!$F$14:$F$5084,OUT!$C$14:$C$5084,$A20,OUT!$D$14:$D$5084,$B20,OUT!$B$14:$B$5084,">="&DATE(2026,10,18),OUT!$B$14:$B$5084,"<="&DATE(2026,10,21),OUT!$L$14:$L$5084,"<>Adjustment") -> 0 | L20: =G20+J20-K20 -> 0.13044 | M20: =SUMIFS('LAPORAN OPERATION'!$F$2:$F$1000,'LAPORAN OPERATION'!$A$2:$A$1000,DATE(2026,10,21),'LAPORAN OPERATION'!$B$2:$B$1000,"Balance",'LAPORAN OPERATION'!$C$2:$C$1000,IF($A20="Pine","Pinus",$A20),'LAPORAN OPERATION'!$D$2:$D$1000,$B20)+SUMIFS('LAPORAN OPERATION'!$F$2:$F$1000,'LAPORAN OPERATION'!$A$2:$A$1000,DATE(2026,10,21),'LAPORAN OPERATION'!$B$2:$B$1000,"Balance",'LAPORAN OPERATION'!$C$2:$C$1000,IF($A20="Pine","Pinus",$A20),'LAPORAN OPERATION'!$D$2:$D$1000,$B20&" (Grade A)") -> 0.13044 | N20: =ROUND(L20-M20,6) -> 0 | O20: =SUMIFS(INCOMING!$F$2:$F$5000,INCOMING!$C$2:$C$5000,$A20,INCOMING!$D$2:$D$5000,$B20,INCOMING!$B$2:$B$5000,">="&DATE(2026,10,22),INCOMING!$B$2:$B$5000,"<="&DATE(2026,10,24)) -> 0 | P20: =SUMIFS(OUT!$F$14:$F$5084,OUT!$C$14:$C$5084,$A20,OUT!$D$14:$D$5084,$B20,OUT!$B$14:$B$5084,">="&DATE(2026,10,22),OUT!$B$14:$B$5084,"<="&DATE(2026,10,24),OUT!$L$14:$L$5084,"<>Adjustment") -> 0.04168 | Q20: =L20+O20-P20 -> 0.08876 | R20: =SUMIFS('LAPORAN OPERATION'!$F$2:$F$1000,'LAPORAN OPERATION'!$A$2:$A$1000,DATE(2026,10,24),'LAPORAN OPERATION'!$B$2:$B$1000,"Count",'LAPORAN OPERATION'!$C$2:$C$1000,IF($A20="Pine","Pinus",$A20),'LAPORAN OPERATION'!$D$2:$D$1000,$B20)+SUMIFS('LAPORAN OPERATION'!$F$2:$F$1000,'LAPORAN OPERATION'!$A$2:$A$1000,DATE(2026,10,24),'LAPORAN OPERATION'!$B$2:$B$1000,"Count",'LAPORAN OPERATION'!$C$2:$C$1000,IF($A20="Pine","Pinus",$A20),'LAPORAN OPERATION'!$D$2:$D$1000,$B20&" (Grade A)") -> 0.08876 | S20: =ROUND(Q20-R20,6) -> 0
A21: Sungkai | B21: 4.5 | C21: 46310 | D21: =SUMIFS('LAPORAN OPERATION'!$F$2:$F$1000,'LAPORAN OPERATION'!$A$2:$A$1000,DATE(2026,10,14),'LAPORAN OPERATION'!$B$2:$B$1000,"Count",'LAPORAN OPERATION'!$C$2:$C$1000,IF($A21="Pine","Pinus",$A21),'LAPORAN OPERATION'!$D$2:$D$1000,$B21)+SUMIFS('LAPORAN OPERATION'!$F$2:$F$1000,'LAPORAN OPERATION'!$A$2:$A$1000,DATE(2026,10,14),'LAPORAN OPERATION'!$B$2:$B$1000,"Count",'LAPORAN OPERATION'!$C$2:$C$1000,IF($A21="Pine","Pinus",$A21),'LAPORAN OPERATION'!$D$2:$D$1000,$B21&" (Grade A)") -> 0.394245 | E21: =SUMIFS(INCOMING!$F$2:$F$5000,INCOMING!$C$2:$C$5000,$A21,INCOMING!$D$2:$D$5000,$B21,INCOMING!$B$2:$B$5000,">="&$C21,INCOMING!$B$2:$B$5000,"<="&DATE(2026,10,17)) -> 0 | F21: =SUMIFS(OUT!$F$14:$F$5084,OUT!$C$14:$C$5084,$A21,OUT!$D$14:$D$5084,$B21,OUT!$B$14:$B$5084,">="&$C21,OUT!$B$14:$B$5084,"<="&DATE(2026,10,17),OUT!$L$14:$L$5084,"<>Adjustment") -> 0 | G21: =D21+E21-F21 -> 0.394245 | H21: =SUMIFS('LAPORAN OPERATION'!$F$2:$F$1000,'LAPORAN OPERATION'!$A$2:$A$1000,DATE(2026,10,17),'LAPORAN OPERATION'!$B$2:$B$1000,"Balance",'LAPORAN OPERATION'!$C$2:$C$1000,IF($A21="Pine","Pinus",$A21),'LAPORAN OPERATION'!$D$2:$D$1000,$B21)+SUMIFS('LAPORAN OPERATION'!$F$2:$F$1000,'LAPORAN OPERATION'!$A$2:$A$1000,DATE(2026,10,17),'LAPORAN OPERATION'!$B$2:$B$1000,"Balance",'LAPORAN OPERATION'!$C$2:$C$1000,IF($A21="Pine","Pinus",$A21),'LAPORAN OPERATION'!$D$2:$D$1000,$B21&" (Grade A)") -> 0.394245 | I21: =ROUND(G21-H21,6) -> 0 | J21: =SUMIFS(INCOMING!$F$2:$F$5000,INCOMING!$C$2:$C$5000,$A21,INCOMING!$D$2:$D$5000,$B21,INCOMING!$B$2:$B$5000,">="&DATE(2026,10,18),INCOMING!$B$2:$B$5000,"<="&DATE(2026,10,21)) -> 0 | K21: =SUMIFS(OUT!$F$14:$F$5084,OUT!$C$14:$C$5084,$A21,OUT!$D$14:$D$5084,$B21,OUT!$B$14:$B$5084,">="&DATE(2026,10,18),OUT!$B$14:$B$5084,"<="&DATE(2026,10,21),OUT!$L$14:$L$5084,"<>Adjustment") -> 0 | L21: =G21+J21-K21 -> 0.394245 | M21: =SUMIFS('LAPORAN OPERATION'!$F$2:$F$1000,'LAPORAN OPERATION'!$A$2:$A$1000,DATE(2026,10,21),'LAPORAN OPERATION'!$B$2:$B$1000,"Balance",'LAPORAN OPERATION'!$C$2:$C$1000,IF($A21="Pine","Pinus",$A21),'LAPORAN OPERATION'!$D$2:$D$1000,$B21)+SUMIFS('LAPORAN OPERATION'!$F$2:$F$1000,'LAPORAN OPERATION'!$A$2:$A$1000,DATE(2026,10,21),'LAPORAN OPERATION'!$B$2:$B$1000,"Balance",'LAPORAN OPERATION'!$C$2:$C$1000,IF($A21="Pine","Pinus",$A21),'LAPORAN OPERATION'!$D$2:$D$1000,$B21&" (Grade A)") -> 0.394245 | N21: =ROUND(L21-M21,6) -> 0 | O21: =SUMIFS(INCOMING!$F$2:$F$5000,INCOMING!$C$2:$C$5000,$A21,INCOMING!$D$2:$D$5000,$B21,INCOMING!$B$2:$B$5000,">="&DATE(2026,10,22),INCOMING!$B$2:$B$5000,"<="&DATE(2026,10,24)) -> 0 | P21: =SUMIFS(OUT!$F$14:$F$5084,OUT!$C$14:$C$5084,$A21,OUT!$D$14:$D$5084,$B21,OUT!$B$14:$B$5084,">="&DATE(2026,10,22),OUT!$B$14:$B$5084,"<="&DATE(2026,10,24),OUT!$L$14:$L$5084,"<>Adjustment") -> 0.388575 | Q21: =L21+O21-P21 -> 0.00567 | R21: =SUMIFS('LAPORAN OPERATION'!$F$2:$F$1000,'LAPORAN OPERATION'!$A$2:$A$1000,DATE(2026,10,24),'LAPORAN OPERATION'!$B$2:$B$1000,"Count",'LAPORAN OPERATION'!$C$2:$C$1000,IF($A21="Pine","Pinus",$A21),'LAPORAN OPERATION'!$D$2:$D$1000,$B21)+SUMIFS('LAPORAN OPERATION'!$F$2:$F$1000,'LAPORAN OPERATION'!$A$2:$A$1000,DATE(2026,10,24),'LAPORAN OPERATION'!$B$2:$B$1000,"Count",'LAPORAN OPERATION'!$C$2:$C$1000,IF($A21="Pine","Pinus",$A21),'LAPORAN OPERATION'!$D$2:$D$1000,$B21&" (Grade A)") -> 0.00567 | S21: =ROUND(Q21-R21,6) -> 0
A22: Sungkai | B22: 5 | C22: 46310 | D22: =SUMIFS('LAPORAN OPERATION'!$F$2:$F$1000,'LAPORAN OPERATION'!$A$2:$A$1000,DATE(2026,10,14),'LAPORAN OPERATION'!$B$2:$B$1000,"Count",'LAPORAN OPERATION'!$C$2:$C$1000,IF($A22="Pine","Pinus",$A22),'LAPORAN OPERATION'!$D$2:$D$1000,$B22)+SUMIFS('LAPORAN OPERATION'!$F$2:$F$1000,'LAPORAN OPERATION'!$A$2:$A$1000,DATE(2026,10,14),'LAPORAN OPERATION'!$B$2:$B$1000,"Count",'LAPORAN OPERATION'!$C$2:$C$1000,IF($A22="Pine","Pinus",$A22),'LAPORAN OPERATION'!$D$2:$D$1000,$B22&" (Grade A)") -> 0.4283 | E22: =SUMIFS(INCOMING!$F$2:$F$5000,INCOMING!$C$2:$C$5000,$A22,INCOMING!$D$2:$D$5000,$B22,INCOMING!$B$2:$B$5000,">="&$C22,INCOMING!$B$2:$B$5000,"<="&DATE(2026,10,17)) -> 0 | F22: =SUMIFS(OUT!$F$14:$F$5084,OUT!$C$14:$C$5084,$A22,OUT!$D$14:$D$5084,$B22,OUT!$B$14:$B$5084,">="&$C22,OUT!$B$14:$B$5084,"<="&DATE(2026,10,17),OUT!$L$14:$L$5084,"<>Adjustment") -> 0 | G22: =D22+E22-F22 -> 0.4283 | H22: =SUMIFS('LAPORAN OPERATION'!$F$2:$F$1000,'LAPORAN OPERATION'!$A$2:$A$1000,DATE(2026,10,17),'LAPORAN OPERATION'!$B$2:$B$1000,"Balance",'LAPORAN OPERATION'!$C$2:$C$1000,IF($A22="Pine","Pinus",$A22),'LAPORAN OPERATION'!$D$2:$D$1000,$B22)+SUMIFS('LAPORAN OPERATION'!$F$2:$F$1000,'LAPORAN OPERATION'!$A$2:$A$1000,DATE(2026,10,17),'LAPORAN OPERATION'!$B$2:$B$1000,"Balance",'LAPORAN OPERATION'!$C$2:$C$1000,IF($A22="Pine","Pinus",$A22),'LAPORAN OPERATION'!$D$2:$D$1000,$B22&" (Grade A)") -> 0.4283 | I22: =ROUND(G22-H22,6) -> 0 | J22: =SUMIFS(INCOMING!$F$2:$F$5000,INCOMING!$C$2:$C$5000,$A22,INCOMING!$D$2:$D$5000,$B22,INCOMING!$B$2:$B$5000,">="&DATE(2026,10,18),INCOMING!$B$2:$B$5000,"<="&DATE(2026,10,21)) -> 0 | K22: =SUMIFS(OUT!$F$14:$F$5084,OUT!$C$14:$C$5084,$A22,OUT!$D$14:$D$5084,$B22,OUT!$B$14:$B$5084,">="&DATE(2026,10,18),OUT!$B$14:$B$5084,"<="&DATE(2026,10,21),OUT!$L$14:$L$5084,"<>Adjustment") -> 0 | L22: =G22+J22-K22 -> 0.4283 | M22: =SUMIFS('LAPORAN OPERATION'!$F$2:$F$1000,'LAPORAN OPERATION'!$A$2:$A$1000,DATE(2026,10,21),'LAPORAN OPERATION'!$B$2:$B$1000,"Balance",'LAPORAN OPERATION'!$C$2:$C$1000,IF($A22="Pine","Pinus",$A22),'LAPORAN OPERATION'!$D$2:$D$1000,$B22)+SUMIFS('LAPORAN OPERATION'!$F$2:$F$1000,'LAPORAN OPERATION'!$A$2:$A$1000,DATE(2026,10,21),'LAPORAN OPERATION'!$B$2:$B$1000,"Balance",'LAPORAN OPERATION'!$C$2:$C$1000,IF($A22="Pine","Pinus",$A22),'LAPORAN OPERATION'!$D$2:$D$1000,$B22&" (Grade A)") -> 0.4283 | N22: =ROUND(L22-M22,6) -> 0 | O22: =SUMIFS(INCOMING!$F$2:$F$5000,INCOMING!$C$2:$C$5000,$A22,INCOMING!$D$2:$D$5000,$B22,INCOMING!$B$2:$B$5000,">="&DATE(2026,10,22),INCOMING!$B$2:$B$5000,"<="&DATE(2026,10,24)) -> 0 | P22: =SUMIFS(OUT!$F$14:$F$5084,OUT!$C$14:$C$5084,$A22,OUT!$D$14:$D$5084,$B22,OUT!$B$14:$B$5084,">="&DATE(2026,10,22),OUT!$B$14:$B$5084,"<="&DATE(2026,10,24),OUT!$L$14:$L$5084,"<>Adjustment") -> 0.353645 | Q22: =L22+O22-P22 -> 0.074655 | R22: =SUMIFS('LAPORAN OPERATION'!$F$2:$F$1000,'LAPORAN OPERATION'!$A$2:$A$1000,DATE(2026,10,24),'LAPORAN OPERATION'!$B$2:$B$1000,"Count",'LAPORAN OPERATION'!$C$2:$C$1000,IF($A22="Pine","Pinus",$A22),'LAPORAN OPERATION'!$D$2:$D$1000,$B22)+SUMIFS('LAPORAN OPERATION'!$F$2:$F$1000,'LAPORAN OPERATION'!$A$2:$A$1000,DATE(2026,10,24),'LAPORAN OPERATION'!$B$2:$B$1000,"Count",'LAPORAN OPERATION'!$C$2:$C$1000,IF($A22="Pine","Pinus",$A22),'LAPORAN OPERATION'!$D$2:$D$1000,$B22&" (Grade A)") -> 0.074655 | S22: =ROUND(Q22-R22,6) -> 0
A23: Sungkai | B23: 5.5 | C23: 46310 | D23: =SUMIFS('LAPORAN OPERATION'!$F$2:$F$1000,'LAPORAN OPERATION'!$A$2:$A$1000,DATE(2026,10,14),'LAPORAN OPERATION'!$B$2:$B$1000,"Count",'LAPORAN OPERATION'!$C$2:$C$1000,IF($A23="Pine","Pinus",$A23),'LAPORAN OPERATION'!$D$2:$D$1000,$B23)+SUMIFS('LAPORAN OPERATION'!$F$2:$F$1000,'LAPORAN OPERATION'!$A$2:$A$1000,DATE(2026,10,14),'LAPORAN OPERATION'!$B$2:$B$1000,"Count",'LAPORAN OPERATION'!$C$2:$C$1000,IF($A23="Pine","Pinus",$A23),'LAPORAN OPERATION'!$D$2:$D$1000,$B23&" (Grade A)") -> 0.400015 | E23: =SUMIFS(INCOMING!$F$2:$F$5000,INCOMING!$C$2:$C$5000,$A23,INCOMING!$D$2:$D$5000,$B23,INCOMING!$B$2:$B$5000,">="&$C23,INCOMING!$B$2:$B$5000,"<="&DATE(2026,10,17)) -> 0 | F23: =SUMIFS(OUT!$F$14:$F$5084,OUT!$C$14:$C$5084,$A23,OUT!$D$14:$D$5084,$B23,OUT!$B$14:$B$5084,">="&$C23,OUT!$B$14:$B$5084,"<="&DATE(2026,10,17),OUT!$L$14:$L$5084,"<>Adjustment") -> 0 | G23: =D23+E23-F23 -> 0.400015 | H23: =SUMIFS('LAPORAN OPERATION'!$F$2:$F$1000,'LAPORAN OPERATION'!$A$2:$A$1000,DATE(2026,10,17),'LAPORAN OPERATION'!$B$2:$B$1000,"Balance",'LAPORAN OPERATION'!$C$2:$C$1000,IF($A23="Pine","Pinus",$A23),'LAPORAN OPERATION'!$D$2:$D$1000,$B23)+SUMIFS('LAPORAN OPERATION'!$F$2:$F$1000,'LAPORAN OPERATION'!$A$2:$A$1000,DATE(2026,10,17),'LAPORAN OPERATION'!$B$2:$B$1000,"Balance",'LAPORAN OPERATION'!$C$2:$C$1000,IF($A23="Pine","Pinus",$A23),'LAPORAN OPERATION'!$D$2:$D$1000,$B23&" (Grade A)") -> 0.400015 | I23: =ROUND(G23-H23,6) -> 0 | J23: =SUMIFS(INCOMING!$F$2:$F$5000,INCOMING!$C$2:$C$5000,$A23,INCOMING!$D$2:$D$5000,$B23,INCOMING!$B$2:$B$5000,">="&DATE(2026,10,18),INCOMING!$B$2:$B$5000,"<="&DATE(2026,10,21)) -> 0 | K23: =SUMIFS(OUT!$F$14:$F$5084,OUT!$C$14:$C$5084,$A23,OUT!$D$14:$D$5084,$B23,OUT!$B$14:$B$5084,">="&DATE(2026,10,18),OUT!$B$14:$B$5084,"<="&DATE(2026,10,21),OUT!$L$14:$L$5084,"<>Adjustment") -> 0 | L23: =G23+J23-K23 -> 0.400015 | M23: =SUMIFS('LAPORAN OPERATION'!$F$2:$F$1000,'LAPORAN OPERATION'!$A$2:$A$1000,DATE(2026,10,21),'LAPORAN OPERATION'!$B$2:$B$1000,"Balance",'LAPORAN OPERATION'!$C$2:$C$1000,IF($A23="Pine","Pinus",$A23),'LAPORAN OPERATION'!$D$2:$D$1000,$B23)+SUMIFS('LAPORAN OPERATION'!$F$2:$F$1000,'LAPORAN OPERATION'!$A$2:$A$1000,DATE(2026,10,21),'LAPORAN OPERATION'!$B$2:$B$1000,"Balance",'LAPORAN OPERATION'!$C$2:$C$1000,IF($A23="Pine","Pinus",$A23),'LAPORAN OPERATION'!$D$2:$D$1000,$B23&" (Grade A)") -> 0.400015 | N23: =ROUND(L23-M23,6) -> 0 | O23: =SUMIFS(INCOMING!$F$2:$F$5000,INCOMING!$C$2:$C$5000,$A23,INCOMING!$D$2:$D$5000,$B23,INCOMING!$B$2:$B$5000,">="&DATE(2026,10,22),INCOMING!$B$2:$B$5000,"<="&DATE(2026,10,24)) -> 0 | P23: =SUMIFS(OUT!$F$14:$F$5084,OUT!$C$14:$C$5084,$A23,OUT!$D$14:$D$5084,$B23,OUT!$B$14:$B$5084,">="&DATE(2026,10,22),OUT!$B$14:$B$5084,"<="&DATE(2026,10,24),OUT!$L$14:$L$5084,"<>Adjustment") -> 0.294965 | Q23: =L23+O23-P23 -> 0.10505 | R23: =SUMIFS('LAPORAN OPERATION'!$F$2:$F$1000,'LAPORAN OPERATION'!$A$2:$A$1000,DATE(2026,10,24),'LAPORAN OPERATION'!$B$2:$B$1000,"Count",'LAPORAN OPERATION'!$C$2:$C$1000,IF($A23="Pine","Pinus",$A23),'LAPORAN OPERATION'!$D$2:$D$1000,$B23)+SUMIFS('LAPORAN OPERATION'!$F$2:$F$1000,'LAPORAN OPERATION'!$A$2:$A$1000,DATE(2026,10,24),'LAPORAN OPERATION'!$B$2:$B$1000,"Count",'LAPORAN OPERATION'!$C$2:$C$1000,IF($A23="Pine","Pinus",$A23),'LAPORAN OPERATION'!$D$2:$D$1000,$B23&" (Grade A)") -> 0.10505 | S23: =ROUND(Q23-R23,6) -> 0
A24: Sungkai | B24: 7.5 | C24: 46310 | D24: =SUMIFS('LAPORAN OPERATION'!$F$2:$F$1000,'LAPORAN OPERATION'!$A$2:$A$1000,DATE(2026,10,14),'LAPORAN OPERATION'!$B$2:$B$1000,"Count",'LAPORAN OPERATION'!$C$2:$C$1000,IF($A24="Pine","Pinus",$A24),'LAPORAN OPERATION'!$D$2:$D$1000,$B24)+SUMIFS('LAPORAN OPERATION'!$F$2:$F$1000,'LAPORAN OPERATION'!$A$2:$A$1000,DATE(2026,10,14),'LAPORAN OPERATION'!$B$2:$B$1000,"Count",'LAPORAN OPERATION'!$C$2:$C$1000,IF($A24="Pine","Pinus",$A24),'LAPORAN OPERATION'!$D$2:$D$1000,$B24&" (Grade A)") -> 2.71845 | E24: =SUMIFS(INCOMING!$F$2:$F$5000,INCOMING!$C$2:$C$5000,$A24,INCOMING!$D$2:$D$5000,$B24,INCOMING!$B$2:$B$5000,">="&$C24,INCOMING!$B$2:$B$5000,"<="&DATE(2026,10,17)) -> 0 | F24: =SUMIFS(OUT!$F$14:$F$5084,OUT!$C$14:$C$5084,$A24,OUT!$D$14:$D$5084,$B24,OUT!$B$14:$B$5084,">="&$C24,OUT!$B$14:$B$5084,"<="&DATE(2026,10,17),OUT!$L$14:$L$5084,"<>Adjustment") -> 0 | G24: =D24+E24-F24 -> 2.71845 | H24: =SUMIFS('LAPORAN OPERATION'!$F$2:$F$1000,'LAPORAN OPERATION'!$A$2:$A$1000,DATE(2026,10,17),'LAPORAN OPERATION'!$B$2:$B$1000,"Balance",'LAPORAN OPERATION'!$C$2:$C$1000,IF($A24="Pine","Pinus",$A24),'LAPORAN OPERATION'!$D$2:$D$1000,$B24)+SUMIFS('LAPORAN OPERATION'!$F$2:$F$1000,'LAPORAN OPERATION'!$A$2:$A$1000,DATE(2026,10,17),'LAPORAN OPERATION'!$B$2:$B$1000,"Balance",'LAPORAN OPERATION'!$C$2:$C$1000,IF($A24="Pine","Pinus",$A24),'LAPORAN OPERATION'!$D$2:$D$1000,$B24&" (Grade A)") -> 2.71845 | I24: =ROUND(G24-H24,6) -> 0 | J24: =SUMIFS(INCOMING!$F$2:$F$5000,INCOMING!$C$2:$C$5000,$A24,INCOMING!$D$2:$D$5000,$B24,INCOMING!$B$2:$B$5000,">="&DATE(2026,10,18),INCOMING!$B$2:$B$5000,"<="&DATE(2026,10,21)) -> 0 | K24: =SUMIFS(OUT!$F$14:$F$5084,OUT!$C$14:$C$5084,$A24,OUT!$D$14:$D$5084,$B24,OUT!$B$14:$B$5084,">="&DATE(2026,10,18),OUT!$B$14:$B$5084,"<="&DATE(2026,10,21),OUT!$L$14:$L$5084,"<>Adjustment") -> 0 | L24: =G24+J24-K24 -> 2.71845 | M24: =SUMIFS('LAPORAN OPERATION'!$F$2:$F$1000,'LAPORAN OPERATION'!$A$2:$A$1000,DATE(2026,10,21),'LAPORAN OPERATION'!$B$2:$B$1000,"Balance",'LAPORAN OPERATION'!$C$2:$C$1000,IF($A24="Pine","Pinus",$A24),'LAPORAN OPERATION'!$D$2:$D$1000,$B24)+SUMIFS('LAPORAN OPERATION'!$F$2:$F$1000,'LAPORAN OPERATION'!$A$2:$A$1000,DATE(2026,10,21),'LAPORAN OPERATION'!$B$2:$B$1000,"Balance",'LAPORAN OPERATION'!$C$2:$C$1000,IF($A24="Pine","Pinus",$A24),'LAPORAN OPERATION'!$D$2:$D$1000,$B24&" (Grade A)") -> 2.71845 | N24: =ROUND(L24-M24,6) -> 0 | O24: =SUMIFS(INCOMING!$F$2:$F$5000,INCOMING!$C$2:$C$5000,$A24,INCOMING!$D$2:$D$5000,$B24,INCOMING!$B$2:$B$5000,">="&DATE(2026,10,22),INCOMING!$B$2:$B$5000,"<="&DATE(2026,10,24)) -> 0 | P24: =SUMIFS(OUT!$F$14:$F$5084,OUT!$C$14:$C$5084,$A24,OUT!$D$14:$D$5084,$B24,OUT!$B$14:$B$5084,">="&DATE(2026,10,22),OUT!$B$14:$B$5084,"<="&DATE(2026,10,24),OUT!$L$14:$L$5084,"<>Adjustment") -> 0.680625 | Q24: =L24+O24-P24 -> 2.037825 | R24: =SUMIFS('LAPORAN OPERATION'!$F$2:$F$1000,'LAPORAN OPERATION'!$A$2:$A$1000,DATE(2026,10,24),'LAPORAN OPERATION'!$B$2:$B$1000,"Count",'LAPORAN OPERATION'!$C$2:$C$1000,IF($A24="Pine","Pinus",$A24),'LAPORAN OPERATION'!$D$2:$D$1000,$B24)+SUMIFS('LAPORAN OPERATION'!$F$2:$F$1000,'LAPORAN OPERATION'!$A$2:$A$1000,DATE(2026,10,24),'LAPORAN OPERATION'!$B$2:$B$1000,"Count",'LAPORAN OPERATION'!$C$2:$C$1000,IF($A24="Pine","Pinus",$A24),'LAPORAN OPERATION'!$D$2:$D$1000,$B24&" (Grade A)") -> 2.037825 | S24: =ROUND(Q24-R24,6) -> 0
A25: Sungkai | B25: 8 | C25: 46310 | D25: =SUMIFS('LAPORAN OPERATION'!$F$2:$F$1000,'LAPORAN OPERATION'!$A$2:$A$1000,DATE(2026,10,14),'LAPORAN OPERATION'!$B$2:$B$1000,"Count",'LAPORAN OPERATION'!$C$2:$C$1000,IF($A25="Pine","Pinus",$A25),'LAPORAN OPERATION'!$D$2:$D$1000,$B25)+SUMIFS('LAPORAN OPERATION'!$F$2:$F$1000,'LAPORAN OPERATION'!$A$2:$A$1000,DATE(2026,10,14),'LAPORAN OPERATION'!$B$2:$B$1000,"Count",'LAPORAN OPERATION'!$C$2:$C$1000,IF($A25="Pine","Pinus",$A25),'LAPORAN OPERATION'!$D$2:$D$1000,$B25&" (Grade A)") -> 3.76424 | E25: =SUMIFS(INCOMING!$F$2:$F$5000,INCOMING!$C$2:$C$5000,$A25,INCOMING!$D$2:$D$5000,$B25,INCOMING!$B$2:$B$5000,">="&$C25,INCOMING!$B$2:$B$5000,"<="&DATE(2026,10,17)) -> 0 | F25: =SUMIFS(OUT!$F$14:$F$5084,OUT!$C$14:$C$5084,$A25,OUT!$D$14:$D$5084,$B25,OUT!$B$14:$B$5084,">="&$C25,OUT!$B$14:$B$5084,"<="&DATE(2026,10,17),OUT!$L$14:$L$5084,"<>Adjustment") -> 0 | G25: =D25+E25-F25 -> 3.76424 | H25: =SUMIFS('LAPORAN OPERATION'!$F$2:$F$1000,'LAPORAN OPERATION'!$A$2:$A$1000,DATE(2026,10,17),'LAPORAN OPERATION'!$B$2:$B$1000,"Balance",'LAPORAN OPERATION'!$C$2:$C$1000,IF($A25="Pine","Pinus",$A25),'LAPORAN OPERATION'!$D$2:$D$1000,$B25)+SUMIFS('LAPORAN OPERATION'!$F$2:$F$1000,'LAPORAN OPERATION'!$A$2:$A$1000,DATE(2026,10,17),'LAPORAN OPERATION'!$B$2:$B$1000,"Balance",'LAPORAN OPERATION'!$C$2:$C$1000,IF($A25="Pine","Pinus",$A25),'LAPORAN OPERATION'!$D$2:$D$1000,$B25&" (Grade A)") -> 3.76424 | I25: =ROUND(G25-H25,6) -> 0 | J25: =SUMIFS(INCOMING!$F$2:$F$5000,INCOMING!$C$2:$C$5000,$A25,INCOMING!$D$2:$D$5000,$B25,INCOMING!$B$2:$B$5000,">="&DATE(2026,10,18),INCOMING!$B$2:$B$5000,"<="&DATE(2026,10,21)) -> 0 | K25: =SUMIFS(OUT!$F$14:$F$5084,OUT!$C$14:$C$5084,$A25,OUT!$D$14:$D$5084,$B25,OUT!$B$14:$B$5084,">="&DATE(2026,10,18),OUT!$B$14:$B$5084,"<="&DATE(2026,10,21),OUT!$L$14:$L$5084,"<>Adjustment") -> 0 | L25: =G25+J25-K25 -> 3.76424 | M25: =SUMIFS('LAPORAN OPERATION'!$F$2:$F$1000,'LAPORAN OPERATION'!$A$2:$A$1000,DATE(2026,10,21),'LAPORAN OPERATION'!$B$2:$B$1000,"Balance",'LAPORAN OPERATION'!$C$2:$C$1000,IF($A25="Pine","Pinus",$A25),'LAPORAN OPERATION'!$D$2:$D$1000,$B25)+SUMIFS('LAPORAN OPERATION'!$F$2:$F$1000,'LAPORAN OPERATION'!$A$2:$A$1000,DATE(2026,10,21),'LAPORAN OPERATION'!$B$2:$B$1000,"Balance",'LAPORAN OPERATION'!$C$2:$C$1000,IF($A25="Pine","Pinus",$A25),'LAPORAN OPERATION'!$D$2:$D$1000,$B25&" (Grade A)") -> 3.76424 | N25: =ROUND(L25-M25,6) -> 0 | O25: =SUMIFS(INCOMING!$F$2:$F$5000,INCOMING!$C$2:$C$5000,$A25,INCOMING!$D$2:$D$5000,$B25,INCOMING!$B$2:$B$5000,">="&DATE(2026,10,22),INCOMING!$B$2:$B$5000,"<="&DATE(2026,10,24)) -> 0 | P25: =SUMIFS(OUT!$F$14:$F$5084,OUT!$C$14:$C$5084,$A25,OUT!$D$14:$D$5084,$B25,OUT!$B$14:$B$5084,">="&DATE(2026,10,22),OUT!$B$14:$B$5084,"<="&DATE(2026,10,24),OUT!$L$14:$L$5084,"<>Adjustment") -> 0.22136 | Q25: =L25+O25-P25 -> 3.54288 | R25: =SUMIFS('LAPORAN OPERATION'!$F$2:$F$1000,'LAPORAN OPERATION'!$A$2:$A$1000,DATE(2026,10,24),'LAPORAN OPERATION'!$B$2:$B$1000,"Count",'LAPORAN OPERATION'!$C$2:$C$1000,IF($A25="Pine","Pinus",$A25),'LAPORAN OPERATION'!$D$2:$D$1000,$B25)+SUMIFS('LAPORAN OPERATION'!$F$2:$F$1000,'LAPORAN OPERATION'!$A$2:$A$1000,DATE(2026,10,24),'LAPORAN OPERATION'!$B$2:$B$1000,"Count",'LAPORAN OPERATION'!$C$2:$C$1000,IF($A25="Pine","Pinus",$A25),'LAPORAN OPERATION'!$D$2:$D$1000,$B25&" (Grade A)") -> 3.54288 | S25: =ROUND(Q25-R25,6) -> 0
A26: Total Sungkai | D26: =SUM(D17:D25) -> 12.372561 | E26: =SUM(E17:E25) -> 0 | F26: =SUM(F17:F25) -> 0 | G26: =SUM(G17:G25) -> 12.372561 | H26: =SUM(H17:H25) -> 12.372561 | I26: =SUM(I17:I25) -> 0 | J26: =SUM(J17:J25) -> 0 | K26: =SUM(K17:K25) -> 0.46159 | ... S26: =SUM(S17:S25) -> 0
A28: Pine | B28: 2.5 | C28: 46309 | D28: =SUMIFS('LAPORAN OPERATION'!$F$2:$F$1000,'LAPORAN OPERATION'!$A$2:$A$1000,DATE(2026,10,14),'LAPORAN OPERATION'!$B$2:$B$1000,"Count",'LAPORAN OPERATION'!$C$2:$C$1000,IF($A28="Pine","Pinus",$A28),'LAPORAN OPERATION'!$D$2:$D$1000,$B28)+SUMIFS('LAPORAN OPERATION'!$F$2:$F$1000,'LAPORAN OPERATION'!$A$2:$A$1000,DATE(2026,10,14),'LAPORAN OPERATION'!$B$2:$B$1000,"Count",'LAPORAN OPERATION'!$C$2:$C$1000,IF($A28="Pine","Pinus",$A28),'LAPORAN OPERATION'!$D$2:$D$1000,$B28&" (Grade A)") -> 0.04878 | E28: =SUMIFS(INCOMING!$F$2:$F$5000,INCOMING!$C$2:$C$5000,$A28,INCOMING!$D$2:$D$5000,$B28,INCOMING!$B$2:$B$5000,">="&$C28,INCOMING!$B$2:$B$5000,"<="&DATE(2026,10,17)) -> 0 | F28: =SUMIFS(OUT!$F$14:$F$5084,OUT!$C$14:$C$5084,$A28,OUT!$D$14:$D$5084,$B28,OUT!$B$14:$B$5084,">="&$C28,OUT!$B$14:$B$5084,"<="&DATE(2026,10,17),OUT!$L$14:$L$5084,"<>Adjustment") -> 0.014275 | G28: =D28+E28-F28 -> 0.034505 | H28: =SUMIFS('LAPORAN OPERATION'!$F$2:$F$1000,'LAPORAN OPERATION'!$A$2:$A$1000,DATE(2026,10,17),'LAPORAN OPERATION'!$B$2:$B$1000,"Balance",'LAPORAN OPERATION'!$C$2:$C$1000,IF($A28="Pine","Pinus",$A28),'LAPORAN OPERATION'!$D$2:$D$1000,$B28)+SUMIFS('LAPORAN OPERATION'!$F$2:$F$1000,'LAPORAN OPERATION'!$A$2:$A$1000,DATE(2026,10,17),'LAPORAN OPERATION'!$B$2:$B$1000,"Balance",'LAPORAN OPERATION'!$C$2:$C$1000,IF($A28="Pine","Pinus",$A28),'LAPORAN OPERATION'!$D$2:$D$1000,$B28&" (Grade A)") -> 0.034505 | I28: =ROUND(G28-H28,6) -> 0 | J28: =SUMIFS(INCOMING!$F$2:$F$5000,INCOMING!$C$2:$C$5000,$A28,INCOMING!$D$2:$D$5000,$B28,INCOMING!$B$2:$B$5000,">="&DATE(2026,10,18),INCOMING!$B$2:$B$5000,"<="&DATE(2026,10,21)) -> 0 | K28: =SUMIFS(OUT!$F$14:$F$5084,OUT!$C$14:$C$5084,$A28,OUT!$D$14:$D$5084,$B28,OUT!$B$14:$B$5084,">="&DATE(2026,10,18),OUT!$B$14:$B$5084,"<="&DATE(2026,10,21),OUT!$L$14:$L$5084,"<>Adjustment") -> 0 | L28: =G28+J28-K28 -> 0.034505 | M28: =SUMIFS('LAPORAN OPERATION'!$F$2:$F$1000,'LAPORAN OPERATION'!$A$2:$A$1000,DATE(2026,10,21),'LAPORAN OPERATION'!$B$2:$B$1000,"Balance",'LAPORAN OPERATION'!$C$2:$C$1000,IF($A28="Pine","Pinus",$A28),'LAPORAN OPERATION'!$D$2:$D$1000,$B28)+SUMIFS('LAPORAN OPERATION'!$F$2:$F$1000,'LAPORAN OPERATION'!$A$2:$A$1000,DATE(2026,10,21),'LAPORAN OPERATION'!$B$2:$B$1000,"Balance",'LAPORAN OPERATION'!$C$2:$C$1000,IF($A28="Pine","Pinus",$A28),'LAPORAN OPERATION'!$D$2:$D$1000,$B28&" (Grade A)") -> 0.034505 | N28: =ROUND(L28-M28,6) -> 0 | O28: =SUMIFS(INCOMING!$F$2:$F$5000,INCOMING!$C$2:$C$5000,$A28,INCOMING!$D$2:$D$5000,$B28,INCOMING!$B$2:$B$5000,">="&DATE(2026,10,22),INCOMING!$B$2:$B$5000,"<="&DATE(2026,10,24)) -> 0 | P28: =SUMIFS(OUT!$F$14:$F$5084,OUT!$C$14:$C$5084,$A28,OUT!$D$14:$D$5084,$B28,OUT!$B$14:$B$5084,">="&DATE(2026,10,22),OUT!$B$14:$B$5084,"<="&DATE(2026,10,24),OUT!$L$14:$L$5084,"<>Adjustment") -> 0 | Q28: =L28+O28-P28 -> 0.034505 | R28: =SUMIFS('LAPORAN OPERATION'!$F$2:$F$1000,'LAPORAN OPERATION'!$A$2:$A$1000,DATE(2026,10,24),'LAPORAN OPERATION'!$B$2:$B$1000,"Count",'LAPORAN OPERATION'!$C$2:$C$1000,IF($A28="Pine","Pinus",$A28),'LAPORAN OPERATION'!$D$2:$D$1000,$B28)+SUMIFS('LAPORAN OPERATION'!$F$2:$F$1000,'LAPORAN OPERATION'!$A$2:$A$1000,DATE(2026,10,24),'LAPORAN OPERATION'!$B$2:$B$1000,"Count",'LAPORAN OPERATION'!$C$2:$C$1000,IF($A28="Pine","Pinus",$A28),'LAPORAN OPERATION'!$D$2:$D$1000,$B28&" (Grade A)") -> 0.034505 | S28: =ROUND(Q28-R28,6) -> 0
A29: Pine | B29: 3.5 | C29: 46309 | D29: =SUMIFS('LAPORAN OPERATION'!$F$2:$F$1000,'LAPORAN OPERATION'!$A$2:$A$1000,DATE(2026,10,14),'LAPORAN OPERATION'!$B$2:$B$1000,"Count",'LAPORAN OPERATION'!$C$2:$C$1000,IF($A29="Pine","Pinus",$A29),'LAPORAN OPERATION'!$D$2:$D$1000,$B29)+SUMIFS('LAPORAN OPERATION'!$F$2:$F$1000,'LAPORAN OPERATION'!$A$2:$A$1000,DATE(2026,10,14),'LAPORAN OPERATION'!$B$2:$B$1000,"Count",'LAPORAN OPERATION'!$C$2:$C$1000,IF($A29="Pine","Pinus",$A29),'LAPORAN OPERATION'!$D$2:$D$1000,$B29&" (Grade A)") -> 0.087675 | E29: =SUMIFS(INCOMING!$F$2:$F$5000,INCOMING!$C$2:$C$5000,$A29,INCOMING!$D$2:$D$5000,$B29,INCOMING!$B$2:$B$5000,">="&$C29,INCOMING!$B$2:$B$5000,"<="&DATE(2026,10,17)) -> 0 | F29: =SUMIFS(OUT!$F$14:$F$5084,OUT!$C$14:$C$5084,$A29,OUT!$D$14:$D$5084,$B29,OUT!$B$14:$B$5084,">="&$C29,OUT!$B$14:$B$5084,"<="&DATE(2026,10,17),OUT!$L$14:$L$5084,"<>Adjustment") -> 0 | G29: =D29+E29-F29 -> 0.087675 | H29: =SUMIFS('LAPORAN OPERATION'!$F$2:$F$1000,'LAPORAN OPERATION'!$A$2:$A$1000,DATE(2026,10,17),'LAPORAN OPERATION'!$B$2:$B$1000,"Balance",'LAPORAN OPERATION'!$C$2:$C$1000,IF($A29="Pine","Pinus",$A29),'LAPORAN OPERATION'!$D$2:$D$1000,$B29)+SUMIFS('LAPORAN OPERATION'!$F$2:$F$1000,'LAPORAN OPERATION'!$A$2:$A$1000,DATE(2026,10,17),'LAPORAN OPERATION'!$B$2:$B$1000,"Balance",'LAPORAN OPERATION'!$C$2:$C$1000,IF($A29="Pine","Pinus",$A29),'LAPORAN OPERATION'!$D$2:$D$1000,$B29&" (Grade A)") -> 0.087675 | I29: =ROUND(G29-H29,6) -> 0 | J29: =SUMIFS(INCOMING!$F$2:$F$5000,INCOMING!$C$2:$C$5000,$A29,INCOMING!$D$2:$D$5000,$B29,INCOMING!$B$2:$B$5000,">="&DATE(2026,10,18),INCOMING!$B$2:$B$5000,"<="&DATE(2026,10,21)) -> 0 | K29: =SUMIFS(OUT!$F$14:$F$5084,OUT!$C$14:$C$5084,$A29,OUT!$D$14:$D$5084,$B29,OUT!$B$14:$B$5084,">="&DATE(2026,10,18),OUT!$B$14:$B$5084,"<="&DATE(2026,10,21),OUT!$L$14:$L$5084,"<>Adjustment") -> 0 | L29: =G29+J29-K29 -> 0.087675 | M29: =SUMIFS('LAPORAN OPERATION'!$F$2:$F$1000,'LAPORAN OPERATION'!$A$2:$A$1000,DATE(2026,10,21),'LAPORAN OPERATION'!$B$2:$B$1000,"Balance",'LAPORAN OPERATION'!$C$2:$C$1000,IF($A29="Pine","Pinus",$A29),'LAPORAN OPERATION'!$D$2:$D$1000,$B29)+SUMIFS('LAPORAN OPERATION'!$F$2:$F$1000,'LAPORAN OPERATION'!$A$2:$A$1000,DATE(2026,10,21),'LAPORAN OPERATION'!$B$2:$B$1000,"Balance",'LAPORAN OPERATION'!$C$2:$C$1000,IF($A29="Pine","Pinus",$A29),'LAPORAN OPERATION'!$D$2:$D$1000,$B29&" (Grade A)") -> 0.087675 | N29: =ROUND(L29-M29,6) -> 0 | O29: =SUMIFS(INCOMING!$F$2:$F$5000,INCOMING!$C$2:$C$5000,$A29,INCOMING!$D$2:$D$5000,$B29,INCOMING!$B$2:$B$5000,">="&DATE(2026,10,22),INCOMING!$B$2:$B$5000,"<="&DATE(2026,10,24)) -> 0 | P29: =SUMIFS(OUT!$F$14:$F$5084,OUT!$C$14:$C$5084,$A29,OUT!$D$14:$D$5084,$B29,OUT!$B$14:$B$5084,">="&DATE(2026,10,22),OUT!$B$14:$B$5084,"<="&DATE(2026,10,24),OUT!$L$14:$L$5084,"<>Adjustment") -> 0 | Q29: =L29+O29-P29 -> 0.087675 | R29: =SUMIFS('LAPORAN OPERATION'!$F$2:$F$1000,'LAPORAN OPERATION'!$A$2:$A$1000,DATE(2026,10,24),'LAPORAN OPERATION'!$B$2:$B$1000,"Count",'LAPORAN OPERATION'!$C$2:$C$1000,IF($A29="Pine","Pinus",$A29),'LAPORAN OPERATION'!$D$2:$D$1000,$B29)+SUMIFS('LAPORAN OPERATION'!$F$2:$F$1000,'LAPORAN OPERATION'!$A$2:$A$1000,DATE(2026,10,24),'LAPORAN OPERATION'!$B$2:$B$1000,"Count",'LAPORAN OPERATION'!$C$2:$C$1000,IF($A29="Pine","Pinus",$A29),'LAPORAN OPERATION'!$D$2:$D$1000,$B29&" (Grade A)") -> 0.087675 | S29: =ROUND(Q29-R29,6) -> 0
A30: Total Pine | D30: =SUM(D28:D29) -> 0.136455 | E30: =SUM(E28:E29) -> 0 | F30: =SUM(F28:F29) -> 0.014275 | G30: =SUM(G28:G29) -> 0.12218 | H30: =SUM(H28:H29) -> 0.12218 | I30: =SUM(I28:I29) -> 0 | J30: =SUM(J28:J29) -> 0 | K30: =SUM(K28:K29) -> 0 | ... S30: =SUM(S28:S29) -> 0
A32: Laporan stok Operation: Wood Stock Inhouse Reports (per Oct 24, 2026).xlsx di 2026\ARSIP\NEW MANAGER\DONALD\02. WOOD, sheet Per Oct 17, 2026 (Count tanggal 14 Okt dan Balance 17 Okt), Per Oct 21, 2026 (Balance 21 Okt) dan Per Oct 24, 2026 (Count 24 Okt). Laporan yang sama dalam PDF: Wood Stock (17 Oct 2026).pdf di 2026\01 INPUT\KAYU\2026-10-17 dan Wood Stock (24 Oct 2026).pdf di folder DONALD tersebut.
A33: Catatan harian: 08_Teak Wood 2026 - By Nuriyanti (1).xlsx, 08_Sungkai Wood 2026 - By Nuriyanti.xlsx dan 08_Pinus Wood 2026.xlsx di 2026\ARSIP\NEW MANAGER\DONALD\02. WOOD, sheet Incomming dan sheet Out per tanggal.
A34: Keluar Pinus mulai 14 Okt karena laporan stok memasukkan pemakaian Pinus 14 Okt di kolom Out.

Sheet IN
A1: No. | B1: PO Date | C1: PO No. | D1: Wood Type | E1: Form | F1: Supplier | G1: Volume (m³) | H1: Value (Rp) | I1: Price per m³ (Rp) | J1: Goods Status | K1: Payment Status | L1: Source | M1: Receipt No. | N1: Invoice No. (Accurate) | O1: Down Payment No. | P1: Payment No.
A2: 1 | B2: 45972 | C2: PO251100011 | D2: Teak | E2: Board | F2: Jujur Jaya | G2: 0.044444 | H2: 400000 | I2: =IF(G2=0,0,H2/G2) -> 9000090 | J2: =IF(OR(tblIN[[#This Row],[Receipt No.]]="",tblIN[[#This Row],[Receipt No.]]="Not received"),"Not received","Received") -> Received | K2: =IF(OR(tblIN[[#This Row],[Payment No.]]="",tblIN[[#This Row],[Payment No.]]="Unpaid"),"Still on waiting Schedule Payment","Paid 100%") -> Paid 100% | L2: WOOD_PURCHASE TEAK row 5 | M2: RI.2025.11.00009 | N2: FB251100015 | O2: No DP | P2: 110203.2025.11.00028
A3: 2 | B3: 45972 | C3: PO251100013 | D3: Teak | E3: Board | F3: Jujur Jaya | G3: 2.49923 | H3: 25369960 | I3: =IF(G3=0,0,H3/G3) -> 10151111 | J3: =IF(OR(tblIN[[#This Row],[Receipt No.]]="",tblIN[[#This Row],[Receipt No.]]="Not received"),"Not received","Received") -> Received | K3: =IF(OR(tblIN[[#This Row],[Payment No.]]="",tblIN[[#This Row],[Payment No.]]="Unpaid"),"Still on waiting Schedule Payment","Paid 100%") -> Paid 100% | L3: WOOD_PURCHASE TEAK row 6 | M3: RI.2025.12.00002 | N3: FB251200006 | O3: No DP | P3: 110203.2025.12.00046
A4: 3 | B4: 45980 | C4: PO251100028 | D4: Teak | E4: Board | F4: Ariana | G4: 0.4314 | H4: 4248900 | I4: =IF(G4=0,0,H4/G4) -> 9849096 | J4: =IF(OR(tblIN[[#This Row],[Receipt No.]]="",tblIN[[#This Row],[Receipt No.]]="Not received"),"Not received","Received") -> Received | K4: =IF(OR(tblIN[[#This Row],[Payment No.]]="",tblIN[[#This Row],[Payment No.]]="Unpaid"),"Still on waiting Schedule Payment","Paid 100%") -> Paid 100% | L4: WOOD_PURCHASE TEAK row 8 | M4: RI.2025.11.00037 | N4: FB251100047 | O4: No DP | P4: 110101.2025.11.00113
A5: 4 | B5: 46006 | C5: PO251200015 | D5: Teak | E5: Board | F5: Ariana | G5: 0.0685 | H5: 616500 | I5: =IF(G5=0,0,H5/G5) -> 9000000 | J5: =IF(OR(tblIN[[#This Row],[Receipt No.]]="",tblIN[[#This Row],[Receipt No.]]="Not received"),"Not received","Received") -> Received | K5: =IF(OR(tblIN[[#This Row],[Payment No.]]="",tblIN[[#This Row],[Payment No.]]="Unpaid"),"Still on waiting Schedule Payment","Paid 100%") -> Paid 100% | L5: WOOD_PURCHASE TEAK row 9 | M5: RI.2025.12.00032 | N5: FB251200045 | O5: No DP | P5: 110101.2025.12.00112
A6: 5 | B6: 46035 | C6: PO260100010 | D6: Teak | E6: Board | F6: Ariana | G6: =1.0069+1.5006+1.0175+2.0235+0.5171+0.5087 -> 6.5743 | H6: 57525125 | I6: =IF(G6=0,0,H6/G6) -> 8750000 | J6: =IF(OR(tblIN[[#This Row],[Receipt No.]]="",tblIN[[#This Row],[Receipt No.]]="Not received"),"Not received","Received") -> Received | K6: =IF(OR(tblIN[[#This Row],[Payment No.]]="",tblIN[[#This Row],[Payment No.]]="Unpaid"),"Still on waiting Schedule Payment","Paid 100%") -> Paid 100% | L6: WOOD_PURCHASE TEAK row 10 | M6: RI.2026.01.00103, RI.2026.02.00061 | N6: FB260100145, FB260200117 | O6: No DP | P6: 110207.2026.01.00071, 110207.2026.03.00003
A7: 6 | B7: 46057 | C7: PO260200002 | D7: Teak | E7: Board | F7: H. Tasmo - Koperasi Albarokah | G7: 3.1489 | H7: 23616750 | I7: =IF(G7=0,0,H7/G7) -> 7500000 | J7: =IF(OR(tblIN[[#This Row],[Receipt No.]]="",tblIN[[#This Row],[Receipt No.]]="Not received"),"Not received","Received") -> Received | K7: =IF(OR(tblIN[[#This Row],[Payment No.]]="",tblIN[[#This Row],[Payment No.]]="Unpaid"),"Still on waiting Schedule Payment","Paid 100%") -> Paid 100% | L7: WOOD_PURCHASE TEAK row 21 | M7: RI.2026.02.00013 | N7: FB260200026 | O7: No DP | P7: 110207.2026.02.00035
A8: 7 | B8: 46063 | C8: PO260200015 | D8: Teak | E8: Board | F8: UD. Divky Wood | G8: 2.623685 | H8: 19815240 | I8: =IF(G8=0,0,H8/G8) -> 7552446.3 | J8: =IF(OR(tblIN[[#This Row],[Receipt No.]]="",tblIN[[#This Row],[Receipt No.]]="Not received"),"Not received","Received") -> Received | K8: =IF(OR(tblIN[[#This Row],[Payment No.]]="",tblIN[[#This Row],[Payment No.]]="Unpaid"),"Still on waiting Schedule Payment","Paid 100%") -> Paid 100% | L8: WOOD_PURCHASE TEAK row 16 | M8: RI.2026.02.00026 | N8: FB260200041 | O8: No DP | P8: 110207.2026.02.00057
A9: 8 | B9: 46070 | C9: PO260200048 | D9: Teak | E9: Board | F9: H. Tasmo - Koperasi Albarokah | G9: 5.2289 | H9: 28758950 | I9: =IF(G9=0,0,H9/G9) -> 5500000 | J9: =IF(OR(tblIN[[#This Row],[Receipt No.]]="",tblIN[[#This Row],[Receipt No.]]="Not received"),"Not received","Received") -> Received | K9: =IF(OR(tblIN[[#This Row],[Payment No.]]="",tblIN[[#This Row],[Payment No.]]="Unpaid"),"Still on waiting Schedule Payment","Paid 100%") -> Paid 100% | L9: WOOD_PURCHASE TEAK row 19 | M9: RI.2026.02.00093 | N9: FB260200152 | O9: No DP | P9: 110207.2026.03.00004
A10: 9 | B10: 46112 | C10: PO260300023 | D10: Teak | E10: Board | F10: UD. Divky Wood | G10: 3.495125 | H10: 26519650 | I10: =IF(G10=0,0,H10/G10) -> 7587611.5 | J10: =IF(OR(tblIN[[#This Row],[Receipt No.]]="",tblIN[[#This Row],[Receipt No.]]="Not received"),"Not received","Received") -> Received | K10: =IF(OR(tblIN[[#This Row],[Payment No.]]="",tblIN[[#This Row],[Payment No.]]="Unpaid"),"Still on waiting Schedule Payment","Paid 100%") -> Paid 100% | L10: WOOD_PURCHASE TEAK row 12 | M10: RI.2026.03.00108 | N10: FB260400068 | O10: No DP | P10: 110207.2026.04.00025
A11: 10 | B11: 46112 | C11: PO260300022 | D11: Teak | E11: Board | F11: H. Tasmo - Koperasi Albarokah | G11: 5.229 | H11: 27153900 | I11: =IF(G11=0,0,H11/G11) -> 5192943.2 | J11: =IF(OR(tblIN[[#This Row],[Receipt No.]]="",tblIN[[#This Row],[Receipt No.]]="Not received"),"Not received","Received") -> Received | K11: =IF(OR(tblIN[[#This Row],[Payment No.]]="",tblIN[[#This Row],[Payment No.]]="Unpaid"),"Still on waiting Schedule Payment","Paid 100%") -> Paid 100% | L11: WOOD_PURCHASE TEAK row 20 | M11: RI.2026.04.00133 | N11: FB260500046 | O11: No DP | P11: 110207.2026.05.00057
A12: 11 | B12: 46115 | C12: PO260400043 | D12: Teak | E12: Board | F12: UD. Divky Wood | G12: 1.41672 | H12: 10625400 | I12: =IF(G12=0,0,H12/G12) -> 7500000 | J12: =IF(OR(tblIN[[#This Row],[Receipt No.]]="",tblIN[[#This Row],[Receipt No.]]="Not received"),"Not received","Received") -> Received | K12: =IF(OR(tblIN[[#This Row],[Payment No.]]="",tblIN[[#This Row],[Payment No.]]="Unpaid"),"Still on waiting Schedule Payment","Paid 100%") -> Paid 100% | L12: WOOD_PURCHASE TEAK row 13 | M12: RI.2026.04.00135 | N12: FB260400192 | O12: No DP | P12: 110207.2026.05.00079
A13: 12 | B13: 46125 | C13: PO260400019 | D13: Teak | E13: Board | F13: UD. Divky Wood | G13: 3.73897 | H13: =28042275+225 -> 28042500 | I13: =IF(G13=0,0,H13/G13) -> 7500060.2 | J13: =IF(OR(tblIN[[#This Row],[Receipt No.]]="",tblIN[[#This Row],[Receipt No.]]="Not received"),"Not received","Received") -> Received | K13: =IF(OR(tblIN[[#This Row],[Payment No.]]="",tblIN[[#This Row],[Payment No.]]="Unpaid"),"Still on waiting Schedule Payment","Paid 100%") -> Paid 100% | L13: WOOD_PURCHASE TEAK row 14 | M13: RI.2026.04.00055 | N13: FB260400108 | O13: No DP | P13: 110207.2026.04.00045
A14: 13 | B14: 46125 | C14: PO260400020 | D14: Teak | E14: Board | F14: H. Tasmo - Koperasi Albarokah | G14: =H14/7500000 -> 5.8880368 | H14: 44160276 | I14: =IF(G14=0,0,H14/G14) -> 7500000 | J14: =IF(OR(tblIN[[#This Row],[Receipt No.]]="",tblIN[[#This Row],[Receipt No.]]="Not received"),"Not received","Received") -> Received | K14: =IF(OR(tblIN[[#This Row],[Payment No.]]="",tblIN[[#This Row],[Payment No.]]="Unpaid"),"Still on waiting Schedule Payment","Paid 100%") -> Paid 100% | L14: WOOD_PURCHASE TEAK row 31 | M14: RI.2026.05.00147 | N14: FB260800145 | O14: No DP | P14: 110207.2026.08.00090
A15: 14 | B15: 46136 | C15: PO260400044 | D15: Teak | E15: Board | F15: UD. Divky Wood | G15: 7.404915 | H15: 56962560 | I15: =IF(G15=0,0,H15/G15) -> 7692533.9 | J15: =IF(OR(tblIN[[#This Row],[Receipt No.]]="",tblIN[[#This Row],[Receipt No.]]="Not received"),"Not received","Received") -> Received | K15: =IF(OR(tblIN[[#This Row],[Payment No.]]="",tblIN[[#This Row],[Payment No.]]="Unpaid"),"Still on waiting Schedule Payment","Paid 100%") -> Paid 100% | L15: WOOD_PURCHASE TEAK row 15 | M15: RI.2026.04.00097 | N15: FB260400155 | O15: No DP | P15: 110207.2026.05.00028
A16: 15 | B16: 46153 | C16: PO260500007 | D16: Teak | E16: Board | F16: H. Tasmo - Koperasi Albarokah | G16: 1.6292 | H16: 12219000 | I16: =IF(G16=0,0,H16/G16) -> 7500000 | J16: =IF(OR(tblIN[[#This Row],[Receipt No.]]="",tblIN[[#This Row],[Receipt No.]]="Not received"),"Not received","Received") -> Received | K16: =IF(OR(tblIN[[#This Row],[Payment No.]]="",tblIN[[#This Row],[Payment No.]]="Unpaid"),"Still on waiting Schedule Payment","Paid 100%") -> Paid 100% | L16: WOOD_PURCHASE TEAK row 22 | M16: RI.2026.05.00028 | N16: FB260500045 | O16: No DP | P16: 110207.2026.05.00043
A17: 16 | B17: 46176 | C17: PO260600020 | D17: Teak | E17: Board | F17: H. Tasmo - Koperasi Albarokah | G17: 2.04603 | H17: =15345225-225 -> 15345000 | I17: =IF(G17=0,0,H17/G17) -> 7499890 | J17: =IF(OR(tblIN[[#This Row],[Receipt No.]]="",tblIN[[#This Row],[Receipt No.]]="Not received"),"Not received","Received") -> Received | K17: =IF(OR(tblIN[[#This Row],[Payment No.]]="",tblIN[[#This Row],[Payment No.]]="Unpaid"),"Still on waiting Schedule Payment","Paid 100%") -> Paid 100% | L17: WOOD_PURCHASE TEAK row 23 | M17: RI.2026.06.00076 | N17: FB260600090 | O17: No DP | P17: 110207.2026.06.00026
A18: 17 | B18: 46176 | C18: PO260500005 | D18: Teak | E18: Board | F18: H. Tasmo - Koperasi Albarokah | G18: =H18/7500000 -> 5.8428619 | H18: =15349000+43821464-15349000 -> 43821464 | I18: =IF(G18=0,0,H18/G18) -> 7500000 | J18: =IF(OR(tblIN[[#This Row],[Receipt No.]]="",tblIN[[#This Row],[Receipt No.]]="Not received"),"Not received","Received") -> Received | K18: =IF(OR(tblIN[[#This Row],[Payment No.]]="",tblIN[[#This Row],[Payment No.]]="Unpaid"),"Still on waiting Schedule Payment","Paid 100%") -> Paid 100% | L18: WOOD_PURCHASE TEAK row 33 | M18: RI.2026.07.00265 | N18: FB260800173 | O18: No DP | P18: 110207.2026.09.00038
A19: 18 | B19: 46183 | C19: PO260600023 | D19: Teak | E19: Log | F19: H. Tasmo - Koperasi Albarokah | G19: =H19/7500000 -> 6.9346667 | H19: 52010000 | I19: =IF(G19=0,0,H19/G19) -> 7500000 | J19: =IF(OR(tblIN[[#This Row],[Receipt No.]]="",tblIN[[#This Row],[Receipt No.]]="Not received"),"Not received","Received") -> Received | K19: =IF(OR(tblIN[[#This Row],[Payment No.]]="",tblIN[[#This Row],[Payment No.]]="Unpaid"),"Still on waiting Schedule Payment","Paid 100%") -> Paid 100% | L19: WOOD_PURCHASE TEAK row 37 | M19: RI.2026.07.00264 | N19: FB260800171 | O19: No DP | P19: 110207.2026.09.00066
A20: 19 | B20: 46190 | C20: PO260600032 | D20: Teak | E20: Board | F20: H. Tasmo - Koperasi Albarokah | G20: 3.5862 | H20: 26896500 | I20: =IF(G20=0,0,H20/G20) -> 7500000 | J20: =IF(OR(tblIN[[#This Row],[Receipt No.]]="",tblIN[[#This Row],[Receipt No.]]="Not received"),"Not received","Received") -> Received | K20: =IF(OR(tblIN[[#This Row],[Payment No.]]="",tblIN[[#This Row],[Payment No.]]="Unpaid"),"Still on waiting Schedule Payment","Paid 100%") -> Paid 100% | L20: WOOD_PURCHASE TEAK row 24 | M20: RI.2026.06.00177 | N20: FB260600207 | O20: No DP | P20: 110207.2026.07.00036
A21: 20 | B21: 46198 | C21: PO260600057 | D21: Teak | E21: Board | F21: H. Tasmo - Koperasi Albarokah | G21: 3.2899 | H21: 24674250 | I21: =IF(G21=0,0,H21/G21) -> 7500000 | J21: =IF(OR(tblIN[[#This Row],[Receipt No.]]="",tblIN[[#This Row],[Receipt No.]]="Not received"),"Not received","Received") -> Received | K21: =IF(OR(tblIN[[#This Row],[Payment No.]]="",tblIN[[#This Row],[Payment No.]]="Unpaid"),"Still on waiting Schedule Payment","Paid 100%") -> Paid 100% | L21: WOOD_PURCHASE TEAK row 25 | M21: RI.2026.06.00173 | N21: FB260700033 | O21: No DP | P21: 110207.2026.07.00004
A22: 21 | B22: 46203 | C22: PO260600058 | D22: Teak | E22: Board | F22: H. Tasmo - Koperasi Albarokah | G22: 4.02 | H22: 30150000 | I22: =IF(G22=0,0,H22/G22) -> 7500000 | J22: =IF(OR(tblIN[[#This Row],[Receipt No.]]="",tblIN[[#This Row],[Receipt No.]]="Not received"),"Not received","Received") -> Received | K22: =IF(OR(tblIN[[#This Row],[Payment No.]]="",tblIN[[#This Row],[Payment No.]]="Unpaid"),"Still on waiting Schedule Payment","Paid 100%") -> Paid 100% | L22: WOOD_PURCHASE TEAK row 27 | M22: RI.2026.07.00132 | N22: FB260700146 | O22: DP260700003 | P22: 110207.2026.07.00045
A23: 22 | B23: 46206 | C23: PO260700013 | D23: Teak | E23: Board | F23: H. Tasmo - Koperasi Albarokah | G23: 5.8887 | H23: 44165250 | I23: =IF(G23=0,0,H23/G23) -> 7500000 | J23: =IF(OR(tblIN[[#This Row],[Receipt No.]]="",tblIN[[#This Row],[Receipt No.]]="Not received"),"Not received","Received") -> Received | K23: =IF(OR(tblIN[[#This Row],[Payment No.]]="",tblIN[[#This Row],[Payment No.]]="Unpaid"),"Still on waiting Schedule Payment","Paid 100%") -> Paid 100% | L23: WOOD_PURCHASE TEAK row 26 | M23: RI.2026.07.00200 | N23: FB260700219 | O23: DP260700006 | P23: 110207.2026.07.00076
A24: 23 | B24: 46209 | C24: PO260700062 | D24: Teak | E24: Board | F24: H. Tasmo - Koperasi Albarokah | G24: =H24/7500000 -> 5.76 | H24: 43200000 | I24: =IF(G24=0,0,H24/G24) -> 7500000 | J24: =IF(OR(tblIN[[#This Row],[Receipt No.]]="",tblIN[[#This Row],[Receipt No.]]="Not received"),"Not received","Received") -> Received | K24: =IF(OR(tblIN[[#This Row],[Payment No.]]="",tblIN[[#This Row],[Payment No.]]="Unpaid"),"Still on waiting Schedule Payment","Paid 100%") -> Paid 100% | L24: WOOD_PURCHASE TEAK row 32 | M24: RI.2026.08.00144 | N24: FB260800175 | O24: No DP | P24: 110207.2026.09.00007
A25: 24 | B25: 46214 | C25: PO260700026 | D25: Teak | E25: Board | F25: H. Tasmo - Koperasi Albarokah | G25: =H25/7500000 -> 3.6077 | H25: 27057750 | I25: =IF(G25=0,0,H25/G25) -> 7500000 | J25: =IF(OR(tblIN[[#This Row],[Receipt No.]]="",tblIN[[#This Row],[Receipt No.]]="Not received"),"Not received","Received") -> Received | K25: =IF(OR(tblIN[[#This Row],[Payment No.]]="",tblIN[[#This Row],[Payment No.]]="Unpaid"),"Still on waiting Schedule Payment","Paid 100%") -> Paid 100% | L25: WOOD_PURCHASE TEAK row 28 | M25: RI.2026.07.00245 | N25: FB260700275 | O25: No DP | P25: 110207.2026.07.00102
A26: 25 | B26: 46220 | C26: PO260700028 | D26: Teak | E26: Board | F26: H. Tasmo - Koperasi Albarokah | G26: =H26/7500000 -> 3.3237333 | H26: 24928000 | I26: =IF(G26=0,0,H26/G26) -> 7500000 | J26: =IF(OR(tblIN[[#This Row],[Receipt No.]]="",tblIN[[#This Row],[Receipt No.]]="Not received"),"Not received","Received") -> Received | K26: =IF(OR(tblIN[[#This Row],[Payment No.]]="",tblIN[[#This Row],[Payment No.]]="Unpaid"),"Still on waiting Schedule Payment","Paid 100%") -> Paid 100% | L26: WOOD_PURCHASE TEAK row 29 | M26: RI.2026.07.00247 | N26: FB260700281 | O26: No DP | P26: 110207.2026.08.00035
A27: 26 | B27: 46220 | C27: PO260700029 | D27: Teak | E27: Board | F27: H. Tasmo - Koperasi Albarokah | G27: =H27/7500000 -> 4.0142 | H27: 30106500 | I27: =IF(G27=0,0,H27/G27) -> 7500000 | J27: =IF(OR(tblIN[[#This Row],[Receipt No.]]="",tblIN[[#This Row],[Receipt No.]]="Not received"),"Not received","Received") -> Received | K27: =IF(OR(tblIN[[#This Row],[Payment No.]]="",tblIN[[#This Row],[Payment No.]]="Unpaid"),"Still on waiting Schedule Payment","Paid 100%") -> Paid 100% | L27: WOOD_PURCHASE TEAK row 30 | M27: RI.2026.07.00248 | N27: FB260700283 | O27: No DP | P27: 110207.2026.08.00062
A28: 27 | B28: 46220 | C28: PO260700027 | D28: Teak | E28: Log | F28: H. Tasmo - Koperasi Albarokah | G28: =H28/7500000 -> 6.9365333 | H28: 52024000 | I28: =IF(G28=0,0,H28/G28) -> 7500000 | J28: =IF(OR(tblIN[[#This Row],[Receipt No.]]="",tblIN[[#This Row],[Receipt No.]]="Not received"),"Not received","Received") -> Received | K28: =IF(OR(tblIN[[#This Row],[Payment No.]]="",tblIN[[#This Row],[Payment No.]]="Unpaid"),"Still on waiting Schedule Payment","Paid 100%") -> Paid 100% | L28: WOOD_PURCHASE TEAK row 38 | M28: RI.2026.08.00143 | N28: FB260800174 | O28: No DP | P28: 110207.2026.09.00098
A29: 28 | B29: 46233 | C29: PO260700064 | D29: Teak | E29: Board | F29: H. Tasmo - Koperasi Albarokah | G29: =H29/7500000 -> 9.9407 | H29: 74555250 | I29: =IF(G29=0,0,H29/G29) -> 7500000 | J29: =IF(OR(tblIN[[#This Row],[Receipt No.]]="",tblIN[[#This Row],[Receipt No.]]="Not received"),"Not received","Received") -> Received | K29: =IF(OR(tblIN[[#This Row],[Payment No.]]="",tblIN[[#This Row],[Payment No.]]="Unpaid"),"Still on waiting Schedule Payment","Paid 100%") -> Paid 100% | L29: WOOD_PURCHASE TEAK row 39 | M29: RI.2026.08.00148 | N29: FB260800178 | O29: No DP | P29: 110207.2026.10.00053
A30: 29 | B30: 46233 | C30: PO260700065 | D30: Teak | E30: Board | F30: H. Tasmo - Koperasi Albarokah | G30: =H30/7500000 -> 10.6625 | H30: 79968750 | I30: =IF(G30=0,0,H30/G30) -> 7500000 | J30: =IF(OR(tblIN[[#This Row],[Receipt No.]]="",tblIN[[#This Row],[Receipt No.]]="Not received"),"Not received","Received") -> Received | K30: =IF(OR(tblIN[[#This Row],[Payment No.]]="",tblIN[[#This Row],[Payment No.]]="Unpaid"),"Still on waiting Schedule Payment","Paid 100%") -> Still on waiting Schedule Payment | L30: WOOD_PURCHASE TEAK row 40 | M30: RI.2026.09.00028 | N30: FB260900030 | O30: No DP | P30: Unpaid
A31: 30 | B31: 46241 | C31: PO260800002 | D31: Teak | E31: Board | F31: UD. Divky Wood | G31: 3.8 | H31: 28532250 | I31: =IF(G31=0,0,H31/G31) -> 7508486.8 | J31: =IF(OR(tblIN[[#This Row],[Receipt No.]]="",tblIN[[#This Row],[Receipt No.]]="Not received"),"Not received","Received") -> Received | K31: =IF(OR(tblIN[[#This Row],[Payment No.]]="",tblIN[[#This Row],[Payment No.]]="Unpaid"),"Still on waiting Schedule Payment","Paid 100%") -> Paid 100% | L31: WOOD_PURCHASE TEAK row 17 | M31: RI.2026.08.00034 | N31: FB260800038 | O31: No DP | P31: 110207.2026.08.00036
A32: 31 | B32: 46252 | C32: PO260800022 | D32: Teak | E32: Board | F32: H. Tasmo - Koperasi Albarokah | G32: =H32/7500000 -> 3.0209 | H32: 22656750 | I32: =IF(G32=0,0,H32/G32) -> 7500000 | J32: =IF(OR(tblIN[[#This Row],[Receipt No.]]="",tblIN[[#This Row],[Receipt No.]]="Not received"),"Not received","Received") -> Received | K32: =IF(OR(tblIN[[#This Row],[Payment No.]]="",tblIN[[#This Row],[Payment No.]]="Unpaid"),"Still on waiting Schedule Payment","Paid 100%") -> Paid 100% | L32: WOOD_PURCHASE TEAK row 41 | M32: RI.2026.08.00147 | N32: FB260800177 | O32: No DP | P32: 110207.2026.10.00029
A33: 32 | B33: 46273 | C33: PO260900004 | D33: Teak | E33: Board | F33: H. Tasmo - Koperasi Albarokah | G33: =H33/7500000 -> 3.5188 | H33: 26391000 | I33: =IF(G33=0,0,H33/G33) -> 7500000 | J33: =IF(OR(tblIN[[#This Row],[Receipt No.]]="",tblIN[[#This Row],[Receipt No.]]="Not received"),"Not received","Received") -> Received | K33: =IF(OR(tblIN[[#This Row],[Payment No.]]="",tblIN[[#This Row],[Payment No.]]="Unpaid"),"Still on waiting Schedule Payment","Paid 100%") -> Still on waiting Schedule Payment | L33: WOOD_PURCHASE TEAK row 42 | M33: RI.2026.09.00029 | N33: FB260900038 | O33: No DP | P33: Unpaid
A34: 33 | B34: 46031 | C34: PO260100007 | D34: Sungkai | E34: Board | F34: Jujur Jaya | G34: 0.9326 | H34: 5222560 | I34: =IF(G34=0,0,H34/G34) -> 5600000 | J34: =IF(OR(tblIN[[#This Row],[Receipt No.]]="",tblIN[[#This Row],[Receipt No.]]="Not received"),"Not received","Received") -> Received | K34: =IF(OR(tblIN[[#This Row],[Payment No.]]="",tblIN[[#This Row],[Payment No.]]="Unpaid"),"Still on waiting Schedule Payment","Paid 100%") -> Paid 100% | L34: WOOD_PURCHASE SUNKAI row 5 | M34: RI.2026.01.00031 | N34: FB260100060 | O34: No DP | P34: 110207.2026.01.00045
A35: 34 | B35: 46048 | C35: PO260100033 | D35: Sungkai | E35: Board | F35: Iskandar | G35: 1 | H35: 6000000 | I35: =IF(G35=0,0,H35/G35) -> 6000000 | J35: =IF(OR(tblIN[[#This Row],[Receipt No.]]="",tblIN[[#This Row],[Receipt No.]]="Not received"),"Not received","Received") -> Received | K35: =IF(OR(tblIN[[#This Row],[Payment No.]]="",tblIN[[#This Row],[Payment No.]]="Unpaid"),"Still on waiting Schedule Payment","Paid 100%") -> Paid 100% | L35: WOOD_PURCHASE SUNKAI row 8 | M35: RI.2026.01.00082 | N35: FB260100127 | O35: No DP | P35: 110207.2026.02.00010
A36: 35 | B36: 46063 | C36: PO260200014 | D36: Sungkai | E36: Board | F36: Jujur Jaya | G36: 0.6394 | H36: 3580640 | I36: =IF(G36=0,0,H36/G36) -> 5600000 | J36: =IF(OR(tblIN[[#This Row],[Receipt No.]]="",tblIN[[#This Row],[Receipt No.]]="Not received"),"Not received","Received") -> Received | K36: =IF(OR(tblIN[[#This Row],[Payment No.]]="",tblIN[[#This Row],[Payment No.]]="Unpaid"),"Still on waiting Schedule Payment","Paid 100%") -> Paid 100% | L36: WOOD_PURCHASE SUNKAI row 6 | M36: RI.2026.02.00025 | N36: FB260200040 | O36: No DP | P36: 110207.2026.02.00056
A37: 36 | B37: 46112 | C37: PO260300025 | D37: Sungkai | E37: Board | F37: CV. Indoraya | G37: 9.1449 | H37: 50296950 | I37: =IF(G37=0,0,H37/G37) -> 5500000 | J37: =IF(OR(tblIN[[#This Row],[Receipt No.]]="",tblIN[[#This Row],[Receipt No.]]="Not received"),"Not received","Received") -> Received | K37: =IF(OR(tblIN[[#This Row],[Payment No.]]="",tblIN[[#This Row],[Payment No.]]="Unpaid"),"Still on waiting Schedule Payment","Paid 100%") -> Paid 100% | L37: WOOD_PURCHASE SUNKAI row 11 | M37: RI.2026.04.00004 | N37: FB260400047 | O37: No DP | P37: 110101.2026.04.00047
A38: 37 | B38: 46130 | C38: PO260400028 | D38: Sungkai | E38: Board | F38: UD. Divky Wood | G38: 7.18675 | H38: 24297924 | I38: =IF(G38=0,0,H38/G38) -> 3380933.5 | J38: =IF(OR(tblIN[[#This Row],[Receipt No.]]="",tblIN[[#This Row],[Receipt No.]]="Not received"),"Not received","Received") -> Received | K38: =IF(OR(tblIN[[#This Row],[Payment No.]]="",tblIN[[#This Row],[Payment No.]]="Unpaid"),"Still on waiting Schedule Payment","Paid 100%") -> Paid 100% | L38: WOOD_PURCHASE SUNKAI row 13 | M38: RI.2026.04.00095 | N38: FB260400153 | O38: No DP | P38: 110207.2026.05.00011
A39: 38 | B39: 46133 | C39: PO260400042 | D39: Sungkai | E39: Board | F39: UD. Divky Wood | G39: 8.1792 | H39: 30069184 | I39: =IF(G39=0,0,H39/G39) -> 3676298.9 | J39: =IF(OR(tblIN[[#This Row],[Receipt No.]]="",tblIN[[#This Row],[Receipt No.]]="Not received"),"Not received","Received") -> Received | K39: =IF(OR(tblIN[[#This Row],[Payment No.]]="",tblIN[[#This Row],[Payment No.]]="Unpaid"),"Still on waiting Schedule Payment","Paid 100%") -> Paid 100% | L39: WOOD_PURCHASE SUNKAI row 15 | M39: RI.2026.04.00134 | N39: FB260400191 | O39: No DP | P39: 110207.2026.05.00060
A40: 39 | B40: 46139 | C40: PO260400033 | D40: Sungkai | E40: Board | F40: CV. Indoraya | G40: 9.5695125 | H40: 52632319 | I40: =IF(G40=0,0,H40/G40) -> 5500000 | J40: =IF(OR(tblIN[[#This Row],[Receipt No.]]="",tblIN[[#This Row],[Receipt No.]]="Not received"),"Not received","Received") -> Received | K40: =IF(OR(tblIN[[#This Row],[Payment No.]]="",tblIN[[#This Row],[Payment No.]]="Unpaid"),"Still on waiting Schedule Payment","Paid 100%") -> Paid 100% | L40: WOOD_PURCHASE SUNKAI row 10 | M40: RI.2026.04.00131 | N40: FB260400189 | O40: DP260400005 | P40: 110207.2026.05.00008
A41: 40 | B41: 46139 | C41: PO260400029 | D41: Sungkai | E41: Board | F41: UD. Divky Wood | G41: 6.453 | H41: 25567560 | I41: =IF(G41=0,0,H41/G41) -> 3962119.9 | J41: =IF(OR(tblIN[[#This Row],[Receipt No.]]="",tblIN[[#This Row],[Receipt No.]]="Not received"),"Not received","Received") -> Received | K41: =IF(OR(tblIN[[#This Row],[Payment No.]]="",tblIN[[#This Row],[Payment No.]]="Unpaid"),"Still on waiting Schedule Payment","Paid 100%") -> Paid 100% | L41: WOOD_PURCHASE SUNKAI row 14 | M41: RI.2026.04.00136 | N41: FB260500164 | O41: No DP | P41: 110207.2026.06.00027
A42: 41 | B42: 46179 | C42: PO260600021 | D42: Sungkai | E42: Board | F42: UD. Divky Wood | G42: 4.171 | H42: 18643706 | I42: =IF(G42=0,0,H42/G42) -> 4469840.8 | J42: =IF(OR(tblIN[[#This Row],[Receipt No.]]="",tblIN[[#This Row],[Receipt No.]]="Not received"),"Not received","Received") -> Received | K42: =IF(OR(tblIN[[#This Row],[Payment No.]]="",tblIN[[#This Row],[Payment No.]]="Unpaid"),"Still on waiting Schedule Payment","Paid 100%") -> Paid 100% | L42: WOOD_PURCHASE SUNKAI row 16 | M42: RI.2026.06.00179 | N42: FB260700095 | O42: DP260600002 | P42: 110207.2026.07.00046
A43: 42 | B43: 46191 | C43: PO260600043 | D43: Sungkai | E43: Board | F43: H. Tasmo - Koperasi Albarokah | G43: =H43/5500000 -> 5.4258182 | H43: 29842000 | I43: =IF(G43=0,0,H43/G43) -> 5500000 | J43: =IF(OR(tblIN[[#This Row],[Receipt No.]]="",tblIN[[#This Row],[Receipt No.]]="Not received"),"Not received","Received") -> Received | K43: =IF(OR(tblIN[[#This Row],[Payment No.]]="",tblIN[[#This Row],[Payment No.]]="Unpaid"),"Still on waiting Schedule Payment","Paid 100%") -> Paid 100% | L43: WOOD_PURCHASE SUNKAI row 18 | M43: RI.2026.08.00001 | N43: FB260700279 | O43: DP260600012 | P43: 110207.2026.08.00007
A44: 43 | B44: 46218 | C44: PO260700024 | D44: Sungkai | E44: Board | F44: CV. Buana Putra Persada | G44: 10 | H44: 58500000 | I44: =IF(G44=0,0,H44/G44) -> 5850000 | J44: =IF(OR(tblIN[[#This Row],[Receipt No.]]="",tblIN[[#This Row],[Receipt No.]]="Not received"),"Not received","Received") -> Received | K44: =IF(OR(tblIN[[#This Row],[Payment No.]]="",tblIN[[#This Row],[Payment No.]]="Unpaid"),"Still on waiting Schedule Payment","Paid 100%") -> Paid 100% | L44: WOOD_PURCHASE SUNKAI row 20 | M44: RI.2026.08.00160 | N44: FB260800194 | O44: DP260700004, DP260700011 | P44: 110207.2026.09.00006
A45: 44 | B45: 46240 | C45: PO260800001 | D45: Sungkai | E45: Board | F45: CV. Buana Putra Persada | G45: =6.9192+2.21435 -> 9.13355 | H45: 53694125 | I45: =IF(G45=0,0,H45/G45) -> 5878779.3 | J45: =IF(OR(tblIN[[#This Row],[Receipt No.]]="",tblIN[[#This Row],[Receipt No.]]="Not received"),"Not received","Received") -> Received | K45: =IF(OR(tblIN[[#This Row],[Payment No.]]="",tblIN[[#This Row],[Payment No.]]="Unpaid"),"Still on waiting Schedule Payment","Paid 100%") -> Paid 100% | L45: WOOD_PURCHASE SUNKAI row 26 | M45: RI.2026.09.00037 | N45: FB260900046 | O45: DP260800003, DP260800004 | P45: 110207.2026.09.00037
A46: 45 | B46: 46241 | C46: PO260800003 | D46: Sungkai | E46: Board | F46: H. Tasmo - Koperasi Albarokah | G46: =3.6951+1.1868+1.4754 -> 6.3573 | H46: 36812700 | I46: =IF(G46=0,0,H46/G46) -> 5790618.7 | J46: =IF(OR(tblIN[[#This Row],[Receipt No.]]="",tblIN[[#This Row],[Receipt No.]]="Not received"),"Not received","Received") -> Received | K46: =IF(OR(tblIN[[#This Row],[Payment No.]]="",tblIN[[#This Row],[Payment No.]]="Unpaid"),"Still on waiting Schedule Payment","Paid 100%") -> Paid 100% | L46: WOOD_PURCHASE SUNKAI row 23 | M46: RI.2026.08.00146 | N46: FB260800176 | O46: No DP | P46: 110207.2026.10.00010
A47: 46 | B47: 46283 | C47: PO260900015 | D47: Teak | E47: Board | F47: H. Tasmo - Koperasi Albarokah | G47: 1.1762 | H47: 16466800 | I47: =IF(G47=0,0,H47/G47) -> 14000000 | J47: =IF(OR(tblIN[[#This Row],[Receipt No.]]="",tblIN[[#This Row],[Receipt No.]]="Not received"),"Not received","Received") -> Received | K47: =IF(OR(tblIN[[#This Row],[Payment No.]]="",tblIN[[#This Row],[Payment No.]]="Unpaid"),"Still on waiting Schedule Payment","Paid 100%") -> Still on waiting Schedule Payment | L47: Accurate PO260900015 | M47: RI.2026.09.00076 | N47: FB260900098 | O47: No DP | P47: Unpaid
A48: 47 | B48: 46297 | C48: PO261000003 | D48: Pine | E48: Board | F48: PD. Jujur Jaya | G48: 0.9839 | H48: 3050090 | I48: =IF(G48=0,0,H48/G48) -> 3100000 | J48: =IF(OR(tblIN[[#This Row],[Receipt No.]]="",tblIN[[#This Row],[Receipt No.]]="Not received"),"Not received","Received") -> Received | K48: =IF(OR(tblIN[[#This Row],[Payment No.]]="",tblIN[[#This Row],[Payment No.]]="Unpaid"),"Still on waiting Schedule Payment","Paid 100%") -> Paid 100% | L48: Accurate PO261000003 | M48: RI.2026.10.00005 | N48: FB261000008 | O48: No DP | P48: 110207.2026.10.00030
A49: 48 | B49: 46302 | C49: PO261000012 | D49: Teak | E49: Board | F49: H. Tasmo - Koperasi Albarokah | G49: 3.3732 | H49: 25299000 | I49: =IF(G49=0,0,H49/G49) -> 7500000 | J49: =IF(OR(tblIN[[#This Row],[Receipt No.]]="",tblIN[[#This Row],[Receipt No.]]="Not received"),"Not received","Received") -> Received | K49: =IF(OR(tblIN[[#This Row],[Payment No.]]="",tblIN[[#This Row],[Payment No.]]="Unpaid"),"Still on waiting Schedule Payment","Paid 100%") -> Still on waiting Schedule Payment | L49: Accurate PO261000012 | M49: RI.2026.10.00022 | N49: FB261000029 | O49: No DP | P49: Unpaid
A50: 49 | B50: 46302 | C50: PO261000009 | D50: Teak | E50: Board | F50: Afwoodz | G50: 3.0467 | H50: 22850250 | I50: =IF(G50=0,0,H50/G50) -> 7500000 | J50: =IF(OR(tblIN[[#This Row],[Receipt No.]]="",tblIN[[#This Row],[Receipt No.]]="Not received"),"Not received","Received") -> Received | K50: =IF(OR(tblIN[[#This Row],[Payment No.]]="",tblIN[[#This Row],[Payment No.]]="Unpaid"),"Still on waiting Schedule Payment","Paid 100%") -> Paid 100% | L50: Accurate PO261000009 | M50: RI.2026.10.00023 | N50: FB261000030 | O50: No DP | P50: 110207.2026.10.00052
A51: 50 | C51: PO261000022 + PO261000024 | D51: Teak | E51: Board | F51: H. Tasmo - Koperasi Albarokah | G51: =1.894305+1.059765+1.997415 -> 4.951485 | H51: =22500000+15000000 -> 37500000 | I51: =IF(G51=0,0,H51/G51) -> 7573485.5 | J51: =IF(OR(tblIN[[#This Row],[Receipt No.]]="",tblIN[[#This Row],[Receipt No.]]="Not received"),"Not received","Received") -> Received | K51: =IF(OR(tblIN[[#This Row],[Payment No.]]="",tblIN[[#This Row],[Payment No.]]="Unpaid"),"Still on waiting Schedule Payment","Paid 100%") -> Still on waiting Schedule Payment | L51: Accurate PO261000022, PO261000024 | M51: Incomming 20-10-26 & 23-10-26 | O51: No DP
A52: Total | G52: =SUBTOTAL(109,tblIN[Volume (m³)]) -> 227.33927 | H52: =SUBTOTAL(109,tblIN[Value (Rp)]) -> 1.5128432e+09

Sheet INCOMING
A1: No. | B1: Date | C1: Wood Type | D1: Thickness (cm) | E1: Qty (pcs) | F1: Volume (m³) | G1: Supplier | H1: PO No. | I1: Source | J1: Notes
A2: 1 | B2: 46315 | C2: Teak | D2: 3.5 | E2: 201 | F2: 1.894305 | G2: H. Tasmo - Koperasi Albarokah | I2: 08_Teak Wood 2026 - By Nuriyanti (1).xlsx Incomming 20-10-26 | J2: 6 pcs without thickness; volume covers 195 pcs
A3: 2 | B3: 46318 | C3: Teak | D3: 3.5 | E3: 115 | F3: 1.059765 | G3: H. Tasmo - Koperasi Albarokah | I3: 08_Teak Wood 2026 - By Nuriyanti (1).xlsx Incomming 23-10-26 | J3: 1 pcs without thickness; volume covers 114 pcs
A4: 3 | B4: 46318 | C4: Teak | D4: 4.5 | E4: 123 | F4: 1.997415 | G4: H. Tasmo - Koperasi Albarokah | I4: 08_Teak Wood 2026 - By Nuriyanti (1).xlsx Incomming 23-10-26

Sheet POTENTIAL IN
A1: No. | B1: Tanggal PO | C1: No. PO | D1: Jenis Kayu | E1: Bentuk | F1: Supplier | G1: Volume (m³) | H1: Nilai (Rp) | I1: Harga per m³ (Rp) | J1: Status Barang | K1: Status Bayar | L1: Sumber | M1: No. Penerimaan | N1: No. Faktur (Accurate) | O1: No. Uang Muka | P1: No. Pembayaran

Sheet OUT
A1: Wood OUT
A4: Description | D4: Teak | E4: Sungkai | F4: Pine | G4: Total
A5: Wood received (m³) | D5: =SUMMARY!C17 -> 148.16234 | E5: =SUMMARY!D17 -> 78.193031 | F5: =SUMMARY!E17 -> 0.9839 | G5: =D5+E5+F5 -> 227.33927
A6: Stock balance (m³) | D6: =SUMMARY!C22 -> 16.12396 | E6: =SUMMARY!D22 -> 9.930121 | F6: =SUMMARY!E22 -> 0.12218 | G6: =D6+E6+F6 -> 26.176261
A7: Gross OUT (m³) | D7: =D5-D6 -> 132.03838 | E7: =E5-E6 -> 68.26291 | F7: =F5-F6 -> 0.86172 | G7: =D7+E7+F7 -> 201.16301
A8: Recorded cutting OUT (m³) | D8: =SUMIFS($F$14:$F$5086,$C$14:$C$5086,"Teak",$L$14:$L$5086,"<>Adjustment") -> 119.33777 | E8: =SUMIFS($F$14:$F$5086,$C$14:$C$5086,"Sungkai",$L$14:$L$5086,"<>Adjustment") -> 52.156448 | F8: =SUMIFS($F$14:$F$5086,$C$14:$C$5086,"Pine",$L$14:$L$5086,"<>Adjustment") -> 0.861745 | G8: =D8+E8+F8 -> 172.35596
A9: Adjustment without cutting record (m³) | D9: =D7-D8 -> 12.700605 | E9: =E7-E8 -> 16.106462 | F9: =F7-F8 -> -2.5e-05 | G9: =D9+E9+F9 -> 28.807042
A10: Recorded percentage | D10: =IF(D7=0,0,D8/D7) -> 0.90381126 | E10: =IF(E7=0,0,E8/E7) -> 0.76405252 | F10: =IF(F7=0,0,F8/F7) -> 1.000029 | G10: =IF(G7=0,0,G8/G7) -> 0.85679752
A13: No. | B13: Date | C13: Wood Type | D13: Thickness (cm) | E13: Qty (pcs) | F13: Volume (m³) | G13: MO No. | H13: Customer | I13: Product | J13: Category | K13: Source | L13: Notes | M13: Sample SPK | N13: Ref Adj | O13: Remaining Adj (m³) | P13: Adj Class
A14: 1 | B14: 46041 | C14: Teak | F14: 0.28086 | G14: 096E/EVI/092025 | H14: =IFERROR(INDEX(REALDATA!$C$2:$C$1048576,MATCH(G14,REALDATA!$B$2:$B$1048576,0)),"131/CR") -> 131/CR | I14: Rose Chair Teak Wood Seat | J14: Production | K14: TEAK_USAGE Mutation Teak row 6 | O14: =IF(AND(L14="Adjustment",N14="",P14<>"Explained"),F14+SUMIFS($F$14:$F$5084,$N$14:$N$5084,A14,$L$14:$L$5084,"Adjustment"),"")
A15: 2 | B15: 46041 | C15: Teak | F15: 0.4681 | G15: 109E/EVI/112025 | H15: =IFERROR(INDEX(REALDATA!$C$2:$C$1048576,MATCH(G15,REALDATA!$B$2:$B$1048576,0)),"125/FJ") -> 125/FJ | I15: Rose Chair Teak Wood Seat | J15: Production | K15: TEAK_USAGE Mutation Teak row 7 | O15: =IF(AND(L15="Adjustment",N15="",P15<>"Explained"),F15+SUMIFS($F$14:$F$5084,$N$14:$N$5084,A15,$L$14:$L$5084,"Adjustment"),"")
A16: 3 | B16: 46041 | C16: Teak | F16: 0.41909 | G16: 107E/EVI/112025 | H16: =IFERROR(INDEX(REALDATA!$C$2:$C$1048576,MATCH(G16,REALDATA!$B$2:$B$1048576,0)),"079/IL") -> 079/IL | I16: Komodo & strap chair | J16: Production | K16: TEAK_USAGE Mutation Teak row 8 | O16: =IF(AND(L16="Adjustment",N16="",P16<>"Explained"),F16+SUMIFS($F$14:$F$5084,$N$14:$N$5084,A16,$L$14:$L$5084,"Adjustment"),"")
A17: 4 | B17: 46041 | C17: Teak | F17: 0.11433 | G17: 096E/EVI/092025 | H17: =IFERROR(INDEX(REALDATA!$C$2:$C$1048576,MATCH(G17,REALDATA!$B$2:$B$1048576,0)),"131/CR") -> 131/CR | I17: New Lego Chair Indoor Cushion | J17: Production | K17: TEAK_USAGE Mutation Teak row 9 | O17: =IF(AND(L17="Adjustment",N17="",P17<>"Explained"),F17+SUMIFS($F$14:$F$5084,$N$14:$N$5084,A17,$L$14:$L$5084,"Adjustment"),"")
A18: 5 | B18: 46041 | C18: Teak | F18: 0.19055 | G18: 107E/EVI/112025 | H18: =IFERROR(INDEX(REALDATA!$C$2:$C$1048576,MATCH(G18,REALDATA!$B$2:$B$1048576,0)),"079/IL") -> 079/IL | I18: New Lego Chair Indoor Cushion | J18: Production | K18: TEAK_USAGE Mutation Teak row 10 | O18: =IF(AND(L18="Adjustment",N18="",P18<>"Explained"),F18+SUMIFS($F$14:$F$5084,$N$14:$N$5084,A18,$L$14:$L$5084,"Adjustment"),"")
A19: 6 | B19: 46041 | C19: Teak | F19: 0.13684 | G19: 107E/EVI/112025 | H19: =IFERROR(INDEX(REALDATA!$C$2:$C$1048576,MATCH(G19,REALDATA!$B$2:$B$1048576,0)),"079/IL") -> 079/IL | I19: Wishbone Chair Natural | J19: Production | K19: TEAK_USAGE Mutation Teak row 11 | O19: =IF(AND(L19="Adjustment",N19="",P19<>"Explained"),F19+SUMIFS($F$14:$F$5084,$N$14:$N$5084,A19,$L$14:$L$5084,"Adjustment"),"")
A20: 7 | B20: 46042 | C20: Teak | F20: 0.1015 | G20: 107E/EVI/112025 | H20: =IFERROR(INDEX(REALDATA!$C$2:$C$1048576,MATCH(G20,REALDATA!$B$2:$B$1048576,0)),"079/IL") -> 079/IL | I20: Pumpkin Lantern (L) | J20: Production | K20: TEAK_USAGE Mutation Teak row 12 | O20: =IF(AND(L20="Adjustment",N20="",P20<>"Explained"),F20+SUMIFS($F$14:$F$5084,$N$14:$N$5084,A20,$L$14:$L$5084,"Adjustment"),"")
A21: 8 | B21: 46050 | C21: Teak | F21: 0.14031 | G21: 096E/EVI/092025 | H21: =IFERROR(INDEX(REALDATA!$C$2:$C$1048576,MATCH(G21,REALDATA!$B$2:$B$1048576,0)),"131/CR") -> 131/CR | I21: Citrus Lounge Chair Teak | J21: Production | K21: TEAK_USAGE Mutation Teak row 13 | O21: =IF(AND(L21="Adjustment",N21="",P21<>"Explained"),F21+SUMIFS($F$14:$F$5084,$N$14:$N$5084,A21,$L$14:$L$5084,"Adjustment"),"")
A22: 9 | B22: 46050 | C22: Teak | F22: 0.16130812 | G22: 096E/EVI/092025 | H22: =IFERROR(INDEX(REALDATA!$C$2:$C$1048576,MATCH(G22,REALDATA!$B$2:$B$1048576,0)),"131/CR") -> 131/CR | I22: Mona Chair Teak with Cushion | J22: Production | K22: TEAK_USAGE Mutation Teak row 14 | O22: =IF(AND(L22="Adjustment",N22="",P22<>"Explained"),F22+SUMIFS($F$14:$F$5084,$N$14:$N$5084,A22,$L$14:$L$5084,"Adjustment"),"")
A23: 10 | B23: 46050 | C23: Teak | F23: 0.26884687 | G23: 109E/EVI/112025 | H23: =IFERROR(INDEX(REALDATA!$C$2:$C$1048576,MATCH(G23,REALDATA!$B$2:$B$1048576,0)),"125/FJ") -> 125/FJ | I23: Mona Chair Teak with Cushion | J23: Production | K23: TEAK_USAGE Mutation Teak row 15 | O23: =IF(AND(L23="Adjustment",N23="",P23<>"Explained"),F23+SUMIFS($F$14:$F$5084,$N$14:$N$5084,A23,$L$14:$L$5084,"Adjustment"),"")
A24: 11 | B24: 46050 | C24: Teak | F24: 0.58186 | G24: 109E/EVI/112025 | H24: =IFERROR(INDEX(REALDATA!$C$2:$C$1048576,MATCH(G24,REALDATA!$B$2:$B$1048576,0)),"125/FJ") -> 125/FJ | I24: Manhattan Chair Teak Webbing Seater | J24: Production | K24: TEAK_USAGE Mutation Teak row 16 | O24: =IF(AND(L24="Adjustment",N24="",P24<>"Explained"),F24+SUMIFS($F$14:$F$5084,$N$14:$N$5084,A24,$L$14:$L$5084,"Adjustment"),"")
A25: 12 | B25: 46056 | C25: Teak | F25: 0.24447 | G25: 109E/EVI/112025 | H25: =IFERROR(INDEX(REALDATA!$C$2:$C$1048576,MATCH(G25,REALDATA!$B$2:$B$1048576,0)),"125/FJ") -> 125/FJ | I25: Manhattan Chair Teak Webbing Seater | J25: Production | K25: TEAK_USAGE Mutation Teak row 17 | O25: =IF(AND(L25="Adjustment",N25="",P25<>"Explained"),F25+SUMIFS($F$14:$F$5084,$N$14:$N$5084,A25,$L$14:$L$5084,"Adjustment"),"")
A26: 13 | B26: 46056 | C26: Teak | F26: 0.360275 | G26: 109E/EVI/112025 | H26: =IFERROR(INDEX(REALDATA!$C$2:$C$1048576,MATCH(G26,REALDATA!$B$2:$B$1048576,0)),"125/FJ") -> 125/FJ | I26: Provence Chair Teak with Cushion | J26: Production | K26: TEAK_USAGE Mutation Teak row 18 | O26: =IF(AND(L26="Adjustment",N26="",P26<>"Explained"),F26+SUMIFS($F$14:$F$5084,$N$14:$N$5084,A26,$L$14:$L$5084,"Adjustment"),"")
A27: 14 | B27: 46056 | C27: Teak | F27: 0.29599 | G27: Sample | H27: Sample | I27: Sample | J27: Sample | K27: TEAK_USAGE Mutation Teak row 19 | O27: =IF(AND(L27="Adjustment",N27="",P27<>"Explained"),F27+SUMIFS($F$14:$F$5084,$N$14:$N$5084,A27,$L$14:$L$5084,"Adjustment"),"")
A28: 15 | B28: 46058 | C28: Teak | F28: 0.10764187 | G28: 096E/EVI/092025 | H28: =IFERROR(INDEX(REALDATA!$C$2:$C$1048576,MATCH(G28,REALDATA!$B$2:$B$1048576,0)),"131/CR") -> 131/CR | I28: Rose Chair Teak Wood Seat | J28: Production | K28: TEAK_USAGE Mutation Teak row 20 | O28: =IF(AND(L28="Adjustment",N28="",P28<>"Explained"),F28+SUMIFS($F$14:$F$5084,$N$14:$N$5084,A28,$L$14:$L$5084,"Adjustment"),"")
A29: 16 | B29: 46058 | C29: Teak | F29: 0.17940312 | G29: 109E/EVI/112025 | H29: =IFERROR(INDEX(REALDATA!$C$2:$C$1048576,MATCH(G29,REALDATA!$B$2:$B$1048576,0)),"125/FJ") -> 125/FJ | I29: Rose Chair Teak Wood Seat | J29: Production | K29: TEAK_USAGE Mutation Teak row 21 | O29: =IF(AND(L29="Adjustment",N29="",P29<>"Explained"),F29+SUMIFS($F$14:$F$5084,$N$14:$N$5084,A29,$L$14:$L$5084,"Adjustment"),"")
A30: 17 | B30: 46058 | C30: Teak | F30: 0.046165 | G30: Sample | H30: Sample | I30: Development | J30: Sample | K30: TEAK_USAGE Mutation Teak row 22 | O30: =IF(AND(L30="Adjustment",N30="",P30<>"Explained"),F30+SUMIFS($F$14:$F$5084,$N$14:$N$5084,A30,$L$14:$L$5084,"Adjustment"),"")
A31: 18 | B31: 46063 | C31: Teak | F31: 0.38383 | G31: 096E/EVI/092025 | H31: =IFERROR(INDEX(REALDATA!$C$2:$C$1048576,MATCH(G31,REALDATA!$B$2:$B$1048576,0)),"131/CR") -> 131/CR | I31: Flevo Counterstool | J31: Production | K31: TEAK_USAGE Mutation Teak row 23 | O31: =IF(AND(L31="Adjustment",N31="",P31<>"Explained"),F31+SUMIFS($F$14:$F$5084,$N$14:$N$5084,A31,$L$14:$L$5084,"Adjustment"),"")
A32: 19 | B32: 46063 | C32: Teak | F32: 0.02592 | G32: 109E/EVI/112025 | H32: =IFERROR(INDEX(REALDATA!$C$2:$C$1048576,MATCH(G32,REALDATA!$B$2:$B$1048576,0)),"125/FJ") -> 125/FJ | I32: Manhattan Chair Teak Webbing Seater | J32: Production | K32: TEAK_USAGE Mutation Teak row 24 | O32: =IF(AND(L32="Adjustment",N32="",P32<>"Explained"),F32+SUMIFS($F$14:$F$5084,$N$14:$N$5084,A32,$L$14:$L$5084,"Adjustment"),"")
A33: 20 | B33: 46063 | C33: Teak | F33: 0.0387225 | G33: 096E/EVI/092025 | H33: =IFERROR(INDEX(REALDATA!$C$2:$C$1048576,MATCH(G33,REALDATA!$B$2:$B$1048576,0)),"131/CR") -> 131/CR | I33: Rose Chair Teak Wood Seat | J33: Production | K33: TEAK_USAGE Mutation Teak row 25 | O33: =IF(AND(L33="Adjustment",N33="",P33<>"Explained"),F33+SUMIFS($F$14:$F$5084,$N$14:$N$5084,A33,$L$14:$L$5084,"Adjustment"),"")
A34: 21 | B34: 46063 | C34: Teak | F34: 0.0645375 | G34: 109E/EVI/112025 | H34: =IFERROR(INDEX(REALDATA!$C$2:$C$1048576,MATCH(G34,REALDATA!$B$2:$B$1048576,0)),"125/FJ") -> 125/FJ | I34: Rose Chair Teak Wood Seat | J34: Production | K34: TEAK_USAGE Mutation Teak row 26 | O34: =IF(AND(L34="Adjustment",N34="",P34<>"Explained"),F34+SUMIFS($F$14:$F$5084,$N$14:$N$5084,A34,$L$14:$L$5084,"Adjustment"),"")
A35: 22 | B35: 46063 | C35: Teak | F35: 0.02568 | G35: 109E/EVI/112025 | H35: =IFERROR(INDEX(REALDATA!$C$2:$C$1048576,MATCH(G35,REALDATA!$B$2:$B$1048576,0)),"125/FJ") -> 125/FJ | I35: Provence Chair Teak with Cushion | J35: Production | K35: TEAK_USAGE Mutation Teak row 27 | O35: =IF(AND(L35="Adjustment",N35="",P35<>"Explained"),F35+SUMIFS($F$14:$F$5084,$N$14:$N$5084,A35,$L$14:$L$5084,"Adjustment"),"")
A36: 23 | B36: 46067 | C36: Teak | F36: 0.38276 | G36: 109E/EVI/112025 | H36: =IFERROR(INDEX(REALDATA!$C$2:$C$1048576,MATCH(G36,REALDATA!$B$2:$B$1048576,0)),"125/FJ") -> 125/FJ | I36: Baobab Dining Table D120 | J36: Production | K36: TEAK_USAGE Mutation Teak row 28 | O36: =IF(AND(L36="Adjustment",N36="",P36<>"Explained"),F36+SUMIFS($F$14:$F$5084,$N$14:$N$5084,A36,$L$14:$L$5084,"Adjustment"),"")
A37: 24 | B37: 46067 | C37: Teak | F37: 0.23116 | G37: 107E/EVI/112025 | H37: =IFERROR(INDEX(REALDATA!$C$2:$C$1048576,MATCH(G37,REALDATA!$B$2:$B$1048576,0)),"079/IL") -> 079/IL | I37: New Lego Chair Indoor Cushion | J37: Production | K37: TEAK_USAGE Mutation Teak row 29 | O37: =IF(AND(L37="Adjustment",N37="",P37<>"Explained"),F37+SUMIFS($F$14:$F$5084,$N$14:$N$5084,A37,$L$14:$L$5084,"Adjustment"),"")
A38: 25 | B38: 46070 | C38: Teak | F38: 0.102555 | G38: Sample | H38: Sample | I38: Sample | J38: Sample | K38: TEAK_USAGE Mutation Teak row 30 | O38: =IF(AND(L38="Adjustment",N38="",P38<>"Explained"),F38+SUMIFS($F$14:$F$5084,$N$14:$N$5084,A38,$L$14:$L$5084,"Adjustment"),"")
A39: 26 | B39: 46070 | C39: Teak | F39: 0.49475 | G39: 109E/EVI/112025 | H39: =IFERROR(INDEX(REALDATA!$C$2:$C$1048576,MATCH(G39,REALDATA!$B$2:$B$1048576,0)),"125/FJ") -> 125/FJ | I39: Baobab Dining Table D120 | J39: Production | K39: TEAK_USAGE Mutation Teak row 31 | O39: =IF(AND(L39="Adjustment",N39="",P39<>"Explained"),F39+SUMIFS($F$14:$F$5084,$N$14:$N$5084,A39,$L$14:$L$5084,"Adjustment"),"")
A40: 27 | B40: 46070 | C40: Teak | F40: 0.285815 | G40: 096E/EVI/092025 | H40: =IFERROR(INDEX(REALDATA!$C$2:$C$1048576,MATCH(G40,REALDATA!$B$2:$B$1048576,0)),"131/CR") -> 131/CR | I40: Brazil Chair | J40: Production | K40: TEAK_USAGE Mutation Teak row 32 | O40: =IF(AND(L40="Adjustment",N40="",P40<>"Explained"),F40+SUMIFS($F$14:$F$5084,$N$14:$N$5084,A40,$L$14:$L$5084,"Adjustment"),"")
A41: 28 | B41: 46070 | C41: Teak | F41: 0.16148 | G41: 126E/EVI/122025 | H41: =IFERROR(INDEX(REALDATA!$C$2:$C$1048576,MATCH(G41,REALDATA!$B$2:$B$1048576,0)),"130/TR") -> 130/TR | I41: Acai Chair Teak with Peel Seater Cushion | J41: Production | K41: TEAK_USAGE Mutation Teak row 33 | O41: =IF(AND(L41="Adjustment",N41="",P41<>"Explained"),F41+SUMIFS($F$14:$F$5084,$N$14:$N$5084,A41,$L$14:$L$5084,"Adjustment"),"")
A42: 29 | B42: 46071 | C42: Teak | F42: 0.1861 | G42: Sample | H42: Sample | I42: Sample | J42: Sample | K42: TEAK_USAGE Mutation Teak row 34 | O42: =IF(AND(L42="Adjustment",N42="",P42<>"Explained"),F42+SUMIFS($F$14:$F$5084,$N$14:$N$5084,A42,$L$14:$L$5084,"Adjustment"),"")
A43: 30 | B43: 46071 | C43: Teak | F43: 0.19206 | G43: 096E/EVI/092025 | H43: =IFERROR(INDEX(REALDATA!$C$2:$C$1048576,MATCH(G43,REALDATA!$B$2:$B$1048576,0)),"131/CR") -> 131/CR | I43: Petra Dining Table Teak with Wood Top D90 | J43: Production | K43: TEAK_USAGE Mutation Teak row 35 | O43: =IF(AND(L43="Adjustment",N43="",P43<>"Explained"),F43+SUMIFS($F$14:$F$5084,$N$14:$N$5084,A43,$L$14:$L$5084,"Adjustment"),"")
A44: 31 | B44: 46071 | C44: Teak | F44: 0.16464 | G44: 096E/EVI/092025 | H44: =IFERROR(INDEX(REALDATA!$C$2:$C$1048576,MATCH(G44,REALDATA!$B$2:$B$1048576,0)),"131/CR") -> 131/CR | I44: Shelby Chair Teak | J44: Production | K44: TEAK_USAGE Mutation Teak row 36 | O44: =IF(AND(L44="Adjustment",N44="",P44<>"Explained"),F44+SUMIFS($F$14:$F$5084,$N$14:$N$5084,A44,$L$14:$L$5084,"Adjustment"),"")
A45: 32 | B45: 46072 | C45: Teak | F45: 0.17501 | G45: 126E/EVI/122025 | H45: =IFERROR(INDEX(REALDATA!$C$2:$C$1048576,MATCH(G45,REALDATA!$B$2:$B$1048576,0)),"130/TR") -> 130/TR | I45: Acai Chair Teak with Peel Seater Cushion | J45: Production | K45: TEAK_USAGE Mutation Teak row 37 | O45: =IF(AND(L45="Adjustment",N45="",P45<>"Explained"),F45+SUMIFS($F$14:$F$5084,$N$14:$N$5084,A45,$L$14:$L$5084,"Adjustment"),"")
A46: 33 | B46: 46073 | C46: Teak | F46: 0.30846 | G46: 109E/EVI/112025 | H46: =IFERROR(INDEX(REALDATA!$C$2:$C$1048576,MATCH(G46,REALDATA!$B$2:$B$1048576,0)),"125/FJ") -> 125/FJ | I46: Prague Dining Rectangular 150 | J46: Production | K46: TEAK_USAGE Mutation Teak row 38 | O46: =IF(AND(L46="Adjustment",N46="",P46<>"Explained"),F46+SUMIFS($F$14:$F$5084,$N$14:$N$5084,A46,$L$14:$L$5084,"Adjustment"),"")
A47: 34 | B47: 46074 | C47: Teak | F47: 0.05304 | G47: 096E/EVI/092025 | H47: =IFERROR(INDEX(REALDATA!$C$2:$C$1048576,MATCH(G47,REALDATA!$B$2:$B$1048576,0)),"131/CR") -> 131/CR | I47: Shelby Chair Teak | J47: Production | K47: TEAK_USAGE Mutation Teak row 39 | O47: =IF(AND(L47="Adjustment",N47="",P47<>"Explained"),F47+SUMIFS($F$14:$F$5084,$N$14:$N$5084,A47,$L$14:$L$5084,"Adjustment"),"")
A48: 35 | B48: 46074 | C48: Teak | F48: 0.05222 | G48: 096E/EVI/092025 | H48: =IFERROR(INDEX(REALDATA!$C$2:$C$1048576,MATCH(G48,REALDATA!$B$2:$B$1048576,0)),"131/CR") -> 131/CR | I48: Citrus Lounge Chair Teak | J48: Production | K48: TEAK_USAGE Mutation Teak row 40 | O48: =IF(AND(L48="Adjustment",N48="",P48<>"Explained"),F48+SUMIFS($F$14:$F$5084,$N$14:$N$5084,A48,$L$14:$L$5084,"Adjustment"),"")
A49: 36 | B49: 46076 | C49: Teak | F49: 0.39314 | G49: 096E/EVI/092025 | H49: =IFERROR(INDEX(REALDATA!$C$2:$C$1048576,MATCH(G49,REALDATA!$B$2:$B$1048576,0)),"131/CR") -> 131/CR | I49: New Lego Sofa Indoor Cushion | J49: Production | K49: TEAK_USAGE Mutation Teak row 41 | O49: =IF(AND(L49="Adjustment",N49="",P49<>"Explained"),F49+SUMIFS($F$14:$F$5084,$N$14:$N$5084,A49,$L$14:$L$5084,"Adjustment"),"")
A50: 37 | B50: 46076 | C50: Teak | F50: 0.108945 | G50: Sample | H50: Sample | I50: Sample | J50: Sample | K50: TEAK_USAGE Mutation Teak row 42 | O50: =IF(AND(L50="Adjustment",N50="",P50<>"Explained"),F50+SUMIFS($F$14:$F$5084,$N$14:$N$5084,A50,$L$14:$L$5084,"Adjustment"),"")
A51: 38 | B51: 46076 | C51: Teak | F51: 0.32919 | G51: 006E/EVI/012026 | H51: =IFERROR(INDEX(REALDATA!$C$2:$C$1048576,MATCH(G51,REALDATA!$B$2:$B$1048576,0)),"041/TD") -> 041/TD | I51: Strap Dining Chair Light Brown Suede | J51: Production | K51: TEAK_USAGE Mutation Teak row 43 | O51: =IF(AND(L51="Adjustment",N51="",P51<>"Explained"),F51+SUMIFS($F$14:$F$5084,$N$14:$N$5084,A51,$L$14:$L$5084,"Adjustment"),"")
A52: 39 | B52: 46077 | C52: Teak | F52: 0.053515 | G52: Sample | H52: Sample | I52: Development | J52: Sample | K52: TEAK_USAGE Mutation Teak row 44 | O52: =IF(AND(L52="Adjustment",N52="",P52<>"Explained"),F52+SUMIFS($F$14:$F$5084,$N$14:$N$5084,A52,$L$14:$L$5084,"Adjustment"),"")
A53: 40 | B53: 46077 | C53: Teak | F53: 0.06236 | G53: Sample | H53: Sample | I53: Sample | J53: Sample | K53: TEAK_USAGE Mutation Teak row 45 | O53: =IF(AND(L53="Adjustment",N53="",P53<>"Explained"),F53+SUMIFS($F$14:$F$5084,$N$14:$N$5084,A53,$L$14:$L$5084,"Adjustment"),"")
A54: 41 | B54: 46077 | C54: Teak | F54: 0.06822 | G54: 109E/EVI/112025 | H54: =IFERROR(INDEX(REALDATA!$C$2:$C$1048576,MATCH(G54,REALDATA!$B$2:$B$1048576,0)),"125/FJ") -> 125/FJ | I54: Rose Chair Teak Wood Seat | J54: Production | K54: TEAK_USAGE Mutation Teak row 46 | O54: =IF(AND(L54="Adjustment",N54="",P54<>"Explained"),F54+SUMIFS($F$14:$F$5084,$N$14:$N$5084,A54,$L$14:$L$5084,"Adjustment"),"")
A55: 42 | B55: 46077 | C55: Teak | F55: 0.14112 | G55: 096E/EVI/092025 | H55: =IFERROR(INDEX(REALDATA!$C$2:$C$1048576,MATCH(G55,REALDATA!$B$2:$B$1048576,0)),"131/CR") -> 131/CR | I55: New Lego Sofa Indoor Cushion | J55: Production | K55: TEAK_USAGE Mutation Teak row 47 | O55: =IF(AND(L55="Adjustment",N55="",P55<>"Explained"),F55+SUMIFS($F$14:$F$5084,$N$14:$N$5084,A55,$L$14:$L$5084,"Adjustment"),"")
A56: 43 | B56: 46077 | C56: Teak | F56: 0.1244 | G56: 096E/EVI/092025 | H56: =IFERROR(INDEX(REALDATA!$C$2:$C$1048576,MATCH(G56,REALDATA!$B$2:$B$1048576,0)),"131/CR") -> 131/CR | I56: Orchid Dining Table Teak with Wood Top D120 | J56: Production | K56: TEAK_USAGE Mutation Teak row 48 | O56: =IF(AND(L56="Adjustment",N56="",P56<>"Explained"),F56+SUMIFS($F$14:$F$5084,$N$14:$N$5084,A56,$L$14:$L$5084,"Adjustment"),"")
A57: 44 | B57: 46077 | C57: Teak | F57: 0.04911 | G57: 109E/EVI/112025 | H57: =IFERROR(INDEX(REALDATA!$C$2:$C$1048576,MATCH(G57,REALDATA!$B$2:$B$1048576,0)),"125/FJ") -> 125/FJ | I57: Baobab Dining Table D120 | J57: Production | K57: TEAK_USAGE Mutation Teak row 49 | O57: =IF(AND(L57="Adjustment",N57="",P57<>"Explained"),F57+SUMIFS($F$14:$F$5084,$N$14:$N$5084,A57,$L$14:$L$5084,"Adjustment"),"")
A58: 45 | B58: 46078 | C58: Teak | F58: 0.113 | G58: 096E/EVI/092025 | H58: =IFERROR(INDEX(REALDATA!$C$2:$C$1048576,MATCH(G58,REALDATA!$B$2:$B$1048576,0)),"131/CR") -> 131/CR | I58: Orchid Dining Table Teak with Wood Top D120 | J58: Production | K58: TEAK_USAGE Mutation Teak row 50 | O58: =IF(AND(L58="Adjustment",N58="",P58<>"Explained"),F58+SUMIFS($F$14:$F$5084,$N$14:$N$5084,A58,$L$14:$L$5084,"Adjustment"),"")
A59: 46 | B59: 46078 | C59: Teak | F59: 0.39192 | G59: 096E/EVI/092025 | H59: =IFERROR(INDEX(REALDATA!$C$2:$C$1048576,MATCH(G59,REALDATA!$B$2:$B$1048576,0)),"131/CR") -> 131/CR | I59: Petra Dining Table Teak with Wood Top D90 | J59: Production | K59: TEAK_USAGE Mutation Teak row 51 | O59: =IF(AND(L59="Adjustment",N59="",P59<>"Explained"),F59+SUMIFS($F$14:$F$5084,$N$14:$N$5084,A59,$L$14:$L$5084,"Adjustment"),"")
A60: 47 | B60: 46078 | C60: Teak | F60: 0.04611 | G60: 109E/EVI/112025 | H60: =IFERROR(INDEX(REALDATA!$C$2:$C$1048576,MATCH(G60,REALDATA!$B$2:$B$1048576,0)),"125/FJ") -> 125/FJ | I60: Provence Chair Teak with Cushion | J60: Production | K60: TEAK_USAGE Mutation Teak row 52 | O60: =IF(AND(L60="Adjustment",N60="",P60<>"Explained"),F60+SUMIFS($F$14:$F$5084,$N$14:$N$5084,A60,$L$14:$L$5084,"Adjustment"),"")
A61: 48 | B61: 46078 | C61: Teak | F61: 0.23638 | G61: Sample | H61: Sample | I61: Sample | J61: Sample | K61: TEAK_USAGE Mutation Teak row 53 | O61: =IF(AND(L61="Adjustment",N61="",P61<>"Explained"),F61+SUMIFS($F$14:$F$5084,$N$14:$N$5084,A61,$L$14:$L$5084,"Adjustment"),"")
A62: 49 | B62: 46078 | C62: Teak | F62: 0.12393 | G62: 109E/EVI/112025 | H62: =IFERROR(INDEX(REALDATA!$C$2:$C$1048576,MATCH(G62,REALDATA!$B$2:$B$1048576,0)),"125/FJ") -> 125/FJ | I62: Xavier DT | J62: Production | K62: TEAK_USAGE Mutation Teak row 54 | O62: =IF(AND(L62="Adjustment",N62="",P62<>"Explained"),F62+SUMIFS($F$14:$F$5084,$N$14:$N$5084,A62,$L$14:$L$5084,"Adjustment"),"")
A63: 50 | B63: 46080 | C63: Teak | F63: 0.21186 | G63: 006E/EVI/012026 | H63: =IFERROR(INDEX(REALDATA!$C$2:$C$1048576,MATCH(G63,REALDATA!$B$2:$B$1048576,0)),"041/TD") -> 041/TD | I63: Strap Dining Chair Light Brown Suede | J63: Production | K63: TEAK_USAGE Mutation Teak row 55 | O63: =IF(AND(L63="Adjustment",N63="",P63<>"Explained"),F63+SUMIFS($F$14:$F$5084,$N$14:$N$5084,A63,$L$14:$L$5084,"Adjustment"),"")
A64: 51 | B64: 46080 | C64: Teak | F64: 0.107055 | G64: 096E/EVI/092025 | H64: =IFERROR(INDEX(REALDATA!$C$2:$C$1048576,MATCH(G64,REALDATA!$B$2:$B$1048576,0)),"131/CR") -> 131/CR | I64: Petra Dining Table Teak with Wood Top D90 | J64: Production | K64: TEAK_USAGE Mutation Teak row 56 | O64: =IF(AND(L64="Adjustment",N64="",P64<>"Explained"),F64+SUMIFS($F$14:$F$5084,$N$14:$N$5084,A64,$L$14:$L$5084,"Adjustment"),"")
A65: 52 | B65: 46083 | C65: Teak | F65: 0.12159 | G65: 109E/EVI/112025 | H65: =IFERROR(INDEX(REALDATA!$C$2:$C$1048576,MATCH(G65,REALDATA!$B$2:$B$1048576,0)),"125/FJ") -> 125/FJ | I65: Baobab Dining Table D120 | J65: Production | K65: TEAK_USAGE Mutation Teak row 57 | O65: =IF(AND(L65="Adjustment",N65="",P65<>"Explained"),F65+SUMIFS($F$14:$F$5084,$N$14:$N$5084,A65,$L$14:$L$5084,"Adjustment"),"")
A66: 53 | B66: 46083 | C66: Teak | F66: 0.07315 | G66: 109E/EVI/112025 | H66: =IFERROR(INDEX(REALDATA!$C$2:$C$1048576,MATCH(G66,REALDATA!$B$2:$B$1048576,0)),"125/FJ") -> 125/FJ | I66: Prague Dining Rectangular 150 | J66: Production | K66: TEAK_USAGE Mutation Teak row 58 | O66: =IF(AND(L66="Adjustment",N66="",P66<>"Explained"),F66+SUMIFS($F$14:$F$5084,$N$14:$N$5084,A66,$L$14:$L$5084,"Adjustment"),"")
A67: 54 | B67: 46083 | C67: Teak | F67: 0.05268 | G67: Sample | H67: Sample | I67: Development | J67: Sample | K67: TEAK_USAGE Mutation Teak row 59 | O67: =IF(AND(L67="Adjustment",N67="",P67<>"Explained"),F67+SUMIFS($F$14:$F$5084,$N$14:$N$5084,A67,$L$14:$L$5084,"Adjustment"),"")
A68: 55 | B68: 46083 | C68: Teak | F68: 0.037665 | G68: Sample | H68: Sample | I68: Sample | J68: Sample | K68: TEAK_USAGE Mutation Teak row 60 | O68: =IF(AND(L68="Adjustment",N68="",P68<>"Explained"),F68+SUMIFS($F$14:$F$5084,$N$14:$N$5084,A68,$L$14:$L$5084,"Adjustment"),"")
A69: 56 | B69: 46083 | C69: Teak | F69: 0.12207 | G69: 006E/EVI/012026 | H69: =IFERROR(INDEX(REALDATA!$C$2:$C$1048576,MATCH(G69,REALDATA!$B$2:$B$1048576,0)),"041/TD") -> 041/TD | I69: Strap Dining Chair Light Brown Suede | J69: Production | K69: TEAK_USAGE Mutation Teak row 61 | O69: =IF(AND(L69="Adjustment",N69="",P69<>"Explained"),F69+SUMIFS($F$14:$F$5084,$N$14:$N$5084,A69,$L$14:$L$5084,"Adjustment"),"")
A70: 57 | B70: 46083 | C70: Teak | F70: 0.55013 | G70: 109E/EVI/112025 | H70: =IFERROR(INDEX(REALDATA!$C$2:$C$1048576,MATCH(G70,REALDATA!$B$2:$B$1048576,0)),"125/FJ") -> 125/FJ | I70: Xavier DT | J70: Production | K70: TEAK_USAGE Mutation Teak row 62 | O70: =IF(AND(L70="Adjustment",N70="",P70<>"Explained"),F70+SUMIFS($F$14:$F$5084,$N$14:$N$5084,A70,$L$14:$L$5084,"Adjustment"),"")
A71: 58 | B71: 46085 | C71: Teak | F71: 0.2824 | G71: 006E/EVI/012026 | H71: =IFERROR(INDEX(REALDATA!$C$2:$C$1048576,MATCH(G71,REALDATA!$B$2:$B$1048576,0)),"041/TD") -> 041/TD | I71: Strap Dining Chair Light Brown Suede | J71: Production | K71: TEAK_USAGE Mutation Teak row 63 | O71: =IF(AND(L71="Adjustment",N71="",P71<>"Explained"),F71+SUMIFS($F$14:$F$5084,$N$14:$N$5084,A71,$L$14:$L$5084,"Adjustment"),"")
A72: 59 | B72: 46085 | C72: Teak | F72: 0.80529 | G72: 109E/EVI/112025 | H72: =IFERROR(INDEX(REALDATA!$C$2:$C$1048576,MATCH(G72,REALDATA!$B$2:$B$1048576,0)),"125/FJ") -> 125/FJ | I72: Prague Dining Rectangular 150 | J72: Production | K72: TEAK_USAGE Mutation Teak row 64 | O72: =IF(AND(L72="Adjustment",N72="",P72<>"Explained"),F72+SUMIFS($F$14:$F$5084,$N$14:$N$5084,A72,$L$14:$L$5084,"Adjustment"),"")
A73: 60 | B73: 46085 | C73: Teak | F73: 0.10083 | G73: 109E/EVI/112025 | H73: =IFERROR(INDEX(REALDATA!$C$2:$C$1048576,MATCH(G73,REALDATA!$B$2:$B$1048576,0)),"125/FJ") -> 125/FJ | I73: Baobab Dining Table D120 | J73: Production | K73: TEAK_USAGE Mutation Teak row 65 | O73: =IF(AND(L73="Adjustment",N73="",P73<>"Explained"),F73+SUMIFS($F$14:$F$5084,$N$14:$N$5084,A73,$L$14:$L$5084,"Adjustment"),"")
A74: 61 | B74: 46087 | C74: Teak | F74: 0.117945 | G74: 109E/EVI/112025 | H74: =IFERROR(INDEX(REALDATA!$C$2:$C$1048576,MATCH(G74,REALDATA!$B$2:$B$1048576,0)),"125/FJ") -> 125/FJ | I74: Xavier DT | J74: Production | K74: TEAK_USAGE Mutation Teak row 66 | O74: =IF(AND(L74="Adjustment",N74="",P74<>"Explained"),F74+SUMIFS($F$14:$F$5084,$N$14:$N$5084,A74,$L$14:$L$5084,"Adjustment"),"")
A75: 62 | B75: 46089 | C75: Teak | F75: 0.30168 | G75: 109E/EVI/112025 | H75: =IFERROR(INDEX(REALDATA!$C$2:$C$1048576,MATCH(G75,REALDATA!$B$2:$B$1048576,0)),"125/FJ") -> 125/FJ | I75: Erik Dining Table 180 | J75: Production | K75: TEAK_USAGE Mutation Teak row 67 | O75: =IF(AND(L75="Adjustment",N75="",P75<>"Explained"),F75+SUMIFS($F$14:$F$5084,$N$14:$N$5084,A75,$L$14:$L$5084,"Adjustment"),"")
A76: 63 | B76: 46089 | C76: Teak | F76: 0.121135 | G76: 006E/EVI/012026 | H76: =IFERROR(INDEX(REALDATA!$C$2:$C$1048576,MATCH(G76,REALDATA!$B$2:$B$1048576,0)),"041/TD") -> 041/TD | I76: Strap Dining Chair Light Brown Suede | J76: Production | K76: TEAK_USAGE Mutation Teak row 68 | O76: =IF(AND(L76="Adjustment",N76="",P76<>"Explained"),F76+SUMIFS($F$14:$F$5084,$N$14:$N$5084,A76,$L$14:$L$5084,"Adjustment"),"")
A77: 64 | B77: 46089 | C77: Teak | F77: 0.13932 | G77: 109E/EVI/112025 | H77: =IFERROR(INDEX(REALDATA!$C$2:$C$1048576,MATCH(G77,REALDATA!$B$2:$B$1048576,0)),"125/FJ") -> 125/FJ | I77: Prague Dining Rectangular 150 | J77: Production | K77: TEAK_USAGE Mutation Teak row 69 | O77: =IF(AND(L77="Adjustment",N77="",P77<>"Explained"),F77+SUMIFS($F$14:$F$5084,$N$14:$N$5084,A77,$L$14:$L$5084,"Adjustment"),"")
A78: 65 | B78: 46089 | C78: Teak | F78: 0.34464151 | G78: 115E-A/EVI/122025 | H78: =IFERROR(INDEX(REALDATA!$C$2:$C$1048576,MATCH(G78,REALDATA!$B$2:$B$1048576,0)),"001/RM") -> 001/RM | I78: Tropez | J78: Production | K78: TEAK_USAGE Mutation Teak row 70 | O78: =IF(AND(L78="Adjustment",N78="",P78<>"Explained"),F78+SUMIFS($F$14:$F$5084,$N$14:$N$5084,A78,$L$14:$L$5084,"Adjustment"),"")
A79: 66 | B79: 46089 | C79: Teak | F79: 0.020678491 | G79: 115E-B/EVI/122025 | H79: =IFERROR(INDEX(REALDATA!$C$2:$C$1048576,MATCH(G79,REALDATA!$B$2:$B$1048576,0)),"001/RM") -> 001/RM | I79: Tropez | J79: Production | K79: TEAK_USAGE Mutation Teak row 71 | O79: =IF(AND(L79="Adjustment",N79="",P79<>"Explained"),F79+SUMIFS($F$14:$F$5084,$N$14:$N$5084,A79,$L$14:$L$5084,"Adjustment"),"")
A80: 67 | B80: 46091 | C80: Teak | F80: 0.19534 | G80: 109E/EVI/112025 | H80: =IFERROR(INDEX(REALDATA!$C$2:$C$1048576,MATCH(G80,REALDATA!$B$2:$B$1048576,0)),"125/FJ") -> 125/FJ | I80: Prague Dining Rectangular 150 | J80: Production | K80: TEAK_USAGE Mutation Teak row 72 | O80: =IF(AND(L80="Adjustment",N80="",P80<>"Explained"),F80+SUMIFS($F$14:$F$5084,$N$14:$N$5084,A80,$L$14:$L$5084,"Adjustment"),"")
A81: 68 | B81: 46091 | C81: Teak | F81: 0.45023113 | G81: 115E-A/EVI/122025 | H81: =IFERROR(INDEX(REALDATA!$C$2:$C$1048576,MATCH(G81,REALDATA!$B$2:$B$1048576,0)),"001/RM") -> 001/RM | I81: Tropez | J81: Production | K81: TEAK_USAGE Mutation Teak row 73 | O81: =IF(AND(L81="Adjustment",N81="",P81<>"Explained"),F81+SUMIFS($F$14:$F$5084,$N$14:$N$5084,A81,$L$14:$L$5084,"Adjustment"),"")
